Workbook

Sheet Fee Breakdown by Entity
A1: Amicorp Self-Service Portal — Complete Entity Fee & Product Information
A2: Indicative fees only — subject to local office confirmation, client profile, complexity, and applicable taxes. Rows marked † have no line-item fee schedule; Setup and Annual totals shown. Filing Required = Yes where income tax or annual financial statements/regulatory return is required. Hourly rates: USD 100–750/hr where not otherwise specified.
A3: Entity Information | F3: Product Content | V3: Enrichment — Structure & Regulation | AD3: Setup Fee (One-off) | AP3: Annual Resposibility Fees (Recurring) | BD3: Reporting & Compliance (As Required) | BR3: Set-up Fee (on-off) | BT3: Set-up Fee (on-off) | BV3: Set-up Fee (on-off) | BX3: Set-up Fee (on-off) | BZ3: Set-up Fee (on-off) | CP3: FATCA / CRS / ESR / MDR Items | DB3: Hourly Rates
A4: Country | B4: LMT Member | C4: Service Type | D4: Entity / Product | E4: Currency | F4: Description | G4: Overview | H4: Setup Time | I4: Ongoing Compliance | J4: Benefit 1 | K4: Benefit 2 | L4: Benefit 3 | M4: Benefit 4 | N4: Ideal for 1 | O4: Ideal for 2 | P4: Ideal for 3 | Q4: Ideal for 4 | R4: Key Feature 1 | S4: Key Feature 2 | T4: Key Feature 3 | U4: Key Feature 4 | V4: Entity Type Category | W4: Legal Framework | X4: Liability Protection | Y4: Regulatory Body / Key Statute | Z4: Public Register | AA4: Min Shareholders | AB4: Typical Use Case | AC4: Risk / Restriction | AD4: Setup Fee | AE4: M/O | AF4: Incorporation Third Party Expenses | AG4: M/O | AH4: Tax identification code | AI4: M/O | AJ4: UBO classification and registry | AK4: M/O | AL4: Bank Account Opening with Amicorp Bank & Trust | AM4: M/O | AN4: Bank Account Opening Third Party Bank (retainer) | AO4: M/O | AP4: Corporate Director Fee | AQ4: M/O | AR4: Trustee Fee | AS4: M/O | AT4: Personal Director Fee | AU4: M/O | AV4: Registered Office Fee | AW4: M/O | AX4: Corporate Secretary Fee | AY4: M/O | AZ4: Government Fee | BA4: M/O | BB4: Regulatory Authority Fee | BC4: M/O | BD4: Accounting (Retainer) | BE4: M/O | BF4: Tax Filing (Retainer) | BG4: M/O | BH4: Annual General Meeting / Board Minutes | BI4: M/O | BJ4: Audit (External Auditors) | BK4: M/O | BL4: Compliance Fee | BM4: M/O | BN4: Economic Substance Filing | BO4: M/O | BP4: UBO Registry Filing | BQ4: M/O | BR4: Fund Formation (Retainer) | BS4: M/O | BT4: Fund Compartment Formation | BU4: M/O | BV4: Preparation of Private Placement Memorandum | BW4: M/O | BX4: Regulatory fees | BY4: M/O | BZ4: Fund Management Services | CA4: M/O | CB4: Fund Administration & NAV calculation | CC4: M/O | CD4: Registrar and transfer agent | CE4: M/O | CF4: Investor KYC and subscription | CG4: M/O | CH4: Fund Director | CI4: M/O | CJ4: Money Laundering Reporting Officer (Retainer) | CK4: M/O | CL4: Annual audit coordination (Retainer) | CM4: M/O | CN4: Financial Statements (Retainer) | CO4: M/O | CP4: FATCA/CRS classification (one-off) | CQ4: M/O | CR4: ESR classification (one-off): | CS4: M/O | CT4: ESR Annual Declaration: USD 125 (fees may vary subject to ESR classification) | CU4: M/O | CV4: ESR Annual Notification: USD 165 | CW4: M/O | CX4: Legal and Corporate work (Retainer) | CY4: M/O | CZ4: Accounting and tax filing (Retainer) | DA4: M/O | DB4: Hourly Rates (Legal & Accounting) | DC4: M/O | DD4: Disbursements (7.5%) | DE4: 3rd Sheet | DF4: 1stSheet | DG4: Check
A5: BAHAMAS | DE5: ##
A6: Bahamas | B6: Marvin Taylor | C6: Company | D6: Bahamas IBC | E6: USD | F6: International Business Company offering tax-neutral structure for international trade and investment holding. | G6: The Bahamas IBC is a entity structure regulated under local law and widely used by international clients of Amicorp. International Business Company offering tax-neutral structure for international trade and investment holding. Our local team manages incorporation, ongoing administration, accounting, and compliance so you can focus on commercial objectives instead of paperwork. | H6: 3-7 business days | I6: Annual return, financial statements filing, and economic substance / UBO declarations | J6: Established Bahamas legal framework familiar to investors, banks, and counterparties | K6: End-to-end Amicorp service: incorporation, registered office, directors, accounting, and reporting | L6: Treaty network and regulatory standing supporting cross-border investment and capital flows | M6: Single point of contact across 30+ jurisdictions for multi-entity group structures | N6: Holding investments into and out of Bahamas | O6: Group holding companies and intermediate SPVs | P6: Joint ventures and shareholder agreements | Q6: Operating subsidiaries with local market access | R6: Limited liability for shareholders | S6: Separate legal entity | T6: Flexible management structure | U6: Tax efficient | V6: IBC | W6: Common Law | X6: Full | Y6: Bahamas Registrar General International Business Companies Act 2000 | Z6: No | AA6: 1 | AB6: Cross-border holding of securities, IP, or real estate outside the Bahamas | AC6: Cannot trade within Bahamas; economic substance rules apply for certain activities | AD6: 1560 | AE6: M | AG6: O | AI6: N/A | AK6: N/A | AL6: 0 | AM6: M | AO6: N/A | AP6: 1560 | AQ6: O | AS6: N/A | AT6: — | AU6: O | AV6: 860 | AW6: M | AX6: 590 | AY6: M | AZ6: 350 | BA6: M | BC6: M | BD6: — | BE6: M | BF6: — | BG6: M | BI6: N/A | BK6: N/A | BM6: N/A | BO6: N/A | BQ6: N/A | BS6: N/A | BU6: N/A | BW6: N/A | BY6: N/A | CA6: N/A | CC6: N/A | CE6: N/A | CG6: N/A | CK6: N/A | CM6: N/A | CO6: N/A | CP6: 400 | CQ6: M | CR6: 300 | CS6: M | CT6: 125 | CU6: M | CW6: N/A | CY6: N/A | DA6: N/A | DB6: USD 100–750/hr (confirm with local office) | DC6: O | DD6: =ROUND(0.075*SUM(AD6,AF6,AH6,AJ6,AL6,AN6,AP6,AR6,AT6,AV6,AX6,AZ6,BB6,BR6,BT6,BV6,BX6,BZ6,CB6,CD6,CF6,CJ6,CL6,CN6,CP6,CR6,CT6,CV6,CX6,CZ6),0) -> 431 | DE6: Bahamas#Company#Bahamas IBC | DF6: =A6&"#"&C6&"#"&D6 -> Bahamas#Company#Bahamas IBC | DG6: =DE6=DF6 -> TRUE
A7: Bahamas | B7: Marvin Taylor | C7: Trust | D7: Bahamas Trust | E7: USD | F7: Discretionary or fixed trust structure for asset protection and succession planning. | G7: The Bahamas Trust is a trust structure regulated under local law and widely used by international clients of Amicorp. Discretionary or fixed trust structure for asset protection and succession planning. Our local team manages incorporation, ongoing administration, accounting, and compliance so you can focus on commercial objectives instead of paperwork. | H7: 5-10 business days | I7: Annual trustee review, beneficiary statements, FATCA/CRS reporting where applicable | J7: Established Bahamas legal framework familiar to investors, banks, and counterparties | K7: End-to-end Amicorp service: incorporation, registered office, directors, accounting, and reporting | L7: Treaty network and regulatory standing supporting cross-border investment and capital flows | M7: Single point of contact across 30+ jurisdictions for multi-entity group structures | N7: High-net-worth families consolidating assets across jurisdictions | O7: Succession and inheritance planning for global families | P7: Asset protection from political, creditor, or matrimonial risks | Q7: Holding shares of a private trust company or family business | R7: Asset protection from third-party claims | S7: Multi-generational succession planning | T7: Confidentiality and privacy of beneficial ownership | U7: Flexible distribution control by trustee | V7: Trust | W7: Common Law | X7: Full (trustee liability only) | Y7: Bahamas Financial Intelligence Unit / Central Bank Trustee Act 1998; Purpose Trust Act 2004 | Z7: No | AB7: Multi-generational wealth preservation with discretionary distributions for HNW families | AC7: CRS/FATCA reporting obligations; trustee must be licensed | AD7: 4500 | AE7: M | AG7: O | AI7: N/A | AK7: N/A | AL7: 0 | AM7: M | AO7: N/A | AQ7: N/A | AR7: 3500 | AS7: M | AT7: — | AU7: O | AV7: — | AW7: M | AX7: — | AY7: M | AZ7: — | BA7: M | BC7: M | BD7: — | BE7: M | BF7: — | BG7: M | BI7: N/A | BK7: N/A | BM7: N/A | BO7: N/A | BQ7: N/A | BS7: N/A | BU7: N/A | BW7: N/A | BY7: N/A | CA7: N/A | CC7: N/A | CE7: N/A | CG7: N/A | CK7: N/A | CM7: N/A | CO7: N/A | CP7: 400 | CQ7: M | CR7: 300 | CS7: M | CT7: 125 | CU7: M | CW7: N/A | CY7: N/A | DA7: N/A | DB7: USD 100–750/hr (confirm with local office) | DC7: O | DD7: =ROUND(0.075*SUM(AD7,AF7,AH7,AJ7,AL7,AN7,AP7,AR7,AT7,AV7,AX7,AZ7,BB7,BR7,BT7,BV7,BX7,BZ7,CB7,CD7,CF7,CJ7,CL7,CN7,CP7,CR7,CT7,CV7,CX7,CZ7),0) -> 662 | DE7: Bahamas#Trust#Bahamas Trust | DF7: =A7&"#"&C7&"#"&D7 -> Bahamas#Trust#Bahamas Trust | DG7: =DE7=DF7 -> TRUE
A8: Bahamas | B8: Marvin Taylor | C8: Fund | D8: Bahamas Ltd | E8: USD | F8: Private Limited Company offering limited liability with straightforward corporate governance. | G8: The Bahamas Ltd is a fund structure regulated under local law and widely used by international clients of Amicorp. Private Limited Company offering limited liability with straightforward corporate governance. Our local team manages incorporation, ongoing administration, accounting, and compliance so you can focus on commercial objectives instead of paperwork. | H8: 4-6 weeks | I8: Annual audited financials, regulator filings, AML/KYC monitoring, and investor reporting | J8: Established Bahamas legal framework familiar to investors, banks, and counterparties | K8: End-to-end Amicorp service: incorporation, registered office, directors, accounting, and reporting | L8: Treaty network and regulatory standing supporting cross-border investment and capital flows | M8: Single point of contact across 30+ jurisdictions for multi-entity group structures | N8: Asset managers launching regulated or private funds | O8: PE/VC sponsors raising committed capital from institutional LPs | P8: Family offices pooling investments across asset classes | Q8: Structured products and securitisation arrangers | R8: Pooled capital with professional management | S8: Investor-friendly structure with familiar legal precedent | T8: Tax-efficient flow-through or treaty-eligible vehicle | U8: Scalable for additional sub-funds or share classes | V8: Investment Fund (Private) | W8: Common Law | X8: Full | Y8: Securities Commission of the Bahamas Investment Funds Act 2019 | Z8: No | AA8: 1 | AB8: Private closed-end investment vehicle for accredited investors | AC8: Must appoint licensed fund administrator; annual audit required | AE8: M | AG8: O | AI8: N/A | AK8: N/A | AL8: 0 | AM8: M | AO8: N/A | AP8: — | AQ8: M | AS8: N/A | AT8: — | AU8: O | AV8: — | AW8: M | AX8: — | AY8: M | AZ8: — | BA8: M | BC8: M | BD8: — | BE8: M | BF8: — | BG8: M | BI8: N/A | BK8: N/A | BM8: N/A | BO8: N/A | BQ8: N/A | BR8: 12000 | BS8: M | BU8: N/A | BW8: N/A | BY8: N/A | CA8: N/A | CB8: 2-8 Basispoints (2,000 USD per month minimum fee) | CC8: O | CE8: N/A | CG8: N/A | CH8: 5000 | CI8: O | CJ8: 2500 | CK8: O | CL8: 1500 | CM8: O | CN8: 1500 | CO8: O | CP8: 400 | CQ8: M | CR8: 300 | CS8: M | CT8: 125 | CU8: M | CW8: N/A | CY8: N/A | DA8: N/A | DB8: USD 100–750/hr (confirm with local office) | DC8: O | DD8: =ROUND(0.075*SUM(AD8,AF8,AH8,AJ8,AL8,AN8,AP8,AR8,AT8,AV8,AX8,AZ8,BB8,BR8,BT8,BV8,BX8,BZ8,CB8,CD8,CF8,CJ8,CL8,CN8,CP8,CR8,CT8,CV8,CX8,CZ8),0) -> 1374 | DE8: Bahamas#Fund#Bahamas Ltd | DF8: =A8&"#"&C8&"#"&D8 -> Bahamas#Fund#Bahamas Ltd | DG8: =DE8=DF8 -> TRUE
A9: Bahamas | B9: Marvin Taylor | C9: Fund | D9: Bahamas Exempt LP | E9: USD | F9: Exempted Limited Partnership, the most popular vehicle for PE/VC/RE funds. | G9: The Bahamas Exempt LP is a fund structure regulated under local law and widely used by international clients of Amicorp. Exempted Limited Partnership, the most popular vehicle for PE/VC/RE funds. Our local team manages incorporation, ongoing administration, accounting, and compliance so you can focus on commercial objectives instead of paperwork. | H9: 4-6 weeks | I9: Annual audited financials, regulator filings, AML/KYC monitoring, and investor reporting | J9: Established Bahamas legal framework familiar to investors, banks, and counterparties | K9: End-to-end Amicorp service: incorporation, registered office, directors, accounting, and reporting | L9: Treaty network and regulatory standing supporting cross-border investment and capital flows | M9: Single point of contact across 30+ jurisdictions for multi-entity group structures | N9: Asset managers launching regulated or private funds | O9: PE/VC sponsors raising committed capital from institutional LPs | P9: Family offices pooling investments across asset classes | Q9: Structured products and securitisation arrangers | R9: Pooled capital with professional management | S9: Investor-friendly structure with familiar legal precedent | T9: Tax-efficient flow-through or treaty-eligible vehicle | U9: Scalable for additional sub-funds or share classes | V9: Investment Fund (Private) | W9: Common Law | X9: Full for LPs; unlimited for GP | Y9: Securities Commission of the Bahamas Exempted Limited Partnership Act 1995 | Z9: No | AA9: 1 GP + 1 LP | AB9: PE and VC fund structures with US-style LP economics and carry arrangements | AC9: GP has unlimited liability unless a corporate GP is used | AE9: M | AG9: O | AI9: N/A | AK9: N/A | AL9: 0 | AM9: M | AO9: N/A | AP9: — | AQ9: M | AS9: N/A | AT9: — | AU9: O | AV9: — | AW9: M | AX9: — | AY9: M | AZ9: — | BA9: M | BC9: M | BD9: — | BE9: M | BF9: — | BG9: M | BI9: N/A | BK9: N/A | BM9: N/A | BO9: N/A | BQ9: N/A | BR9: 12000 | BS9: M | BU9: N/A | BW9: N/A | BY9: N/A | CA9: N/A | CB9: 2-8 Basispoints (2,000 USD per month minimum fee) | CC9: O | CE9: N/A | CG9: N/A | CH9: 5000 | CI9: O | CJ9: 2500 | CK9: O | CL9: 1500 | CM9: O | CN9: 1500 | CO9: O | CP9: 400 | CQ9: M | CR9: 300 | CS9: M | CT9: 125 | CU9: M | CW9: N/A | CY9: N/A | DA9: N/A | DB9: USD 100–750/hr (confirm with local office) | DC9: O | DD9: =ROUND(0.075*SUM(AD9,AF9,AH9,AJ9,AL9,AN9,AP9,AR9,AT9,AV9,AX9,AZ9,BB9,BR9,BT9,BV9,BX9,BZ9,CB9,CD9,CF9,CJ9,CL9,CN9,CP9,CR9,CT9,CV9,CX9,CZ9),0) -> 1374 | DE9: Bahamas#Fund#Bahamas Exempt LP | DF9: =A9&"#"&C9&"#"&D9 -> Bahamas#Fund#Bahamas Exempt LP | DG9: =DE9=DF9 -> TRUE
A10: Bahamas | B10: Marvin Taylor | C10: Fund | D10: Bahamas Unit Trust | E10: USD | F10: Pooled investment vehicle where investors hold units representing beneficial interest. | G10: The Bahamas Unit Trust is a fund structure regulated under local law and widely used by international clients of Amicorp. Pooled investment vehicle where investors hold units representing beneficial interest. Our local team manages incorporation, ongoing administration, accounting, and compliance so you can focus on commercial objectives instead of paperwork. | H10: 4-6 weeks | I10: Annual audited financials, regulator filings, AML/KYC monitoring, and investor reporting | J10: Established Bahamas legal framework familiar to investors, banks, and counterparties | K10: End-to-end Amicorp service: incorporation, registered office, directors, accounting, and reporting | L10: Treaty network and regulatory standing supporting cross-border investment and capital flows | M10: Single point of contact across 30+ jurisdictions for multi-entity group structures | N10: Asset managers launching regulated or private funds | O10: PE/VC sponsors raising committed capital from institutional LPs | P10: Family offices pooling investments across asset classes | Q10: Structured products and securitisation arrangers | R10: Pooled capital with professional management | S10: Investor-friendly structure with familiar legal precedent | T10: Tax-efficient flow-through or treaty-eligible vehicle | U10: Scalable for additional sub-funds or share classes | V10: Investment Fund (Private) | W10: Common Law | X10: Full (trustee liability only) | Y10: Securities Commission of the Bahamas Investment Funds Act 2019 | Z10: No | AA10: 1 trustee + 1 unitholder | AB10: Pooled investment structures for retail or institutional investors in listed or unlisted assets | AC10: Trustee must be licensed; subject to Investment Funds Act licensing | AE10: M | AG10: O | AI10: N/A | AK10: N/A | AL10: 0 | AM10: M | AO10: N/A | AP10: — | AQ10: M | AS10: N/A | AT10: — | AU10: O | AV10: — | AW10: M | AX10: — | AY10: M | AZ10: — | BA10: M | BC10: M | BD10: — | BE10: M | BF10: — | BG10: M | BI10: N/A | BK10: N/A | BM10: N/A | BO10: N/A | BQ10: N/A | BR10: 12000 | BS10: M | BU10: N/A | BW10: N/A | BY10: N/A | CA10: N/A | CB10: 2-8 Basispoints (2,000 USD per month minimum fee) | CC10: O | CE10: N/A | CG10: N/A | CH10: 5000 | CI10: O | CJ10: 2500 | CK10: O | CL10: 1500 | CM10: O | CN10: 1500 | CO10: O | CP10: 400 | CQ10: M | CR10: 300 | CS10: M | CT10: 125 | CU10: M | CW10: N/A | CY10: N/A | DA10: N/A | DB10: USD 100–750/hr (confirm with local office) | DC10: O | DD10: =ROUND(0.075*SUM(AD10,AF10,AH10,AJ10,AL10,AN10,AP10,AR10,AT10,AV10,AX10,AZ10,BB10,BR10,BT10,BV10,BX10,BZ10,CB10,CD10,CF10,CJ10,CL10,CN10,CP10,CR10,CT10,CV10,CX10,CZ10),0) -> 1374 | DE10: Bahamas#Fund#Bahamas Unit Trust | DF10: =A10&"#"&C10&"#"&D10 -> Bahamas#Fund#Bahamas Unit Trust | DG10: =DE10=DF10 -> TRUE
A11: Bahamas | B11: Marvin Taylor | C11: Fund | D11: Bahamas SAC | E11: USD | F11: Segregated Accounts Company allowing ring-fenced investment portfolios. | G11: The Bahamas SAC is a fund structure regulated under local law and widely used by international clients of Amicorp. Segregated Accounts Company allowing ring-fenced investment portfolios. Our local team manages incorporation, ongoing administration, accounting, and compliance so you can focus on commercial objectives instead of paperwork. | H11: 4-6 weeks | I11: Annual audited financials, regulator filings, AML/KYC monitoring, and investor reporting | J11: Established Bahamas legal framework familiar to investors, banks, and counterparties | K11: End-to-end Amicorp service: incorporation, registered office, directors, accounting, and reporting | L11: Treaty network and regulatory standing supporting cross-border investment and capital flows | M11: Single point of contact across 30+ jurisdictions for multi-entity group structures | N11: Asset managers launching regulated or private funds | O11: PE/VC sponsors raising committed capital from institutional LPs | P11: Family offices pooling investments across asset classes | Q11: Structured products and securitisation arrangers | R11: Pooled capital with professional management | S11: Investor-friendly structure with familiar legal precedent | T11: Tax-efficient flow-through or treaty-eligible vehicle | U11: Scalable for additional sub-funds or share classes | V11: Segregated Portfolio Company | W11: Common Law | X11: Full (statutory cell segregation) | Y11: Securities Commission of the Bahamas Segregated Accounts Companies Act 2004 | Z11: No | AA11: 1 | AB11: Multi-class investment fund with legally ring-fenced portfolios in a single entity | AC11: Cell segregation not always recognised in foreign jurisdictions; legal opinion required | AE11: M | AG11: O | AI11: N/A | AK11: N/A | AL11: 0 | AM11: M | AO11: N/A | AP11: — | AQ11: M | AS11: N/A | AT11: — | AU11: O | AV11: — | AW11: M | AX11: — | AY11: M | AZ11: — | BA11: M | BC11: M | BD11: — | BE11: M | BF11: — | BG11: M | BI11: N/A | BK11: N/A | BM11: N/A | BO11: N/A | BQ11: N/A | BR11: 12000 | BS11: M | BU11: N/A | BW11: N/A | BY11: N/A | CA11: N/A | CB11: 2-8 Basispoints (2,000 USD per month minimum fee) | CC11: O | CE11: N/A | CG11: N/A | CH11: 5000 | CI11: O | CJ11: 2500 | CK11: O | CL11: 1500 | CM11: O | CN11: 1500 | CO11: O | CP11: 400 | CQ11: M | CR11: 300 | CS11: M | CT11: 125 | CU11: M | CW11: N/A | CY11: N/A | DA11: N/A | DB11: USD 100–750/hr (confirm with local office) | DC11: O | DD11: =ROUND(0.075*SUM(AD11,AF11,AH11,AJ11,AL11,AN11,AP11,AR11,AT11,AV11,AX11,AZ11,BB11,BR11,BT11,BV11,BX11,BZ11,CB11,CD11,CF11,CJ11,CL11,CN11,CP11,CR11,CT11,CV11,CX11,CZ11),0) -> 1374 | DE11: Bahamas#Fund#Bahamas SAC | DF11: =A11&"#"&C11&"#"&D11 -> Bahamas#Fund#Bahamas SAC | DG11: =DE11=DF11 -> TRUE
A12: Bahamas | B12: Marvin Taylor | C12: Fund | D12: Bahamas ICON | E12: USD | F12: Bahamian Investment Condominium — innovative co-ownership fund structure. | G12: The Bahamas ICON is a fund structure regulated under local law and widely used by international clients of Amicorp. Bahamian Investment Condominium — innovative co-ownership fund structure. Our local team manages incorporation, ongoing administration, accounting, and compliance so you can focus on commercial objectives instead of paperwork. | H12: 4-6 weeks | I12: Annual audited financials, regulator filings, AML/KYC monitoring, and investor reporting | J12: Established Bahamas legal framework familiar to investors, banks, and counterparties | K12: End-to-end Amicorp service: incorporation, registered office, directors, accounting, and reporting | L12: Treaty network and regulatory standing supporting cross-border investment and capital flows | M12: Single point of contact across 30+ jurisdictions for multi-entity group structures | N12: Asset managers launching regulated or private funds | O12: PE/VC sponsors raising committed capital from institutional LPs | P12: Family offices pooling investments across asset classes | Q12: Structured products and securitisation arrangers | R12: Pooled capital with professional management | S12: Investor-friendly structure with familiar legal precedent | T12: Tax-efficient flow-through or treaty-eligible vehicle | U12: Scalable for additional sub-funds or share classes | V12: Investment Fund (Private) | W12: Common Law | X12: Full (proportionate to co-ownership interest) | Y12: Securities Commission of the Bahamas Investment Condominium Act 2003 | Z12: No | AA12: 2+ | AB12: Real asset co-ownership structures (real estate, infrastructure) without corporate form | AC12: Niche structure; limited precedent; may not be recognised in all jurisdictions | AE12: M | AG12: O | AI12: N/A | AK12: N/A | AL12: 0 | AM12: M | AO12: N/A | AP12: — | AQ12: M | AS12: N/A | AT12: — | AU12: O | AV12: — | AW12: M | AX12: — | AY12: M | AZ12: — | BA12: M | BC12: M | BD12: — | BE12: M | BF12: — | BG12: M | BI12: N/A | BK12: N/A | BM12: N/A | BO12: N/A | BQ12: N/A | BR12: 12000 | BS12: M | BU12: N/A | BW12: N/A | BY12: N/A | CA12: N/A | CB12: 2-8 Basispoints (2,000 USD per month minimum fee) | CC12: O | CE12: N/A | CG12: N/A | CH12: 5000 | CI12: O | CJ12: 2500 | CK12: O | CL12: 1500 | CM12: O | CN12: 1500 | CO12: O | CP12: 400 | CQ12: M | CR12: 300 | CS12: M | CT12: 125 | CU12: M | CW12: N/A | CY12: N/A | DA12: N/A | DB12: USD 100–750/hr (confirm with local office) | DC12: O | DD12: =ROUND(0.075*SUM(AD12,AF12,AH12,AJ12,AL12,AN12,AP12,AR12,AT12,AV12,AX12,AZ12,BB12,BR12,BT12,BV12,BX12,BZ12,CB12,CD12,CF12,CJ12,CL12,CN12,CP12,CR12,CT12,CV12,CX12,CZ12),0) -> 1374 | DE12: Bahamas#Fund#Bahamas ICON | DF12: =A12&"#"&C12&"#"&D12 -> Bahamas#Fund#Bahamas ICON | DG12: =DE12=DF12 -> TRUE
A13: ARGENTINA | DE13: ## | DF13: =A13&"#"&C13&"#"&D13 -> ARGENTINA##
A14: Argentina | B14: Carlos Fitte | C14: Trust | D14: Argentina Fideicomiso de Garantía | E14: USD | F14: Guarantee trust (fideicomiso) commonly used in Latin American jurisdictions. | G14: The Argentina Fideicomiso de Garantía is a trust structure regulated under local law and widely used by international clients of Amicorp. Guarantee trust (fideicomiso) commonly used in Latin American jurisdictions. Our local team manages incorporation, ongoing administration, accounting, and compliance so you can focus on commercial objectives instead of paperwork. | H14: 5-10 business days | I14: Annual trustee review, beneficiary statements, FATCA/CRS reporting where applicable | J14: Established Argentina legal framework familiar to investors, banks, and counterparties | K14: End-to-end Amicorp service: incorporation, registered office, directors, accounting, and reporting | L14: Treaty network and regulatory standing supporting cross-border investment and capital flows | M14: Single point of contact across 30+ jurisdictions for multi-entity group structures | N14: High-net-worth families consolidating assets across jurisdictions | O14: Succession and inheritance planning for global families | P14: Asset protection from political, creditor, or matrimonial risks | Q14: Holding shares of a private trust company or family business | R14: Asset protection from third-party claims | S14: Multi-generational succession planning | T14: Confidentiality and privacy of beneficial ownership | U14: Flexible distribution control by trustee | V14: Trust (Fideicomiso) | W14: Civil Law | X14: Assets segregated from fiduciario | Y14: CNV (Comisión Nacional de Valores) Civil and Commercial Code Art. 1666-1707 | Z14: No | AA14: 1 fiduciante + 1 fiduciario | AB14: Securing obligations in real estate or infrastructure financing transactions | AC14: Argentina FX controls and high inflation risk; complex tax treatment | AD14: 3500 | AE14: M | AG14: O | AI14: N/A | AK14: N/A | AL14: 0 | AM14: M | AO14: N/A | AP14: — | AQ14: N/A | AS14: M | AT14: — | AU14: O | AV14: — | AW14: M | AX14: — | AY14: M | AZ14: — | BA14: M | BC14: M | BD14: — | BE14: M | BF14: — | BG14: M | BI14: N/A | BK14: N/A | BM14: N/A | BO14: N/A | BQ14: N/A | BS14: N/A | BU14: N/A | BW14: N/A | BY14: N/A | CA14: N/A | CC14: N/A | CE14: N/A | CG14: N/A | CK14: N/A | CM14: N/A | CO14: N/A | CP14: 400 | CQ14: M | CS14: N/A | CU14: N/A | CW14: N/A | CY14: N/A | DA14: N/A | DB14: USD 100–750/hr (confirm with local office) | DC14: O | DD14: =ROUND(0.075*SUM(AD14,AF14,AH14,AJ14,AL14,AN14,AP14,AR14,AT14,AV14,AX14,AZ14,BB14,BR14,BT14,BV14,BX14,BZ14,CB14,CD14,CF14,CJ14,CL14,CN14,CP14,CR14,CT14,CV14,CX14,CZ14),0) -> 293 | DE14: Argentina#Trust#Argentina Fideicomiso de Garantía | DF14: =A14&"#"&C14&"#"&D14 -> Argentina#Trust#Argentina Fideicomiso de Garantía | DG14: =DE14=DF14 -> TRUE
A15: Argentina | B15: Carlos Fitte | C15: Trust | D15: Argentina Trust | E15: USD | F15: Discretionary or fixed trust structure for asset protection and succession planning. | G15: The Argentina Trust is a trust structure regulated under local law and widely used by international clients of Amicorp. Discretionary or fixed trust structure for asset protection and succession planning. Our local team manages incorporation, ongoing administration, accounting, and compliance so you can focus on commercial objectives instead of paperwork. | H15: 5-10 business days | I15: Annual trustee review, beneficiary statements, FATCA/CRS reporting where applicable | J15: Established Argentina legal framework familiar to investors, banks, and counterparties | K15: End-to-end Amicorp service: incorporation, registered office, directors, accounting, and reporting | L15: Treaty network and regulatory standing supporting cross-border investment and capital flows | M15: Single point of contact across 30+ jurisdictions for multi-entity group structures | N15: High-net-worth families consolidating assets across jurisdictions | O15: Succession and inheritance planning for global families | P15: Asset protection from political, creditor, or matrimonial risks | Q15: Holding shares of a private trust company or family business | R15: Asset protection from third-party claims | S15: Multi-generational succession planning | T15: Confidentiality and privacy of beneficial ownership | U15: Flexible distribution control by trustee | V15: Trust (Fideicomiso) | W15: Civil Law | X15: Assets segregated from fiduciario | Y15: BCRA / CNV Civil and Commercial Code Art. 1666-1707 | Z15: No | AA15: 1 fiduciante + 1 fiduciario | AB15: Succession planning and family asset management for Argentine resident families | AC15: Argentina capital controls; forced heirship rules may interact with trust terms | AD15: 5000 | AE15: M | AG15: O | AI15: N/A | AK15: N/A | AL15: 0 | AM15: M | AO15: N/A | AQ15: N/A | AR15: 4000 | AS15: M | AT15: — | AU15: O | AV15: — | AW15: M | AX15: — | AY15: M | AZ15: — | BA15: M | BC15: M | BD15: — | BE15: M | BF15: — | BG15: M | BI15: N/A | BK15: N/A | BM15: N/A | BO15: N/A | BQ15: N/A | BS15: N/A | BU15: N/A | BW15: N/A | BY15: N/A | CA15: N/A | CC15: N/A | CE15: N/A | CG15: N/A | CK15: N/A | CM15: N/A | CO15: N/A | CP15: 400 | CQ15: M | CS15: N/A | CU15: N/A | CW15: N/A | CY15: N/A | DA15: N/A | DB15: USD 100–750/hr (confirm with local office) | DC15: O | DD15: =ROUND(0.075*SUM(AD15,AF15,AH15,AJ15,AL15,AN15,AP15,AR15,AT15,AV15,AX15,AZ15,BB15,BR15,BT15,BV15,BX15,BZ15,CB15,CD15,CF15,CJ15,CL15,CN15,CP15,CR15,CT15,CV15,CX15,CZ15),0) -> 705 | DE15: Argentina#Trust#Argentina Trust | DF15: =A15&"#"&C15&"#"&D15 -> Argentina#Trust#Argentina Trust | DG15: =DE15=DF15 -> TRUE
A16: ABU DHABI | DE16: ## | DF16: =A16&"#"&C16&"#"&D16 -> ABU DHABI##
A17: Abu Dhabi | B17: Supriya Dixit Kambil | C17: Company | D17: Abu Dhabi ADGM SPV | E17: USD | F17: Abu Dhabi Global Market Special Purpose Vehicle for structured finance and investment holding. | G17: The Abu Dhabi ADGM SPV is an entity structure, regulated under English common law and widely used by local and international clients of Amicorp. Abu Dhabi Global Market Special Purpose Vehicle is used for isolating financial and legal risk by ring-fencing certain assets and liabilities for structured finance and investment holding. Our local team manages incorporation, ongoing administration, accounting, and compliance so you can focus on commercial objectives instead of paperwork. | H17: 10 business days | I17: Annual return filing , financial statements filing, and UBO declarations | J17: Established Abu Dhabi legal framework familiar to investors, banks, and counterparties | K17: End-to-end Amicorp service: incorporation, registered office, accounting, and reporting | L17: Treaty network and regulatory standing supporting cross-border investment and capital flows | M17: Single point of contact across 30+ jurisdictions for multi-entity group structures | N17: Holding investments into and out of Abu Dhabi | O17: Group holding companies and intermediate SPVs | P17: Joint ventures and shareholder agreements | Q17: Operating subsidiaries with local market access | R17: Limited liability for shareholders | S17: Separate legal entity | T17: Flexible management structure | U17: Tax efficient - 9% corporated tax is applicable | V17: Special Purpose Vehicle | W17: Common Law (English) | X17: Full | Y17: ADGM Registration Authority ADGM Companies Regulations 2020 | Z17: Yes (ADGM register) | AA17: 1 | AB17: Structured finance, securitisation, and cross-border M&A deal structuring | AC17: Must demonstrate nexus to ADGM; annual substance fees apply | AD17: 5000 | AE17: M | AF17: NA | AG17: O | AH17: 500 | AI17: M | AK17: O | AL17: 0 | AM17: O | AN17: 2000 | AO17: O | AP17: — | AQ17: O | AR17: NA | AS17: N/A | AT17: — | AU17: O | AV17: 1600 | AW17: M | AX17: — | AY17: O | AZ17: 1900 | BA17: M | BC17: O | BD17: 1500 | BE17: O | BF17: — | BG17: N/A | BH17: NA | BI17: N/A | BJ17: NA | BK17: N/A | BL17: 1600 | BM17: O | BN17: NA | BO17: N/A | BP17: Mandatory | BQ17: O | BS17: N/A | BU17: N/A | BW17: N/A | BY17: N/A | CA17: N/A | CC17: N/A | CE17: N/A | CG17: N/A | CK17: N/A | CM17: N/A | CO17: N/A | CP17: 400 | CQ17: M | CS17: N/A | CU17: N/A | CW17: N/A | CY17: N/A | DA17: N/A | DB17: USD 100–750/hr (confirm with local office) | DC17: O | DD17: =ROUND(0.075*SUM(AD17,AF17,AH17,AJ17,AL17,AN17,AP17,AR17,AT17,AV17,AX17,AZ17,BB17,BR17,BT17,BV17,BX17,BZ17,CB17,CD17,CF17,CJ17,CL17,CN17,CP17,CR17,CT17,CV17,CX17,CZ17),0) -> 855 | DE17: Abu Dhabi#Company#Abu Dhabi ADGM SPV | DF17: =A17&"#"&C17&"#"&D17 -> Abu Dhabi#Company#Abu Dhabi ADGM SPV | DG17: =DE17=DF17 -> TRUE
A18: Abu Dhabi | B18: Supriya Dixit Kambil | C18: Company | D18: Abu Dhabi ADGM - Private Limited Company | E18: USD | F18: Private company limited by shares established in the Abu Dhabi Global Market financial free zone. | G18: The Abu Dhabi ADGM - Private Private company limited by shares is a entity structure regulated under English Common law and widely used by local and international clients of Amicorp. Our local team manages incorporation, ongoing administration, accounting, and compliance so you can focus on commercial objectives instead of paperwork. | H18: 10 business days | I18: Annual return, financial statements filing, and economic substance / UBO declarations | J18: Established Abu Dhabi legal framework familiar to investors, banks, and counterparties | K18: End-to-end Amicorp service: incorporation, coordination for lease agreement, accounting, and reporting | L18: Treaty network and regulatory standing supporting cross-border investment and capital flows | M18: Single point of contact across 30+ jurisdictions for multi-entity group structures | N18: Holding investments into and out of Abu Dhabi, providing operational services in ADGM free zone and outside UAE only. | P18: Joint ventures and shareholder agreements | Q18: Operating subsidiaries with access to ADGM free zone and outside UAE market | R18: Limited liability for shareholders | S18: Separate legal entity | T18: Flexible management structure | U18: Tax efficient - 9% corporated tax is applicable | V18: Limited Company | W18: Common Law (English) | X18: Full | Y18: ADGM Registration Authority ADGM Companies Regulations 2020 | Z18: Yes (ADGM register) | AA18: 1 | AB18: Holding company and operating company providing services in ADGM and outside UAE | AC18: Must maintain ADGM office presence and hire minimum 1 employee to fulfil ADGM economic substance requirements; 9% UAE CT and 0% UAE CT for qualifying income only | AD18: 6000 | AE18: M | AG18: O | AH18: 500 | AI18: M | AK18: O | AL18: 0 | AM18: O | AN18: 2000 | AO18: O | AP18: — | AQ18: O | AR18: NA | AS18: N/A | AT18: — | AU18: O | AV18: lease agreement is required from the client at the time of oncorporation | AW18: M | AX18: — | AY18: O | AZ18: 5800 | BA18: M | BC18: O | BD18: 1500 | BE18: O | BF18: — | BG18: N/A | BH18: NA | BI18: N/A | BJ18: Mandatory - from ADGM registered auditors | BK18: O | BL18: 1600 | BM18: O | BN18: NA | BO18: N/A | BP18: Mandatory | BQ18: O | BS18: N/A | BU18: N/A | BW18: N/A | BY18: N/A | CA18: N/A | CC18: N/A | CE18: N/A | CG18: N/A | CK18: N/A | CM18: N/A | CO18: N/A | CP18: 400 | CQ18: M | CS18: N/A | CU18: N/A | CW18: N/A | CY18: N/A | DA18: N/A | DB18: USD 100–750/hr (confirm with local office) | DC18: O | DD18: =ROUND(0.075*SUM(AD18,AF18,AH18,AJ18,AL18,AN18,AP18,AR18,AT18,AV18,AX18,AZ18,BB18,BR18,BT18,BV18,BX18,BZ18,CB18,CD18,CF18,CJ18,CL18,CN18,CP18,CR18,CT18,CV18,CX18,CZ18),0) -> 1103 | DE18: Abu Dhabi#Company#Abu Dhabi ADGM - Private Limited Company | DF18: =A18&"#"&C18&"#"&D18 -> Abu Dhabi#Company#Abu Dhabi ADGM - Private Limited Company | DG18: =DE18=DF18 -> TRUE
A19: Abu Dhabi | B19: Supriya Dixit Kambil | C19: Company | D19: Abu Dhabi ADGM - Foundation | E19: USD | F19: Foundation structure suitable for wealth management and succession plannng. A common choice among HNWI | G19: The Abu Dhabi Foundation is regulated under english common local law and widely used by local and international clients of Amicorp. Our local team manages incorporation, ongoing administration, accounting, and compliance so you can focus on commercial objectives instead of paperwork. | H19: 10 business days | I19: Annual return, financial statements filing, and economic substance / UBO declarations | J19: Established Abu Dhabi legal framework familiar to investors, banks, and counterparties | K19: End-to-end Amicorp service: incorporation, registered office, accounting, and reporting | L19: Treaty network and regulatory standing supporting cross-border investment and capital flows | M19: Single point of contact across 30+ jurisdictions for multi-entity group structures | N19: Wealth management and succession planning, | O19: Succession and inheritance planning for global families | P19: High-net-worth families consolidating assets across jurisdictions | S19: Separate legal entity | T19: Flexible management structure | U19: Tax efficient - 9% corporated tax is applicable | V19: Other - Foundation | W19: Common Law (English) | X19: Varies by structure as defined in the charter of the foundation | Y19: ADGM Registration Authority ADGM Foundation Regulations 2017 | Z19: Yes | AA19: Varies Founder, minimum 2 council members, beneficiaries | AC19: Foundation is eligible to 9% UAE CT and 0% UAE CT if qualified as exempt by FTA | AD19: 5500 | AE19: M | AF19: NA | AG19: O | AH19: 500 | AI19: M | AK19: O | AL19: 0 | AM19: O | AN19: 2000 | AO19: O | AP19: 15000 | AQ19: O | AR19: NA | AS19: N/A | AT19: — | AU19: O | AV19: 1600 | AW19: M | AX19: — | AY19: O | AZ19: 1000 | BA19: M | BC19: O | BD19: 1500 | BE19: O | BF19: — | BG19: N/A | BH19: NA | BI19: N/A | BJ19: NA | BK19: N/A | BL19: 1600 | BM19: O | BN19: NA | BO19: N/A | BP19: Yes | BQ19: O | BS19: N/A | BU19: N/A | BW19: N/A | BY19: N/A | CA19: N/A | CC19: N/A | CE19: N/A | CG19: N/A | CK19: N/A | CM19: N/A | CO19: N/A | CP19: 400 | CQ19: M | CS19: N/A | CU19: N/A | CW19: N/A | CY19: N/A | DA19: N/A | DB19: USD 100–750/hr (confirm with local office) | DC19: O | DD19: =ROUND(0.075*SUM(AD19,AF19,AH19,AJ19,AL19,AN19,AP19,AR19,AT19,AV19,AX19,AZ19,BB19,BR19,BT19,BV19,BX19,BZ19,CB19,CD19,CF19,CJ19,CL19,CN19,CP19,CR19,CT19,CV19,CX19,CZ19),0) -> 1950 | DE19: Abu Dhabi#Company#Abu Dhabi ADGM - Foundation | DF19: =A19&"#"&C19&"#"&D19 -> Abu Dhabi#Company#Abu Dhabi ADGM - Foundation | DG19: =DE19=DF19 -> TRUE
A20: BRAZIL | DE20: ## | DF20: =A20&"#"&C20&"#"&D20 -> BRAZIL##
A21: Brazil | B21: Marco Navarro | C21: Fund | D21: Brazil FI | E21: USD | F21: Brazilian Fundo de Investimento — standard investment fund vehicle. | G21: The Brazil FI is a fund structure regulated under local law and widely used by international clients of Amicorp. Brazilian Fundo de Investimento — standard investment fund vehicle. Our local team manages incorporation, ongoing administration, accounting, and compliance so you can focus on commercial objectives instead of paperwork. | H21: 4-6 weeks | I21: Annual audited financials, regulator filings, AML/KYC monitoring, and investor reporting | J21: Established Brazil legal framework familiar to investors, banks, and counterparties | K21: End-to-end Amicorp service: incorporation, registered office, directors, accounting, and reporting | L21: Treaty network and regulatory standing supporting cross-border investment and capital flows | M21: Single point of contact across 30+ jurisdictions for multi-entity group structures | N21: Asset managers launching regulated or private funds | O21: PE/VC sponsors raising committed capital from institutional LPs | P21: Family offices pooling investments across asset classes | Q21: Structured products and securitisation arrangers | R21: Pooled capital with professional management | S21: Investor-friendly structure with familiar legal precedent | T21: Tax-efficient flow-through or treaty-eligible vehicle | U21: Scalable for additional sub-funds or share classes | V21: Investment Fund (Regulated) | W21: Civil Law | X21: Full (condominium structure, not entity) | Y21: CVM (Comissão de Valores Mobiliários) CVM Resolution 175/2022; Law 8,668/93 | Z21: Yes (CVM registration) | AA21: 1 administrator + 1 investor | AB21: Brazilian domestic investment fund for diversified fixed income or multi-asset portfolios | AC21: Brazilian FX controls; mandatory local administrator; CVM reporting requirements | AE21: M | AG21: O | AI21: N/A | AK21: N/A | AL21: 0 | AM21: M | AO21: N/A | AP21: — | AQ21: M | AS21: N/A | AT21: — | AU21: O | AV21: — | AW21: M | AX21: — | AY21: M | AZ21: — | BA21: M | BC21: M | BD21: — | BE21: M | BF21: — | BG21: M | BI21: N/A | BK21: N/A | BM21: N/A | BO21: N/A | BQ21: N/A | BR21: 15000 | BS21: M | BU21: N/A | BW21: N/A | BY21: N/A | CA21: N/A | CB21: 2-8 Basispoints (2,000 USD per month minimum fee) | CC21: O | CE21: N/A | CG21: N/A | CI21: O | CJ21: 2500 | CK21: O | CL21: 1500 | CM21: O | CN21: 1500 | CO21: O | CP21: 400 | CQ21: M | CS21: N/A | CU21: N/A | CW21: N/A | CY21: N/A | DA21: N/A | DB21: USD 100–750/hr (confirm with local office) | DC21: O | DD21: =ROUND(0.075*SUM(AD21,AF21,AH21,AJ21,AL21,AN21,AP21,AR21,AT21,AV21,AX21,AZ21,BB21,BR21,BT21,BV21,BX21,BZ21,CB21,CD21,CF21,CJ21,CL21,CN21,CP21,CR21,CT21,CV21,CX21,CZ21),0) -> 1568 | DE21: Brazil#Fund#Brazil FI | DF21: =A21&"#"&C21&"#"&D21 -> Brazil#Fund#Brazil FI | DG21: =DE21=DF21 -> TRUE
A22: Brazil | B22: Marco Navarro | C22: Fund | D22: Brazil FIC | E22: USD | F22: Brazilian Fundo de Investimento em Cotas — fund of funds structure. | G22: The Brazil FIC is a fund structure regulated under local law and widely used by international clients of Amicorp. Brazilian Fundo de Investimento em Cotas — fund of funds structure. Our local team manages incorporation, ongoing administration, accounting, and compliance so you can focus on commercial objectives instead of paperwork. | H22: 4-6 weeks | I22: Annual audited financials, regulator filings, AML/KYC monitoring, and investor reporting | J22: Established Brazil legal framework familiar to investors, banks, and counterparties | K22: End-to-end Amicorp service: incorporation, registered office, directors, accounting, and reporting | L22: Treaty network and regulatory standing supporting cross-border investment and capital flows | M22: Single point of contact across 30+ jurisdictions for multi-entity group structures | N22: Asset managers launching regulated or private funds | O22: PE/VC sponsors raising committed capital from institutional LPs | P22: Family offices pooling investments across asset classes | Q22: Structured products and securitisation arrangers | R22: Pooled capital with professional management | S22: Investor-friendly structure with familiar legal precedent | T22: Tax-efficient flow-through or treaty-eligible vehicle | U22: Scalable for additional sub-funds or share classes | V22: Investment Fund (Regulated) | W22: Civil Law | X22: Full | Y22: CVM CVM Resolution 175/2022 | Z22: Yes | AA22: 1+ | AB22: Fund-of-funds structure for institutional investors allocating to multiple Brazilian funds | AC22: Double fee layer (FIC + underlying FI); concentration limits apply | AE22: M | AG22: O | AI22: N/A | AK22: N/A | AL22: 0 | AM22: M | AO22: N/A | AP22: — | AQ22: M | AS22: N/A | AT22: — | AU22: O | AV22: — | AW22: M | AX22: — | AY22: M | AZ22: — | BA22: M | BC22: M | BD22: — | BE22: M | BF22: — | BG22: M | BI22: N/A | BK22: N/A | BM22: N/A | BO22: N/A | BQ22: N/A | BR22: 15000 | BS22: M | BU22: N/A | BW22: N/A | BY22: N/A | CA22: N/A | CB22: 2-8 Basispoints (2,000 USD per month minimum fee) | CC22: O | CE22: N/A | CG22: N/A | CI22: O | CJ22: 2500 | CK22: O | CL22: 1500 | CM22: O | CN22: 1500 | CO22: O | CP22: 400 | CQ22: M | CS22: N/A | CU22: N/A | CW22: N/A | CY22: N/A | DA22: N/A | DB22: USD 100–750/hr (confirm with local office) | DC22: O | DD22: =ROUND(0.075*SUM(AD22,AF22,AH22,AJ22,AL22,AN22,AP22,AR22,AT22,AV22,AX22,AZ22,BB22,BR22,BT22,BV22,BX22,BZ22,CB22,CD22,CF22,CJ22,CL22,CN22,CP22,CR22,CT22,CV22,CX22,CZ22),0) -> 1568 | DE22: Brazil#Fund#Brazil FIC | DF22: =A22&"#"&C22&"#"&D22 -> Brazil#Fund#Brazil FIC | DG22: =DE22=DF22 -> TRUE
A23: Brazil | B23: Marco Navarro | C23: Fund | D23: Brazil FIA | E23: USD | F23: Brazilian Fundo de Investimento em Ações — equity investment fund. | G23: The Brazil FIA is a fund structure regulated under local law and widely used by international clients of Amicorp. Brazilian Fundo de Investimento em Ações — equity investment fund. Our local team manages incorporation, ongoing administration, accounting, and compliance so you can focus on commercial objectives instead of paperwork. | H23: 4-6 weeks | I23: Annual audited financials, regulator filings, AML/KYC monitoring, and investor reporting | J23: Established Brazil legal framework familiar to investors, banks, and counterparties | K23: End-to-end Amicorp service: incorporation, registered office, directors, accounting, and reporting | L23: Treaty network and regulatory standing supporting cross-border investment and capital flows | M23: Single point of contact across 30+ jurisdictions for multi-entity group structures | N23: Asset managers launching regulated or private funds | O23: PE/VC sponsors raising committed capital from institutional LPs | P23: Family offices pooling investments across asset classes | Q23: Structured products and securitisation arrangers | R23: Pooled capital with professional management | S23: Investor-friendly structure with familiar legal precedent | T23: Tax-efficient flow-through or treaty-eligible vehicle | U23: Scalable for additional sub-funds or share classes | V23: Investment Fund (Regulated) | W23: Civil Law | X23: Full | Y23: CVM CVM Resolution 175/2022 | Z23: Yes | AA23: 1+ | AB23: Brazilian equity investment fund investing ≥67% in listed equities (Bovespa) | AC23: FX risk; high volatility in Brazilian equity markets; BRL hedging cost | AE23: M | AG23: O | AI23: N/A | AK23: N/A | AL23: 0 | AM23: M | AO23: N/A | AP23: — | AQ23: M | AS23: N/A | AT23: — | AU23: O | AV23: — | AW23: M | AX23: — | AY23: M | AZ23: — | BA23: M | BC23: M | BD23: — | BE23: M | BF23: — | BG23: M | BI23: N/A | BK23: N/A | BM23: N/A | BO23: N/A | BQ23: N/A | BR23: 15000 | BS23: M | BU23: N/A | BW23: N/A | BY23: N/A | CA23: N/A | CB23: 2-8 Basispoints (2,000 USD per month minimum fee) | CC23: O | CE23: N/A | CG23: N/A | CI23: O | CJ23: 2500 | CK23: O | CL23: 1500 | CM23: O | CN23: 1500 | CO23: O | CP23: 400 | CQ23: M | CS23: N/A | CU23: N/A | CW23: N/A | CY23: N/A | DA23: N/A | DB23: USD 100–750/hr (confirm with local office) | DC23: O | DD23: =ROUND(0.075*SUM(AD23,AF23,AH23,AJ23,AL23,AN23,AP23,AR23,AT23,AV23,AX23,AZ23,BB23,BR23,BT23,BV23,BX23,BZ23,CB23,CD23,CF23,CJ23,CL23,CN23,CP23,CR23,CT23,CV23,CX23,CZ23),0) -> 1568 | DE23: Brazil#Fund#Brazil FIA | DF23: =A23&"#"&C23&"#"&D23 -> Brazil#Fund#Brazil FIA | DG23: =DE23=DF23 -> TRUE
A24: Brazil | B24: Marco Navarro | C24: Fund | D24: Brazil FIP | E24: USD | F24: Brazilian Fundo de Investimento em Participações — private equity fund. | G24: The Brazil FIP is a fund structure regulated under local law and widely used by international clients of Amicorp. Brazilian Fundo de Investimento em Participações — private equity fund. Our local team manages incorporation, ongoing administration, accounting, and compliance so you can focus on commercial objectives instead of paperwork. | H24: 4-6 weeks | I24: Annual audited financials, regulator filings, AML/KYC monitoring, and investor reporting | J24: Established Brazil legal framework familiar to investors, banks, and counterparties | K24: End-to-end Amicorp service: incorporation, registered office, directors, accounting, and reporting | L24: Treaty network and regulatory standing supporting cross-border investment and capital flows | M24: Single point of contact across 30+ jurisdictions for multi-entity group structures | N24: Asset managers launching regulated or private funds | O24: PE/VC sponsors raising committed capital from institutional LPs | P24: Family offices pooling investments across asset classes | Q24: Structured products and securitisation arrangers | R24: Pooled capital with professional management | S24: Investor-friendly structure with familiar legal precedent | T24: Tax-efficient flow-through or treaty-eligible vehicle | U24: Scalable for additional sub-funds or share classes | V24: Investment Fund (AIF) | W24: Civil Law | X24: Full | Y24: CVM CVM Resolution 175/2022; Law 12,431/11 | Z24: Yes | AA24: 1+ | AB24: Private equity and buyout fund investing in Brazilian non-listed companies | AC24: Minimum 10-year term; governance and reporting requirements under CVM | AE24: M | AG24: O | AI24: N/A | AK24: N/A | AL24: 0 | AM24: M | AO24: N/A | AP24: — | AQ24: M | AS24: N/A | AT24: — | AU24: O | AV24: — | AW24: M | AX24: — | AY24: M | AZ24: — | BA24: M | BC24: M | BD24: — | BE24: M | BF24: — | BG24: M | BI24: N/A | BK24: N/A | BM24: N/A | BO24: N/A | BQ24: N/A | BR24: 15000 | BS24: M | BU24: N/A | BW24: N/A | BY24: N/A | CA24: N/A | CB24: 2-8 Basispoints (2,000 USD per month minimum fee) | CC24: O | CE24: N/A | CG24: N/A | CI24: O | CJ24: 2500 | CK24: O | CL24: 1500 | CM24: O | CN24: 1500 | CO24: O | CP24: 400 | CQ24: M | CS24: N/A | CU24: N/A | CW24: N/A | CY24: N/A | DA24: N/A | DB24: USD 100–750/hr (confirm with local office) | DC24: O | DD24: =ROUND(0.075*SUM(AD24,AF24,AH24,AJ24,AL24,AN24,AP24,AR24,AT24,AV24,AX24,AZ24,BB24,BR24,BT24,BV24,BX24,BZ24,CB24,CD24,CF24,CJ24,CL24,CN24,CP24,CR24,CT24,CV24,CX24,CZ24),0) -> 1568 | DE24: Brazil#Fund#Brazil FIP | DF24: =A24&"#"&C24&"#"&D24 -> Brazil#Fund#Brazil FIP | DG24: =DE24=DF24 -> TRUE
A25: Brazil | B25: Marco Navarro | C25: Fund | D25: Brazil FII | E25: USD | F25: Brazilian Fundo de Investimento Imobiliário — real estate investment fund. | G25: The Brazil FII is a fund structure regulated under local law and widely used by international clients of Amicorp. Brazilian Fundo de Investimento Imobiliário — real estate investment fund. Our local team manages incorporation, ongoing administration, accounting, and compliance so you can focus on commercial objectives instead of paperwork. | H25: 4-6 weeks | I25: Annual audited financials, regulator filings, AML/KYC monitoring, and investor reporting | J25: Established Brazil legal framework familiar to investors, banks, and counterparties | K25: End-to-end Amicorp service: incorporation, registered office, directors, accounting, and reporting | L25: Treaty network and regulatory standing supporting cross-border investment and capital flows | M25: Single point of contact across 30+ jurisdictions for multi-entity group structures | N25: Asset managers launching regulated or private funds | O25: PE/VC sponsors raising committed capital from institutional LPs | P25: Family offices pooling investments across asset classes | Q25: Structured products and securitisation arrangers | R25: Pooled capital with professional management | S25: Investor-friendly structure with familiar legal precedent | T25: Tax-efficient flow-through or treaty-eligible vehicle | U25: Scalable for additional sub-funds or share classes | V25: REIT/Business Trust | W25: Civil Law | X25: Full | Y25: CVM Law 8,668/93; CVM Resolution 175/2022 | Z25: Yes | AA25: 1+ | AB25: Real estate investment trust listed on B3 for retail and institutional investors | AC25: Must distribute ≥95% of income semi-annually; minimum 50 investors for tax exemption | AE25: M | AG25: O | AI25: N/A | AK25: N/A | AL25: 0 | AM25: M | AO25: N/A | AP25: — | AQ25: M | AS25: N/A | AT25: — | AU25: O | AV25: — | AW25: M | AX25: — | AY25: M | AZ25: — | BA25: M | BC25: M | BD25: — | BE25: M | BF25: — | BG25: M | BI25: N/A | BK25: N/A | BM25: N/A | BO25: N/A | BQ25: N/A | BR25: 15000 | BS25: M | BU25: N/A | BW25: N/A | BY25: N/A | CA25: N/A | CB25: 2-8 Basispoints (2,000 USD per month minimum fee) | CC25: O | CE25: N/A | CG25: N/A | CI25: O | CJ25: 2500 | CK25: O | CL25: 1500 | CM25: O | CN25: 1500 | CO25: O | CP25: 400 | CQ25: M | CS25: N/A | CU25: N/A | CW25: N/A | CY25: N/A | DA25: N/A | DB25: USD 100–750/hr (confirm with local office) | DC25: O | DD25: =ROUND(0.075*SUM(AD25,AF25,AH25,AJ25,AL25,AN25,AP25,AR25,AT25,AV25,AX25,AZ25,BB25,BR25,BT25,BV25,BX25,BZ25,CB25,CD25,CF25,CJ25,CL25,CN25,CP25,CR25,CT25,CV25,CX25,CZ25),0) -> 1568 | DE25: Brazil#Fund#Brazil FII | DF25: =A25&"#"&C25&"#"&D25 -> Brazil#Fund#Brazil FII | DG25: =DE25=DF25 -> TRUE
A26: Brazil | B26: Marco Navarro | C26: Fund | D26: Brazil FI-Infra | E26: USD | F26: Brazilian infrastructure investment fund for long-term infrastructure projects. | G26: The Brazil FI-Infra is a fund structure regulated under local law and widely used by international clients of Amicorp. Brazilian infrastructure investment fund for long-term infrastructure projects. Our local team manages incorporation, ongoing administration, accounting, and compliance so you can focus on commercial objectives instead of paperwork. | H26: 4-6 weeks | I26: Annual audited financials, regulator filings, AML/KYC monitoring, and investor reporting | J26: Established Brazil legal framework familiar to investors, banks, and counterparties | K26: End-to-end Amicorp service: incorporation, registered office, directors, accounting, and reporting | L26: Treaty network and regulatory standing supporting cross-border investment and capital flows | M26: Single point of contact across 30+ jurisdictions for multi-entity group structures | N26: Asset managers launching regulated or private funds | O26: PE/VC sponsors raising committed capital from institutional LPs | P26: Family offices pooling investments across asset classes | Q26: Structured products and securitisation arrangers | R26: Pooled capital with professional management | S26: Investor-friendly structure with familiar legal precedent | T26: Tax-efficient flow-through or treaty-eligible vehicle | U26: Scalable for additional sub-funds or share classes | V26: Investment Fund (AIF) | W26: Civil Law | X26: Full | Y26: CVM Law 12,431/2011; CVM Resolution 175/2022 | Z26: Yes | AA26: 1+ | AB26: Infrastructure debt fund investing in regulated infrastructure assets (energy, sanitation, transport) | AC26: Must invest ≥85% in infrastructure debentures; long lock-up periods typical | AE26: M | AG26: O | AI26: N/A | AK26: N/A | AL26: 0 | AM26: M | AO26: N/A | AP26: — | AQ26: M | AS26: N/A | AT26: — | AU26: O | AV26: — | AW26: M | AX26: — | AY26: M | AZ26: — | BA26: M | BC26: M | BD26: — | BE26: M | BF26: — | BG26: M | BI26: N/A | BK26: N/A | BM26: N/A | BO26: N/A | BQ26: N/A | BR26: 15000 | BS26: M | BU26: N/A | BW26: N/A | BY26: N/A | CA26: N/A | CB26: 2-8 Basispoints (2,000 USD per month minimum fee) | CC26: O | CE26: N/A | CG26: N/A | CI26: O | CJ26: 2500 | CK26: O | CL26: 1500 | CM26: O | CN26: 1500 | CO26: O | CP26: 400 | CQ26: M | CS26: N/A | CU26: N/A | CW26: N/A | CY26: N/A | DA26: N/A | DB26: USD 100–750/hr (confirm with local office) | DC26: O | DD26: =ROUND(0.075*SUM(AD26,AF26,AH26,AJ26,AL26,AN26,AP26,AR26,AT26,AV26,AX26,AZ26,BB26,BR26,BT26,BV26,BX26,BZ26,CB26,CD26,CF26,CJ26,CL26,CN26,CP26,CR26,CT26,CV26,CX26,CZ26),0) -> 1568 | DE26: Brazil#Fund#Brazil FI-Infra | DF26: =A26&"#"&C26&"#"&D26 -> Brazil#Fund#Brazil FI-Infra | DG26: =DE26=DF26 -> TRUE
A27: BRITISH VIRGIN ISLANDS | DE27: ## | DF27: =A27&"#"&C27&"#"&D27 -> BRITISH VIRGIN ISLANDS##
A28: British Virgin Islands | B28: Pedro Garcia | C28: Company | D28: British Virgin Islands BVIBC | E28: USD | F28: BVI Business Company, a flexible tax-neutral vehicle widely used for international holding and trading activities. | G28: The British Virgin Islands BVIBC is a entity structure regulated under local law and widely used by international clients of Amicorp. BVI Business Company, a flexible tax-neutral vehicle widely used for international holding and trading activities. Our local team manages incorporation, ongoing administration, accounting, and compliance so you can focus on commercial objectives instead of paperwork. | H28: 3-7 business days | I28: Annual return, financial statements filing, and economic substance / UBO declarations | J28: Established British Virgin Islands legal framework familiar to investors, banks, and counterparties | K28: End-to-end Amicorp service: incorporation, registered office, directors, accounting, and reporting | L28: Treaty network and regulatory standing supporting cross-border investment and capital flows | M28: Single point of contact across 30+ jurisdictions for multi-entity group structures | N28: Holding investments into and out of British Virgin Islands | O28: Group holding companies and intermediate SPVs | P28: Joint ventures and shareholder agreements | Q28: Operating subsidiaries with local market access | R28: Limited liability for shareholders | S28: Separate legal entity | T28: Flexible management structure | U28: Tax efficient | V28: IBC | W28: Common Law | X28: Full | Y28: BVI Financial Services Commission BVI Business Companies Act 2004 (as amended) | Z28: No (beneficial ownership in private register) | AA28: 1 | AB28: Holding structure for international investments, IP, or cross-border M&A SPVs | AC28: Economic substance rules for holding companies; FATF/OECD grey-list risk for certain activities | AD28: 1780 | AE28: M | AG28: O | AI28: N/A | AK28: N/A | AL28: 0 | AM28: M | AO28: N/A | AP28: 2500 | AQ28: O | AS28: N/A | AT28: — | AU28: O | AV28: 930 | AW28: M | AX28: 1010 | AY28: 0 | AZ28: 550 | BA28: M | BC28: M | BD28: 1000 | BE28: O | BF28: 1500 | BG28: O | BI28: N/A | BK28: N/A | BL28: 350 | BM28: O | BN28: 125 | BO28: O | BQ28: N/A | BS28: N/A | BU28: N/A | BW28: N/A | BY28: N/A | CA28: N/A | CC28: N/A | CE28: N/A | CG28: N/A | CK28: N/A | CM28: N/A | CO28: N/A | CP28: 400 | CQ28: M | CR28: 300 | CS28: M | CT28: 125 | CU28: M | CW28: N/A | CY28: N/A | DA28: N/A | DB28: USD 100–750/hr (confirm with local office) | DC28: O | DD28: =ROUND(0.075*SUM(AD28,AF28,AH28,AJ28,AL28,AN28,AP28,AR28,AT28,AV28,AX28,AZ28,BB28,BR28,BT28,BV28,BX28,BZ28,CB28,CD28,CF28,CJ28,CL28,CN28,CP28,CR28,CT28,CV28,CX28,CZ28),0) -> 570 | DE28: British Virgin Islands#Company#British Virgin Islands BVIBC | DF28: =A28&"#"&C28&"#"&D28 -> British Virgin Islands#Company#British Virgin Islands BVIBC | DG28: =DE28=DF28 -> TRUE
A29: British Virgin Islands | B29: Pedro Garcia | C29: Company | D29: British Virgin Islands SPC | E29: USD | F29: Segregated Portfolio Company allowing creation of ring-fenced portfolios within a single legal entity. | G29: The British Virgin Islands SPC is a entity structure regulated under local law and widely used by international clients of Amicorp. Segregated Portfolio Company allowing creation of ring-fenced portfolios within a single legal entity. Our local team manages incorporation, ongoing administration, accounting, and compliance so you can focus on commercial objectives instead of paperwork. | H29: 3-7 business days | I29: Annual return, financial statements filing, and economic substance / UBO declarations | J29: Established British Virgin Islands legal framework familiar to investors, banks, and counterparties | K29: End-to-end Amicorp service: incorporation, registered office, directors, accounting, and reporting | L29: Treaty network and regulatory standing supporting cross-border investment and capital flows | M29: Single point of contact across 30+ jurisdictions for multi-entity group structures | N29: Holding investments into and out of British Virgin Islands | O29: Group holding companies and intermediate SPVs | P29: Joint ventures and shareholder agreements | Q29: Operating subsidiaries with local market access | R29: Limited liability for shareholders | S29: Separate legal entity | T29: Flexible management structure | U29: Tax efficient | V29: Segregated Portfolio Company | W29: Common Law | X29: Full (statutory cell segregation) | Y29: BVI Financial Services Commission BVI Business Companies Act 2004 (SPC provisions) | Z29: No | AA29: 1 | AB29: Multi-class hedge fund or insurance vehicle with legally ring-fenced portfolios | AC29: Requires FSC approval; cell segregation may not be recognised in non-BVI courts | AD29: 3500 | AE29: M | AG29: O | AI29: N/A | AK29: N/A | AL29: 0 | AM29: M | AO29: N/A | AP29: 2800 | AQ29: M | AS29: N/A | AT29: — | AU29: O | AV29: 930 | AW29: M | AX29: — | AY29: 0 | AZ29: — | BA29: M | BC29: M | BD29: — | BE29: M | BF29: — | BG29: M | BI29: N/A | BK29: N/A | BM29: N/A | BO29: N/A | BQ29: N/A | BS29: N/A | BU29: N/A | BW29: N/A | BY29: N/A | CA29: N/A | CC29: N/A | CE29: N/A | CG29: N/A | CK29: N/A | CM29: N/A | CO29: N/A | CP29: 400 | CQ29: M | CR29: 300 | CS29: M | CT29: 125 | CU29: M | CW29: N/A | CY29: N/A | DA29: N/A | DB29: USD 100–750/hr (confirm with local office) | DC29: O | DD29: =ROUND(0.075*SUM(AD29,AF29,AH29,AJ29,AL29,AN29,AP29,AR29,AT29,AV29,AX29,AZ29,BB29,BR29,BT29,BV29,BX29,BZ29,CB29,CD29,CF29,CJ29,CL29,CN29,CP29,CR29,CT29,CV29,CX29,CZ29),0) -> 604 | DE29: British Virgin Islands#Company#British Virgin Islands SPC | DF29: =A29&"#"&C29&"#"&D29 -> British Virgin Islands#Company#British Virgin Islands SPC | DG29: =DE29=DF29 -> TRUE
A30: British Virgin Islands | B30: Pedro Garcia | C30: Trust | D30: British Virgin Islands Vista Trust | E30: USD | F30: BVI Vista Trust providing enhanced settlor control and asset protection features. | G30: The British Virgin Islands Vista Trust is a trust structure regulated under local law and widely used by international clients of Amicorp. BVI Vista Trust providing enhanced settlor control and asset protection features. Our local team manages incorporation, ongoing administration, accounting, and compliance so you can focus on commercial objectives instead of paperwork. | H30: 5-10 business days | I30: Annual trustee review, beneficiary statements, FATCA/CRS reporting where applicable | J30: Established British Virgin Islands legal framework familiar to investors, banks, and counterparties | K30: End-to-end Amicorp service: incorporation, registered office, directors, accounting, and reporting | L30: Treaty network and regulatory standing supporting cross-border investment and capital flows | M30: Single point of contact across 30+ jurisdictions for multi-entity group structures | N30: High-net-worth families consolidating assets across jurisdictions | O30: Succession and inheritance planning for global families | P30: Asset protection from political, creditor, or matrimonial risks | Q30: Holding shares of a private trust company or family business | R30: Asset protection from third-party claims | S30: Multi-generational succession planning | T30: Confidentiality and privacy of beneficial ownership | U30: Flexible distribution control by trustee | V30: Trust (VISTA) | W30: Common Law | X30: Full | Y30: BVI Financial Services Commission Virgin Islands Special Trusts Act (VISTA) 2003 | Z30: No | AB30: Long-term holding of BVI BC shares without trustee interference in company management | AC30: Only usable for BVI BC shares; requires licensed BVI trustee; limited suitability for non-BVI assets | AD30: 5530 | AE30: M | AG30: O | AI30: N/A | AK30: N/A | AL30: 0 | AM30: M | AO30: N/A | AQ30: N/A | AR30: 5530 | AS30: M | AT30: — | AU30: O | AW30: M | AX30: — | AY30: M | AZ30: 550 | BA30: M | BC30: M | BD30: 1500 | BE30: M | BF30: — | BG30: M | BI30: N/A | BK30: N/A | BM30: N/A | BO30: N/A | BQ30: N/A | BS30: N/A | BU30: N/A | BW30: N/A | BY30: N/A | CA30: N/A | CC30: N/A | CE30: N/A | CG30: N/A | CK30: N/A | CM30: N/A | CO30: N/A | CP30: 400 | CQ30: M | CR30: 300 | CS30: M | CT30: 125 | CU30: M | CW30: N/A | CY30: N/A | DA30: N/A | DB30: Other administrative services: USD 100-125/hr Other legal services: USD 125-175/hr Trust lawyer, manager or equivalent: USD 175-200/hr | DC30: O | DD30: =ROUND(0.075*SUM(AD30,AF30,AH30,AJ30,AL30,AN30,AP30,AR30,AT30,AV30,AX30,AZ30,BB30,BR30,BT30,BV30,BX30,BZ30,CB30,CD30,CF30,CJ30,CL30,CN30,CP30,CR30,CT30,CV30,CX30,CZ30),0) -> 933 | DE30: British Virgin Islands#Trust#British Virgin Islands Vista Trust | DF30: =A30&"#"&C30&"#"&D30 -> British Virgin Islands#Trust#British Virgin Islands Vista Trust | DG30: =DE30=DF30 -> TRUE
A31: British Virgin Islands | B31: Pedro Garcia | C31: Trust | D31: British Virgin Islands Trust | E31: USD | F31: Discretionary or fixed trust structure for asset protection and succession planning. | G31: The British Virgin Islands Trust is a trust structure regulated under local law and widely used by international clients of Amicorp. Discretionary or fixed trust structure for asset protection and succession planning. Our local team manages incorporation, ongoing administration, accounting, and compliance so you can focus on commercial objectives instead of paperwork. | H31: 5-10 business days | I31: Annual trustee review, beneficiary statements, FATCA/CRS reporting where applicable | J31: Established British Virgin Islands legal framework familiar to investors, banks, and counterparties | K31: End-to-end Amicorp service: incorporation, registered office, directors, accounting, and reporting | L31: Treaty network and regulatory standing supporting cross-border investment and capital flows | M31: Single point of contact across 30+ jurisdictions for multi-entity group structures | N31: High-net-worth families consolidating assets across jurisdictions | O31: Succession and inheritance planning for global families | P31: Asset protection from political, creditor, or matrimonial risks | Q31: Holding shares of a private trust company or family business | R31: Asset protection from third-party claims | S31: Multi-generational succession planning | T31: Confidentiality and privacy of beneficial ownership | U31: Flexible distribution control by trustee | V31: Trust | W31: Common Law | X31: Full | Y31: BVI Financial Services Commission Trustee Act 1993; Virgin Islands Special Trusts Act 2003 | Z31: No | AB31: Discretionary family trust for international HNW clients with multi-jurisdictional assets | AC31: CRS/FATCA reporting; trustee must hold valid BVI trust licence | AD31: 5530 | AE31: M | AG31: O | AI31: N/A | AK31: N/A | AL31: 0 | AM31: M | AO31: N/A | AQ31: N/A | AR31: 6500 | AS31: M | AT31: — | AU31: O | AV31: — | AW31: M | AX31: — | AY31: M | AZ31: 185 | BA31: M | BC31: M | BD31: 1300 | BE31: M | BF31: — | BG31: M | BI31: N/A | BK31: N/A | BM31: N/A | BO31: N/A | BQ31: N/A | BS31: N/A | BU31: N/A | BW31: N/A | BY31: N/A | CA31: N/A | CC31: N/A | CE31: N/A | CG31: N/A | CK31: N/A | CM31: N/A | CO31: N/A | CP31: 400 | CQ31: M | CR31: 300 | CS31: M | CT31: 125 | CU31: M | CW31: N/A | CY31: N/A | DA31: N/A | DB31: Administrative/Accounting services: USD 100-200/hr Other administrative services: USD 100-125/hr Other legal services: USD 125-175/hr Trust lawyer, manager or equivalent: USD 175-200/hr | DC31: O | DD31: =ROUND(0.075*SUM(AD31,AF31,AH31,AJ31,AL31,AN31,AP31,AR31,AT31,AV31,AX31,AZ31,BB31,BR31,BT31,BV31,BX31,BZ31,CB31,CD31,CF31,CJ31,CL31,CN31,CP31,CR31,CT31,CV31,CX31,CZ31),0) -> 978 | DE31: British Virgin Islands#Trust#British Virgin Islands Trust | DF31: =A31&"#"&C31&"#"&D31 -> British Virgin Islands#Trust#British Virgin Islands Trust | DG31: =DE31=DF31 -> TRUE
A32: British Virgin Islands | B32: Pedro Garcia | C32: Fund | D32: British Virgin Islands Ltd | E32: USD | F32: Private Limited Company offering limited liability with straightforward corporate governance. | G32: The British Virgin Islands Ltd is a fund structure regulated under local law and widely used by international clients of Amicorp. Private Limited Company offering limited liability with straightforward corporate governance. Our local team manages incorporation, ongoing administration, accounting, and compliance so you can focus on commercial objectives instead of paperwork. | H32: 4-6 weeks | I32: Annual audited financials, regulator filings, AML/KYC monitoring, and investor reporting | J32: Established British Virgin Islands legal framework familiar to investors, banks, and counterparties | K32: End-to-end Amicorp service: incorporation, registered office, directors, accounting, and reporting | L32: Treaty network and regulatory standing supporting cross-border investment and capital flows | M32: Single point of contact across 30+ jurisdictions for multi-entity group structures | N32: Asset managers launching regulated or private funds | O32: PE/VC sponsors raising committed capital from institutional LPs | P32: Family offices pooling investments across asset classes | Q32: Structured products and securitisation arrangers | R32: Pooled capital with professional management | S32: Investor-friendly structure with familiar legal precedent | T32: Tax-efficient flow-through or treaty-eligible vehicle | U32: Scalable for additional sub-funds or share classes | V32: Investment Fund (Private) | W32: Common Law | X32: Full | Y32: BVI Financial Services Commission Securities and Investment Business Act 2010; Investment Business (Approved Managers) Regulations 2012 | Z32: No | AA32: 1 | AB32: Closed-end private investment fund for sophisticated investors in a BVI company wrapper | AC32: Must register with FSC if offering to public; annual audit and reporting required | AE32: M | AG32: O | AI32: N/A | AK32: N/A | AL32: 0 | AM32: M | AO32: N/A | AP32: — | AQ32: M | AS32: N/A | AT32: — | AU32: O | AV32: — | AW32: M | AX32: — | AY32: M | AZ32: — | BA32: M | BC32: M | BD32: — | BE32: M | BF32: — | BG32: M | BI32: N/A | BK32: N/A | BM32: N/A | BO32: N/A | BQ32: N/A | BR32: 12000 | BS32: M | BU32: N/A | BW32: N/A | BY32: N/A | CA32: N/A | CB32: 2-8 Basispoints (2,000 USD per month minimum fee) | CC32: O | CE32: N/A | CG32: N/A | CH32: 5000 | CI32: O | CJ32: 2500 | CK32: O | CL32: 1500 | CM32: O | CN32: 1500 | CO32: O | CP32: 400 | CQ32: M | CR32: 300 | CS32: M | CT32: 125 | CU32: M | CW32: N/A | CY32: N/A | DA32: N/A | DB32: USD 100–750/hr (confirm with local office) | DC32: O | DD32: =ROUND(0.075*SUM(AD32,AF32,AH32,AJ32,AL32,AN32,AP32,AR32,AT32,AV32,AX32,AZ32,BB32,BR32,BT32,BV32,BX32,BZ32,CB32,CD32,CF32,CJ32,CL32,CN32,CP32,CR32,CT32,CV32,CX32,CZ32),0) -> 1374 | DE32: British Virgin Islands#Fund#British Virgin Islands Ltd | DF32: =A32&"#"&C32&"#"&D32 -> British Virgin Islands#Fund#British Virgin Islands Ltd | DG32: =DE32=DF32 -> TRUE
A33: British Virgin Islands | B33: Pedro Garcia | C33: Fund | D33: British Virgin Islands LP | E33: USD | F33: Limited Partnership offering flexible profit allocation and limited partner protection. | G33: The British Virgin Islands LP is a fund structure regulated under local law and widely used by international clients of Amicorp. Limited Partnership offering flexible profit allocation and limited partner protection. Our local team manages incorporation, ongoing administration, accounting, and compliance so you can focus on commercial objectives instead of paperwork. | H33: 4-6 weeks | I33: Annual audited financials, regulator filings, AML/KYC monitoring, and investor reporting | J33: Established British Virgin Islands legal framework familiar to investors, banks, and counterparties | K33: End-to-end Amicorp service: incorporation, registered office, directors, accounting, and reporting | L33: Treaty network and regulatory standing supporting cross-border investment and capital flows | M33: Single point of contact across 30+ jurisdictions for multi-entity group structures | N33: Asset managers launching regulated or private funds | O33: PE/VC sponsors raising committed capital from institutional LPs | P33: Family offices pooling investments across asset classes | Q33: Structured products and securitisation arrangers | R33: Pooled capital with professional management | S33: Investor-friendly structure with familiar legal precedent | T33: Tax-efficient flow-through or treaty-eligible vehicle | U33: Scalable for additional sub-funds or share classes | V33: Investment Fund (Private) | W33: Common Law | X33: Full for LPs; unlimited for GP | Y33: BVI Financial Services Commission Limited Partnership Act 1996 | Z33: No | AA33: 1 GP + 1 LP | AB33: PE/VC fund structure mirroring Cayman LP economics for Asian and European investors | AC33: GP unlimited liability unless corporate GP; limited BVI fund regulation vs Cayman | AE33: M | AG33: O | AI33: N/A | AK33: N/A | AL33: 0 | AM33: M | AO33: N/A | AP33: — | AQ33: M | AS33: N/A | AT33: — | AU33: O | AV33: — | AW33: M | AX33: — | AY33: M | AZ33: — | BA33: M | BC33: M | BD33: — | BE33: M | BF33: — | BG33: M | BI33: N/A | BK33: N/A | BM33: N/A | BO33: N/A | BQ33: N/A | BR33: 12000 | BS33: M | BU33: N/A | BW33: N/A | BY33: N/A | CA33: N/A | CB33: 2-8 Basispoints (2,000 USD per month minimum fee) | CC33: O | CE33: N/A | CG33: N/A | CH33: 5000 | CI33: O | CJ33: 2500 | CK33: O | CL33: 1500 | CM33: O | CN33: 1500 | CO33: O | CP33: 400 | CQ33: M | CR33: 300 | CS33: M | CT33: 125 | CU33: M | CW33: N/A | CY33: N/A | DA33: N/A | DB33: USD 100–750/hr (confirm with local office) | DC33: O | DD33: =ROUND(0.075*SUM(AD33,AF33,AH33,AJ33,AL33,AN33,AP33,AR33,AT33,AV33,AX33,AZ33,BB33,BR33,BT33,BV33,BX33,BZ33,CB33,CD33,CF33,CJ33,CL33,CN33,CP33,CR33,CT33,CV33,CX33,CZ33),0) -> 1374 | DE33: British Virgin Islands#Fund#British Virgin Islands LP | DF33: =A33&"#"&C33&"#"&D33 -> British Virgin Islands#Fund#British Virgin Islands LP | DG33: =DE33=DF33 -> TRUE
A34: British Virgin Islands | B34: Pedro Garcia | C34: Fund | D34: British Virgin Islands SPC | E34: USD | F34: Segregated Portfolio Company allowing creation of ring-fenced portfolios within a single legal entity. | G34: The British Virgin Islands SPC is a fund structure regulated under local law and widely used by international clients of Amicorp. Segregated Portfolio Company allowing creation of ring-fenced portfolios within a single legal entity. Our local team manages incorporation, ongoing administration, accounting, and compliance so you can focus on commercial objectives instead of paperwork. | H34: 4-6 weeks | I34: Annual audited financials, regulator filings, AML/KYC monitoring, and investor reporting | J34: Established British Virgin Islands legal framework familiar to investors, banks, and counterparties | K34: End-to-end Amicorp service: incorporation, registered office, directors, accounting, and reporting | L34: Treaty network and regulatory standing supporting cross-border investment and capital flows | M34: Single point of contact across 30+ jurisdictions for multi-entity group structures | N34: Asset managers launching regulated or private funds | O34: PE/VC sponsors raising committed capital from institutional LPs | P34: Family offices pooling investments across asset classes | Q34: Structured products and securitisation arrangers | R34: Pooled capital with professional management | S34: Investor-friendly structure with familiar legal precedent | T34: Tax-efficient flow-through or treaty-eligible vehicle | U34: Scalable for additional sub-funds or share classes | V34: Segregated Portfolio Company | W34: Common Law | X34: Full (statutory cell segregation) | Y34: BVI Financial Services Commission BVI Business Companies Act 2004 | Z34: No | AA34: 1 | AB34: Multi-strategy fund or insurance captive with separate legal portfolios in one entity | AC34: FSC approval required; cross-border recognition of cell segregation not guaranteed | AE34: M | AG34: O | AI34: N/A | AK34: N/A | AL34: 0 | AM34: M | AO34: N/A | AP34: — | AQ34: M | AS34: N/A | AT34: — | AU34: O | AV34: — | AW34: M | AX34: — | AY34: M | AZ34: — | BA34: M | BC34: M | BD34: — | BE34: M | BF34: — | BG34: M | BI34: N/A | BK34: N/A | BM34: N/A | BO34: N/A | BQ34: N/A | BR34: 12000 | BS34: M | BU34: N/A | BW34: N/A | BY34: N/A | CA34: N/A | CB34: 2-8 Basispoints (2,000 USD per month minimum fee) | CC34: O | CE34: N/A | CG34: N/A | CH34: 5000 | CI34: O | CJ34: 2500 | CK34: O | CL34: 1500 | CM34: O | CN34: 1500 | CO34: O | CP34: 400 | CQ34: M | CR34: 300 | CS34: M | CT34: 125 | CU34: M | CW34: N/A | CY34: N/A | DA34: N/A | DB34: USD 100–750/hr (confirm with local office) | DC34: O | DD34: =ROUND(0.075*SUM(AD34,AF34,AH34,AJ34,AL34,AN34,AP34,AR34,AT34,AV34,AX34,AZ34,BB34,BR34,BT34,BV34,BX34,BZ34,CB34,CD34,CF34,CJ34,CL34,CN34,CP34,CR34,CT34,CV34,CX34,CZ34),0) -> 1374 | DE34: British Virgin Islands#Fund#British Virgin Islands SPC | DF34: =A34&"#"&C34&"#"&D34 -> British Virgin Islands#Fund#British Virgin Islands SPC | DG34: =DE34=DF34 -> TRUE
A35: British Virgin Islands | B35: Pedro Garcia | C35: Fund | D35: British Virgin Islands Unit Trust | E35: USD | F35: Pooled investment vehicle where investors hold units representing beneficial interest. | G35: The British Virgin Islands Unit Trust is a fund structure regulated under local law and widely used by international clients of Amicorp. Pooled investment vehicle where investors hold units representing beneficial interest. Our local team manages incorporation, ongoing administration, accounting, and compliance so you can focus on commercial objectives instead of paperwork. | H35: 4-6 weeks | I35: Annual audited financials, regulator filings, AML/KYC monitoring, and investor reporting | J35: Established British Virgin Islands legal framework familiar to investors, banks, and counterparties | K35: End-to-end Amicorp service: incorporation, registered office, directors, accounting, and reporting | L35: Treaty network and regulatory standing supporting cross-border investment and capital flows | M35: Single point of contact across 30+ jurisdictions for multi-entity group structures | N35: Asset managers launching regulated or private funds | O35: PE/VC sponsors raising committed capital from institutional LPs | P35: Family offices pooling investments across asset classes | Q35: Structured products and securitisation arrangers | R35: Pooled capital with professional management | S35: Investor-friendly structure with familiar legal precedent | T35: Tax-efficient flow-through or treaty-eligible vehicle | U35: Scalable for additional sub-funds or share classes | V35: Investment Fund (Private) | W35: Common Law | X35: Full | Y35: BVI Financial Services Commission Securities and Investment Business Act 2010 | Z35: No | AA35: 1 trustee + 1 unitholder | AB35: Pooled investment trust for Asian investors preferring unit trust format | AC35: Trustee must hold BVI licence; FSC registration required | AE35: M | AG35: O | AI35: N/A | AK35: N/A | AL35: 0 | AM35: M | AO35: N/A | AP35: — | AQ35: M | AS35: N/A | AT35: — | AU35: O | AV35: — | AW35: M | AX35: — | AY35: M | AZ35: — | BA35: M | BC35: M | BD35: — | BE35: M | BF35: — | BG35: M | BI35: N/A | BK35: N/A | BM35: N/A | BO35: N/A | BQ35: N/A | BR35: 12000 | BS35: M | BU35: N/A | BW35: N/A | BY35: N/A | CA35: N/A | CB35: 2-8 Basispoints (2,000 USD per month minimum fee) | CC35: O | CE35: N/A | CG35: N/A | CH35: 5000 | CI35: O | CJ35: 2500 | CK35: O | CL35: 1500 | CM35: O | CN35: 1500 | CO35: O | CP35: 400 | CQ35: M | CR35: 300 | CS35: M | CT35: 125 | CU35: M | CW35: N/A | CY35: N/A | DA35: N/A | DB35: USD 100–750/hr (confirm with local office) | DC35: O | DD35: =ROUND(0.075*SUM(AD35,AF35,AH35,AJ35,AL35,AN35,AP35,AR35,AT35,AV35,AX35,AZ35,BB35,BR35,BT35,BV35,BX35,BZ35,CB35,CD35,CF35,CJ35,CL35,CN35,CP35,CR35,CT35,CV35,CX35,CZ35),0) -> 1374 | DE35: British Virgin Islands#Fund#British Virgin Islands Unit Trust | DF35: =A35&"#"&C35&"#"&D35 -> British Virgin Islands#Fund#British Virgin Islands Unit Trust | DG35: =DE35=DF35 -> TRUE
A36: British Virgin Islands | B36: Pedro Garcia | C36: Fund | D36: British Virgin Islands LLP | E36: USD | F36: Limited Liability Partnership combining partnership flexibility with limited liability. | G36: The British Virgin Islands LLP is a fund structure regulated under local law and widely used by international clients of Amicorp. Limited Liability Partnership combining partnership flexibility with limited liability. Our local team manages incorporation, ongoing administration, accounting, and compliance so you can focus on commercial objectives instead of paperwork. | H36: 4-6 weeks | I36: Annual audited financials, regulator filings, AML/KYC monitoring, and investor reporting | J36: Established British Virgin Islands legal framework familiar to investors, banks, and counterparties | K36: End-to-end Amicorp service: incorporation, registered office, directors, accounting, and reporting | L36: Treaty network and regulatory standing supporting cross-border investment and capital flows | M36: Single point of contact across 30+ jurisdictions for multi-entity group structures | N36: Asset managers launching regulated or private funds | O36: PE/VC sponsors raising committed capital from institutional LPs | P36: Family offices pooling investments across asset classes | Q36: Structured products and securitisation arrangers | R36: Pooled capital with professional management | S36: Investor-friendly structure with familiar legal precedent | T36: Tax-efficient flow-through or treaty-eligible vehicle | U36: Scalable for additional sub-funds or share classes | V36: Investment Fund (Private) | W36: Common Law | X36: Full (limited liability for all members) | Y36: BVI Financial Services Commission Limited Liability Partnership Act 2004 | Z36: No | AA36: 2+ | AB36: Carried interest vehicle or co-investment structure with flexible profit sharing | AC36: Less commonly used than LP for PE structures; limited market familiarity | AE36: M | AG36: O | AI36: N/A | AK36: N/A | AL36: 0 | AM36: M | AO36: N/A | AP36: — | AQ36: M | AS36: N/A | AT36: — | AU36: O | AV36: — | AW36: M | AX36: — | AY36: M | AZ36: — | BA36: M | BC36: M | BD36: — | BE36: M | BF36: — | BG36: M | BI36: N/A | BK36: N/A | BM36: N/A | BO36: N/A | BQ36: N/A | BR36: 12000 | BS36: M | BU36: N/A | BW36: N/A | BY36: N/A | CA36: N/A | CB36: 2-8 Basispoints (2,000 USD per month minimum fee) | CC36: O | CE36: N/A | CG36: N/A | CH36: 5000 | CI36: O | CJ36: 2500 | CK36: O | CL36: 1500 | CM36: O | CN36: 1500 | CO36: O | CP36: 400 | CQ36: M | CR36: 300 | CS36: M | CT36: 125 | CU36: M | CW36: N/A | CY36: N/A | DA36: N/A | DB36: USD 100–750/hr (confirm with local office) | DC36: O | DD36: =ROUND(0.075*SUM(AD36,AF36,AH36,AJ36,AL36,AN36,AP36,AR36,AT36,AV36,AX36,AZ36,BB36,BR36,BT36,BV36,BX36,BZ36,CB36,CD36,CF36,CJ36,CL36,CN36,CP36,CR36,CT36,CV36,CX36,CZ36),0) -> 1374 | DE36: British Virgin Islands#Fund#British Virgin Islands LLP | DF36: =A36&"#"&C36&"#"&D36 -> British Virgin Islands#Fund#British Virgin Islands LLP | DG36: =DE36=DF36 -> TRUE
A37: BARBADOS | DE37: ## | DF37: =A37&"#"&C37&"#"&D37 -> BARBADOS##
A38: Barbados | B38: Kimbert Solomon | C38: Company | D38: Barbados Domestic | E38: USD | F38: Domestic company incorporated under local laws for onshore business operations. | G38: The Barbados Domestic is a entity structure regulated under local law and widely used by international clients of Amicorp. Domestic company incorporated under local laws for onshore business operations. Our local team manages incorporation, ongoing administration, accounting, and compliance so you can focus on commercial objectives instead of paperwork. | H38: 3-7 business days | I38: Annual return, financial statements filing, and economic substance / UBO declarations | J38: Established Barbados legal framework familiar to investors, banks, and counterparties | K38: End-to-end Amicorp service: incorporation, registered office, directors, accounting, and reporting | L38: Treaty network and regulatory standing supporting cross-border investment and capital flows | M38: Single point of contact across 30+ jurisdictions for multi-entity group structures | N38: Holding investments into and out of Barbados | O38: Group holding companies and intermediate SPVs | P38: Joint ventures and shareholder agreements | Q38: Operating subsidiaries with local market access | R38: Limited liability for shareholders | S38: Separate legal entity | T38: Flexible management structure | U38: Tax efficient | V38: Limited Company | W38: Common Law | X38: Full | Y38: Corporate Affairs & Intellectual Property Office Companies Act Cap. 308 | Z38: Yes | AA38: 1 | AB38: Local operating company or financial services entity accessing Barbados tax treaty network | AC38: OECD substance requirements; Barbados subject to periodic FATF review | AD38: 3670 | AE38: M | AG38: O | AI38: N/A | AK38: N/A | AL38: 0 | AM38: M | AO38: N/A | AP38: 1610 | AQ38: M | AS38: N/A | AT38: 3850 | AU38: O | AV38: 2180 | AW38: 0 | AX38: — | AY38: M | AZ38: 500 | BA38: M | BC38: M | BD38: 800 | BE38: M | BF38: 750 | BG38: M | BI38: N/A | BK38: N/A | BM38: N/A | BO38: N/A | BQ38: N/A | BS38: N/A | BU38: N/A | BW38: N/A | BY38: N/A | CA38: N/A | CC38: N/A | CE38: N/A | CG38: N/A | CK38: N/A | CM38: N/A | CO38: N/A | CP38: 400 | CQ38: M | CS38: N/A | CU38: N/A | CW38: N/A | CY38: N/A | DA38: N/A | DB38: Administrative/Accounting services: USD 100-150/hr Corporate secretarial and legal services: USD 135-235/hr | DC38: O | DD38: =ROUND(0.075*SUM(AD38,AF38,AH38,AJ38,AL38,AN38,AP38,AR38,AT38,AV38,AX38,AZ38,BB38,BR38,BT38,BV38,BX38,BZ38,CB38,CD38,CF38,CJ38,CL38,CN38,CP38,CR38,CT38,CV38,CX38,CZ38),0) -> 916 | DE38: Barbados#Company#Barbados Domestic | DF38: =A38&"#"&C38&"#"&D38 -> Barbados#Company#Barbados Domestic | DG38: =DE38=DF38 -> TRUE
A39: Barbados | B39: Kimbert Solomon | C39: Company | D39: Barbados SRL | E39: USD | F39: Sociedad de Responsabilidad Limitada — a private limited liability company under civil law. | G39: The Barbados SRL is a entity structure regulated under local law and widely used by international clients of Amicorp. Sociedad de Responsabilidad Limitada — a private limited liability company under civil law. Our local team manages incorporation, ongoing administration, accounting, and compliance so you can focus on commercial objectives instead of paperwork. | H39: 3-7 business days | I39: Annual return, financial statements filing, and economic substance / UBO declarations | J39: Established Barbados legal framework familiar to investors, banks, and counterparties | K39: End-to-end Amicorp service: incorporation, registered office, directors, accounting, and reporting | L39: Treaty network and regulatory standing supporting cross-border investment and capital flows | M39: Single point of contact across 30+ jurisdictions for multi-entity group structures | N39: Holding investments into and out of Barbados | O39: Group holding companies and intermediate SPVs | P39: Joint ventures and shareholder agreements | Q39: Operating subsidiaries with local market access | R39: Limited liability for shareholders | S39: Separate legal entity | T39: Flexible management structure | U39: Tax efficient | V39: Limited Company | W39: Common Law | X39: Full | Y39: Corporate Affairs & Intellectual Property Office Companies Act Cap. 308 | Z39: Yes | AA39: 1 | AB39: Holding or operational company for regional Caribbean business activities | AC39: CRS reporting; substance requirements | AD39: 3200 | AE39: M | AG39: O | AI39: N/A | AK39: N/A | AL39: 0 | AM39: M | AO39: N/A | AP39: 2600 | AQ39: M | AS39: N/A | AT39: — | AU39: O | AV39: — | AW39: 0 | AX39: — | AY39: M | AZ39: — | BA39: M | BC39: M | BD39: — | BE39: M | BF39: — | BG39: M | BI39: N/A | BK39: N/A | BM39: N/A | BO39: N/A | BQ39: N/A | BS39: N/A | BU39: N/A | BW39: N/A | BY39: N/A | CA39: N/A | CC39: N/A | CE39: N/A | CG39: N/A | CK39: N/A | CM39: N/A | CO39: N/A | CP39: 400 | CQ39: M | CS39: N/A | CU39: N/A | CW39: N/A | CY39: N/A | DA39: N/A | DB39: USD 100–750/hr (confirm with local office) | DC39: O | DD39: =ROUND(0.075*SUM(AD39,AF39,AH39,AJ39,AL39,AN39,AP39,AR39,AT39,AV39,AX39,AZ39,BB39,BR39,BT39,BV39,BX39,BZ39,CB39,CD39,CF39,CJ39,CL39,CN39,CP39,CR39,CT39,CV39,CX39,CZ39),0) -> 465 | DE39: Barbados#Company#Barbados SRL | DF39: =A39&"#"&C39&"#"&D39 -> Barbados#Company#Barbados SRL | DG39: =DE39=DF39 -> TRUE
A40: Barbados | B40: Kimbert Solomon | C40: Company | D40: Barbados SCC | E40: USD | F40: Series Cell Company enabling segregated cell structures for efficient multi-asset management. | G40: The Barbados SCC is a entity structure regulated under local law and widely used by international clients of Amicorp. Series Cell Company enabling segregated cell structures for efficient multi-asset management. Our local team manages incorporation, ongoing administration, accounting, and compliance so you can focus on commercial objectives instead of paperwork. | H40: 3-7 business days | I40: Annual return, financial statements filing, and economic substance / UBO declarations | J40: Established Barbados legal framework familiar to investors, banks, and counterparties | K40: End-to-end Amicorp service: incorporation, registered office, directors, accounting, and reporting | L40: Treaty network and regulatory standing supporting cross-border investment and capital flows | M40: Single point of contact across 30+ jurisdictions for multi-entity group structures | N40: Holding investments into and out of Barbados | O40: Group holding companies and intermediate SPVs | P40: Joint ventures and shareholder agreements | Q40: Operating subsidiaries with local market access | R40: Limited liability for shareholders | S40: Separate legal entity | T40: Flexible management structure | U40: Tax efficient | V40: Segregated Portfolio Company | W40: Common Law | X40: Full (statutory cell segregation) | Y40: Corporate Affairs & Intellectual Property Office Segregated Cell Companies Act 2016 | Z40: Yes | AA40: 1 | AB40: Multi-class insurance captive or investment fund vehicle with ring-fenced sub-portfolios | AC40: Cell segregation not universally recognised; legal opinion required for cross-border structures | AD40: 5330 | AE40: M | AG40: O | AI40: N/A | AK40: N/A | AL40: 0 | AM40: M | AO40: N/A | AP40: 3080 | AQ40: M | AS40: N/A | AT40: 4240 | AU40: O | AV40: 2960 | AW40: 0 | AX40: — | AY40: M | AZ40: 500 | BA40: M | BC40: M | BD40: — | BE40: M | BF40: 1100 | BG40: M | BI40: N/A | BK40: N/A | BM40: N/A | BO40: N/A | BQ40: N/A | BS40: N/A | BU40: N/A | BW40: N/A | BY40: N/A | CA40: N/A | CC40: N/A | CE40: N/A | CG40: N/A | CK40: N/A | CM40: N/A | CO40: N/A | CP40: 400 | CQ40: M | CS40: N/A | CU40: N/A | CW40: N/A | CY40: N/A | DA40: N/A | DB40: USD 100–750/hr (confirm with local office) | DC40: O | DD40: =ROUND(0.075*SUM(AD40,AF40,AH40,AJ40,AL40,AN40,AP40,AR40,AT40,AV40,AX40,AZ40,BB40,BR40,BT40,BV40,BX40,BZ40,CB40,CD40,CF40,CJ40,CL40,CN40,CP40,CR40,CT40,CV40,CX40,CZ40),0) -> 1238 | DE40: Barbados#Company#Barbados SCC | DF40: =A40&"#"&C40&"#"&D40 -> Barbados#Company#Barbados SCC | DG40: =DE40=DF40 -> TRUE
A41: Barbados | B41: Kimbert Solomon | C41: Trust | D41: Barbados Trust with Swiss Trustee | E41: USD | F41: Trust administered by a Swiss-regulated professional trustee. | G41: The Barbados Trust with Swiss Trustee is a trust structure regulated under local law and widely used by international clients of Amicorp. Trust administered by a Swiss-regulated professional trustee. Our local team manages incorporation, ongoing administration, accounting, and compliance so you can focus on commercial objectives instead of paperwork. | H41: 5-10 business days | I41: Annual trustee review, beneficiary statements, FATCA/CRS reporting where applicable | J41: Established Barbados legal framework familiar to investors, banks, and counterparties | K41: End-to-end Amicorp service: incorporation, registered office, directors, accounting, and reporting | L41: Treaty network and regulatory standing supporting cross-border investment and capital flows | M41: Single point of contact across 30+ jurisdictions for multi-entity group structures | N41: High-net-worth families consolidating assets across jurisdictions | O41: Succession and inheritance planning for global families | P41: Asset protection from political, creditor, or matrimonial risks | Q41: Holding shares of a private trust company or family business | R41: Asset protection from third-party claims | S41: Multi-generational succession planning | T41: Confidentiality and privacy of beneficial ownership | U41: Flexible distribution control by trustee | V41: Trust | W41: Common Law | X41: Full | Y41: Financial Services Commission Barbados International Trusts Act Cap. 245 | Z41: No | AB41: International trust with Swiss-licensed trustee providing additional Swiss regulatory oversight | AC41: Higher trustee fees due to Swiss regulation; dual-jurisdiction reporting (CRS Barbados + CH) | AD41: 7000 | AE41: M | AG41: O | AI41: N/A | AK41: N/A | AL41: 0 | AM41: M | AO41: N/A | AQ41: N/A | AR41: 7000 | AS41: M | AT41: — | AU41: O | AV41: — | AW41: 0 | AX41: — | AY41: M | AZ41: 800 | BA41: M | BC41: M | BD41: 1000 | BE41: M | BF41: 650 | BG41: M | BI41: N/A | BK41: N/A | BM41: N/A | BO41: N/A | BQ41: N/A | BS41: N/A | BU41: N/A | BW41: N/A | BY41: N/A | CA41: N/A | CC41: N/A | CE41: N/A | CG41: N/A | CK41: N/A | CM41: N/A | CO41: N/A | CP41: 400 | CQ41: M | CS41: N/A | CU41: N/A | CW41: N/A | CY41: N/A | DA41: N/A | DB41: USD 100–750/hr (confirm with local office) | DC41: O | DD41: =ROUND(0.075*SUM(AD41,AF41,AH41,AJ41,AL41,AN41,AP41,AR41,AT41,AV41,AX41,AZ41,BB41,BR41,BT41,BV41,BX41,BZ41,CB41,CD41,CF41,CJ41,CL41,CN41,CP41,CR41,CT41,CV41,CX41,CZ41),0) -> 1140 | DE41: Barbados#Trust#Barbados Trust with Swiss Trustee | DF41: =A41&"#"&C41&"#"&D41 -> Barbados#Trust#Barbados Trust with Swiss Trustee | DG41: =DE41=DF41 -> TRUE
A42: Barbados | B42: Kimbert Solomon | C42: Fund | D42: Barbados Ltd | E42: USD | F42: Private Limited Company offering limited liability with straightforward corporate governance. | G42: The Barbados Ltd is a fund structure regulated under local law and widely used by international clients of Amicorp. Private Limited Company offering limited liability with straightforward corporate governance. Our local team manages incorporation, ongoing administration, accounting, and compliance so you can focus on commercial objectives instead of paperwork. | H42: 4-6 weeks | I42: Annual audited financials, regulator filings, AML/KYC monitoring, and investor reporting | J42: Established Barbados legal framework familiar to investors, banks, and counterparties | K42: End-to-end Amicorp service: incorporation, registered office, directors, accounting, and reporting | L42: Treaty network and regulatory standing supporting cross-border investment and capital flows | M42: Single point of contact across 30+ jurisdictions for multi-entity group structures | N42: Asset managers launching regulated or private funds | O42: PE/VC sponsors raising committed capital from institutional LPs | P42: Family offices pooling investments across asset classes | Q42: Structured products and securitisation arrangers | R42: Pooled capital with professional management | S42: Investor-friendly structure with familiar legal precedent | T42: Tax-efficient flow-through or treaty-eligible vehicle | U42: Scalable for additional sub-funds or share classes | V42: Investment Fund (Private) | W42: Common Law | X42: Full | Y42: Financial Services Commission Barbados Mutual Funds Act Cap. 320B | Z42: No | AA42: 1 | AB42: Private investment fund for accredited investors seeking Barbados treaty benefits | AC42: Must appoint FSC-licensed administrator; annual audited accounts | AE42: M | AG42: O | AI42: N/A | AK42: N/A | AL42: 0 | AM42: M | AO42: N/A | AP42: — | AQ42: M | AS42: N/A | AT42: — | AU42: O | AV42: — | AW42: M | AX42: — | AY42: M | AZ42: — | BA42: M | BC42: M | BD42: — | BE42: M | BF42: — | BG42: M | BI42: N/A | BK42: N/A | BM42: N/A | BO42: N/A | BQ42: N/A | BR42: 10000 | BS42: M | BU42: N/A | BW42: N/A | BY42: N/A | CA42: N/A | CB42: 2-8 Basispoints (2,000 USD per month minimum fee) | CC42: O | CE42: N/A | CG42: N/A | CH42: 5000 | CI42: O | CJ42: 2500 | CK42: O | CL42: 1500 | CM42: O | CN42: 1500 | CO42: O | CP42: 400 | CQ42: M | CS42: N/A | CU42: N/A | CW42: N/A | CY42: N/A | DA42: N/A | DB42: USD 100–750/hr (confirm with local office) | DC42: O | DD42: =ROUND(0.075*SUM(AD42,AF42,AH42,AJ42,AL42,AN42,AP42,AR42,AT42,AV42,AX42,AZ42,BB42,BR42,BT42,BV42,BX42,BZ42,CB42,CD42,CF42,CJ42,CL42,CN42,CP42,CR42,CT42,CV42,CX42,CZ42),0) -> 1193 | DE42: Barbados#Fund#Barbados Ltd | DF42: =A42&"#"&C42&"#"&D42 -> Barbados#Fund#Barbados Ltd | DG42: =DE42=DF42 -> TRUE
A43: Barbados | B43: Kimbert Solomon | C43: Fund | D43: Barbados SRL | E43: USD | F43: Sociedad de Responsabilidad Limitada — a private limited liability company under civil law. | G43: The Barbados SRL is a fund structure regulated under local law and widely used by international clients of Amicorp. Sociedad de Responsabilidad Limitada — a private limited liability company under civil law. Our local team manages incorporation, ongoing administration, accounting, and compliance so you can focus on commercial objectives instead of paperwork. | H43: 4-6 weeks | I43: Annual audited financials, regulator filings, AML/KYC monitoring, and investor reporting | J43: Established Barbados legal framework familiar to investors, banks, and counterparties | K43: End-to-end Amicorp service: incorporation, registered office, directors, accounting, and reporting | L43: Treaty network and regulatory standing supporting cross-border investment and capital flows | M43: Single point of contact across 30+ jurisdictions for multi-entity group structures | N43: Asset managers launching regulated or private funds | O43: PE/VC sponsors raising committed capital from institutional LPs | P43: Family offices pooling investments across asset classes | Q43: Structured products and securitisation arrangers | R43: Pooled capital with professional management | S43: Investor-friendly structure with familiar legal precedent | T43: Tax-efficient flow-through or treaty-eligible vehicle | U43: Scalable for additional sub-funds or share classes | V43: Investment Fund (Private) | W43: Common Law | X43: Full | Y43: Financial Services Commission Barbados Mutual Funds Act Cap. 320B | Z43: No | AA43: 1 | AB43: Fund vehicle structured as SRL for Latin American investor familiarity | AC43: FSC licensing; annual audit | AE43: M | AG43: O | AI43: N/A | AK43: N/A | AL43: 0 | AM43: M | AO43: N/A | AP43: — | AQ43: M | AS43: N/A | AT43: — | AU43: O | AV43: — | AW43: M | AX43: — | AY43: M | AZ43: — | BA43: M | BC43: M | BD43: — | BE43: M | BF43: — | BG43: M | BI43: N/A | BK43: N/A | BM43: N/A | BO43: N/A | BQ43: N/A | BR43: 10000 | BS43: M | BU43: N/A | BW43: N/A | BY43: N/A | CA43: N/A | CB43: 2-8 Basispoints (2,000 USD per month minimum fee) | CC43: O | CE43: N/A | CG43: N/A | CH43: 5000 | CI43: O | CJ43: 2500 | CK43: O | CL43: 1500 | CM43: O | CN43: 1500 | CO43: O | CP43: 400 | CQ43: M | CS43: N/A | CU43: N/A | CW43: N/A | CY43: N/A | DA43: N/A | DB43: USD 100–750/hr (confirm with local office) | DC43: O | DD43: =ROUND(0.075*SUM(AD43,AF43,AH43,AJ43,AL43,AN43,AP43,AR43,AT43,AV43,AX43,AZ43,BB43,BR43,BT43,BV43,BX43,BZ43,CB43,CD43,CF43,CJ43,CL43,CN43,CP43,CR43,CT43,CV43,CX43,CZ43),0) -> 1193 | DE43: Barbados#Fund#Barbados SRL | DF43: =A43&"#"&C43&"#"&D43 -> Barbados#Fund#Barbados SRL | DG43: =DE43=DF43 -> TRUE
A44: Barbados | B44: Kimbert Solomon | C44: Fund | D44: Barbados LP | E44: USD | F44: Limited Partnership offering flexible profit allocation and limited partner protection. | G44: The Barbados LP is a fund structure regulated under local law and widely used by international clients of Amicorp. Limited Partnership offering flexible profit allocation and limited partner protection. Our local team manages incorporation, ongoing administration, accounting, and compliance so you can focus on commercial objectives instead of paperwork. | H44: 4-6 weeks | I44: Annual audited financials, regulator filings, AML/KYC monitoring, and investor reporting | J44: Established Barbados legal framework familiar to investors, banks, and counterparties | K44: End-to-end Amicorp service: incorporation, registered office, directors, accounting, and reporting | L44: Treaty network and regulatory standing supporting cross-border investment and capital flows | M44: Single point of contact across 30+ jurisdictions for multi-entity group structures | N44: Asset managers launching regulated or private funds | O44: PE/VC sponsors raising committed capital from institutional LPs | P44: Family offices pooling investments across asset classes | Q44: Structured products and securitisation arrangers | R44: Pooled capital with professional management | S44: Investor-friendly structure with familiar legal precedent | T44: Tax-efficient flow-through or treaty-eligible vehicle | U44: Scalable for additional sub-funds or share classes | V44: Investment Fund (Private) | W44: Common Law | X44: Full for LPs; unlimited for GP | Y44: Financial Services Commission Barbados International Societies with Restricted Liability Act | Z44: No | AA44: 1 GP + 1 LP | AB44: PE fund structure for regional Caribbean and international investors | AC44: GP unlimited liability; FSC supervision | AE44: M | AG44: O | AI44: N/A | AK44: N/A | AL44: 0 | AM44: M | AO44: N/A | AP44: — | AQ44: M | AS44: N/A | AT44: — | AU44: O | AV44: — | AW44: M | AX44: — | AY44: M | AZ44: — | BA44: M | BC44: M | BD44: — | BE44: M | BF44: — | BG44: M | BI44: N/A | BK44: N/A | BM44: N/A | BO44: N/A | BQ44: N/A | BR44: 10000 | BS44: M | BU44: N/A | BW44: N/A | BY44: N/A | CA44: N/A | CB44: 2-8 Basispoints (2,000 USD per month minimum fee) | CC44: O | CE44: N/A | CG44: N/A | CH44: 5000 | CI44: O | CJ44: 2500 | CK44: O | CL44: 1500 | CM44: O | CN44: 1500 | CO44: O | CP44: 400 | CQ44: M | CS44: N/A | CU44: N/A | CW44: N/A | CY44: N/A | DA44: N/A | DB44: USD 100–750/hr (confirm with local office) | DC44: O | DD44: =ROUND(0.075*SUM(AD44,AF44,AH44,AJ44,AL44,AN44,AP44,AR44,AT44,AV44,AX44,AZ44,BB44,BR44,BT44,BV44,BX44,BZ44,CB44,CD44,CF44,CJ44,CL44,CN44,CP44,CR44,CT44,CV44,CX44,CZ44),0) -> 1193 | DE44: Barbados#Fund#Barbados LP | DF44: =A44&"#"&C44&"#"&D44 -> Barbados#Fund#Barbados LP | DG44: =DE44=DF44 -> TRUE
A45: Barbados | B45: Kimbert Solomon | C45: Fund | D45: Barbados Unit Trust | E45: USD | F45: Pooled investment vehicle where investors hold units representing beneficial interest. | G45: The Barbados Unit Trust is a fund structure regulated under local law and widely used by international clients of Amicorp. Pooled investment vehicle where investors hold units representing beneficial interest. Our local team manages incorporation, ongoing administration, accounting, and compliance so you can focus on commercial objectives instead of paperwork. | H45: 4-6 weeks | I45: Annual audited financials, regulator filings, AML/KYC monitoring, and investor reporting | J45: Established Barbados legal framework familiar to investors, banks, and counterparties | K45: End-to-end Amicorp service: incorporation, registered office, directors, accounting, and reporting | L45: Treaty network and regulatory standing supporting cross-border investment and capital flows | M45: Single point of contact across 30+ jurisdictions for multi-entity group structures | N45: Asset managers launching regulated or private funds | O45: PE/VC sponsors raising committed capital from institutional LPs | P45: Family offices pooling investments across asset classes | Q45: Structured products and securitisation arrangers | R45: Pooled capital with professional management | S45: Investor-friendly structure with familiar legal precedent | T45: Tax-efficient flow-through or treaty-eligible vehicle | U45: Scalable for additional sub-funds or share classes | V45: Investment Fund (Private) | W45: Common Law | X45: Full | Y45: Financial Services Commission Barbados Mutual Funds Act Cap. 320B | Z45: No | AA45: 1 trustee + 1 unitholder | AB45: Pooled investment trust for retail-facing fund structures in the Caribbean | AC45: Licensed trustee required; annual audit | AE45: M | AG45: O | AI45: N/A | AK45: N/A | AL45: 0 | AM45: M | AO45: N/A | AP45: — | AQ45: M | AS45: N/A | AT45: — | AU45: O | AV45: — | AW45: M | AX45: — | AY45: M | AZ45: — | BA45: M | BC45: M | BD45: — | BE45: M | BF45: — | BG45: M | BI45: N/A | BK45: N/A | BM45: N/A | BO45: N/A | BQ45: N/A | BR45: 10000 | BS45: M | BU45: N/A | BW45: N/A | BY45: N/A | CA45: N/A | CB45: 2-8 Basispoints (2,000 USD per month minimum fee) | CC45: O | CE45: N/A | CG45: N/A | CH45: 5000 | CI45: O | CJ45: 2500 | CK45: O | CL45: 1500 | CM45: O | CN45: 1500 | CO45: O | CP45: 400 | CQ45: M | CS45: N/A | CU45: N/A | CW45: N/A | CY45: N/A | DA45: N/A | DB45: USD 100–750/hr (confirm with local office) | DC45: O | DD45: =ROUND(0.075*SUM(AD45,AF45,AH45,AJ45,AL45,AN45,AP45,AR45,AT45,AV45,AX45,AZ45,BB45,BR45,BT45,BV45,BX45,BZ45,CB45,CD45,CF45,CJ45,CL45,CN45,CP45,CR45,CT45,CV45,CX45,CZ45),0) -> 1193 | DE45: Barbados#Fund#Barbados Unit Trust | DF45: =A45&"#"&C45&"#"&D45 -> Barbados#Fund#Barbados Unit Trust | DG45: =DE45=DF45 -> TRUE
A46: Barbados | B46: Kimbert Solomon | C46: Fund | D46: Barbados SCC | E46: USD | F46: Series Cell Company enabling segregated cell structures for efficient multi-asset management. | G46: The Barbados SCC is a fund structure regulated under local law and widely used by international clients of Amicorp. Series Cell Company enabling segregated cell structures for efficient multi-asset management. Our local team manages incorporation, ongoing administration, accounting, and compliance so you can focus on commercial objectives instead of paperwork. | H46: 4-6 weeks | I46: Annual audited financials, regulator filings, AML/KYC monitoring, and investor reporting | J46: Established Barbados legal framework familiar to investors, banks, and counterparties | K46: End-to-end Amicorp service: incorporation, registered office, directors, accounting, and reporting | L46: Treaty network and regulatory standing supporting cross-border investment and capital flows | M46: Single point of contact across 30+ jurisdictions for multi-entity group structures | N46: Asset managers launching regulated or private funds | O46: PE/VC sponsors raising committed capital from institutional LPs | P46: Family offices pooling investments across asset classes | Q46: Structured products and securitisation arrangers | R46: Pooled capital with professional management | S46: Investor-friendly structure with familiar legal precedent | T46: Tax-efficient flow-through or treaty-eligible vehicle | U46: Scalable for additional sub-funds or share classes | V46: Segregated Portfolio Company | W46: Common Law | X46: Full (statutory cell segregation) | Y46: Financial Services Commission Barbados Segregated Cell Companies Act 2016 | Z46: No | AA46: 1 | AB46: Multi-class fund with statutory cell separation for insurance or investment purposes | AC46: Cell recognition risk in foreign courts; annual audit required | AE46: M | AG46: O | AI46: N/A | AK46: N/A | AL46: 0 | AM46: M | AO46: N/A | AP46: 3080 | AQ46: M | AS46: N/A | AT46: 4240 | AU46: O | AV46: 2960 | AW46: M | AX46: — | AY46: M | AZ46: 500 | BA46: M | BC46: M | BD46: — | BE46: M | BF46: 1100 | BG46: M | BI46: N/A | BK46: N/A | BM46: N/A | BO46: N/A | BQ46: N/A | BR46: 5330 | BS46: M | BU46: N/A | BW46: N/A | BY46: N/A | CA46: N/A | CB46: 2-8 Basispoints (2,000 USD per month minimum fee) | CC46: O | CE46: N/A | CG46: N/A | CH46: 5000 | CI46: O | CJ46: 2500 | CK46: O | CL46: 1500 | CM46: O | CN46: 1500 | CO46: O | CP46: 400 | CQ46: M | CS46: N/A | CU46: N/A | CW46: N/A | CY46: N/A | DA46: N/A | DB46: USD 100–750/hr (confirm with local office) | DC46: O | DD46: =ROUND(0.075*SUM(AD46,AF46,AH46,AJ46,AL46,AN46,AP46,AR46,AT46,AV46,AX46,AZ46,BB46,BR46,BT46,BV46,BX46,BZ46,CB46,CD46,CF46,CJ46,CL46,CN46,CP46,CR46,CT46,CV46,CX46,CZ46),0) -> 1651 | DE46: Barbados#Fund#Barbados SCC | DF46: =A46&"#"&C46&"#"&D46 -> Barbados#Fund#Barbados SCC | DG46: =DE46=DF46 -> TRUE
A47: Barbados | C47: Company | D47: Barbados External Company | E47: USD | F47: External company registration allowing a foreign-incorporated company to operate from Barbados | G47: The Barbados External Company is the registration of a company incorporated outside Barbados that establishes a place of business in Barbados, giving access to the island's treaty network and professional infrastructure without re-incorporation. | H47: 5-10 business days | I47: Annual return with CAIPO, corporate income tax filing, financial statements, and UBO declarations | J47: Established Barbados legal framework familiar to investors, banks, and counterparties | K47: End-to-end Amicorp service: incorporation, registered office, directors, accounting, and reporting | L47: Treaty network and regulatory standing supporting cross-border investment and capital flows | M47: Single point of contact across 30+ jurisdictions for multi-entity group structures | N47: Foreign groups establishing a Barbados place of business | O47: Treaty-based holding and financing platforms | P47: Regional headquarters for Caribbean and Latin American operations | Q47: International business retaining original place of incorporation | R47: Registration of an existing foreign company — no re-incorporation required | S47: Access to Barbados's extensive double tax treaty network | T47: Low corporate tax rates on a sliding scale (5.5% to 1%) | U47: Continuity of corporate history and existing contracts | V47: External Company | W47: Common Law | X47: Per home jurisdiction of incorporation | Y47: Corporate Affairs and Intellectual Property Office (CAIPO) Companies Act, Cap. 308 | Z47: Yes | AA47: 1 | AB47: Foreign company operating from Barbados to access the treaty network and regional markets | AC47: Must maintain home-jurisdiction good standing; taxable presence in Barbados; annual dual compliance | AD47: 5330 | AE47: M | AG47: N/A | AI47: N/A | AK47: N/A | AM47: N/A | AO47: N/A | AP47: 3080 | AQ47: M | AS47: N/A | AT47: 4240 | AU47: O | AV47: 2960 | AW47: 0 | AY47: N/A | AZ47: 1500 | BA47: M | BC47: N/A | BD47: 800 | BE47: O | BF47: 750 | BG47: O | BI47: N/A | BK47: N/A | BM47: N/A | BO47: N/A | BQ47: N/A | BS47: N/A | BU47: N/A | BW47: N/A | BY47: N/A | CA47: N/A | CC47: N/A | CE47: N/A | CG47: N/A | CK47: N/A | CM47: N/A | CO47: N/A | CQ47: N/A | CS47: N/A | CU47: N/A | CW47: N/A | CY47: N/A | DA47: N/A | DB47: administrative/accounting services: USD 150-250/hr corporate secretarial and legal services: USD 150-400/hr | DC47: O | DD47: =ROUND(0.075*SUM(AD47,AF47,AH47,AJ47,AL47,AN47,AP47,AR47,AT47,AV47,AX47,AZ47,BB47,BR47,BT47,BV47,BX47,BZ47,CB47,CD47,CF47,CJ47,CL47,CN47,CP47,CR47,CT47,CV47,CX47,CZ47),0) -> 1283 | DE47: Barbados#Company#Barbados External Company | DF47: =A47&"#"&C47&"#"&D47 -> Barbados#Company#Barbados External Company | DG47: =DE47=DF47 -> TRUE
A48: CANADA
A49: Canada | C49: Partnership | D49: Canada LP | E49: USD | F49: Canadian Limited Partnership offering a flow-through vehicle with no entity-level Canadian tax for non-resident partners | G49: The Canada LP (typically formed in Ontario or British Columbia) is a fiscally transparent partnership; where partners are non-resident and no business is carried on in Canada, no Canadian tax filing obligation on profits generally arises, combining a respected G7 jurisdiction with flow-through treatment. | H49: 3-7 business days | I49: Annual registration renewal, partnership records maintenance, and FATCA/CRS classification where applicable | J49: Established Canada legal framework familiar to investors, banks, and counterparties | K49: End-to-end Amicorp service: incorporation, registered office, directors, accounting, and reporting | L49: Treaty network and regulatory standing supporting cross-border investment and capital flows | M49: Single point of contact across 30+ jurisdictions for multi-entity group structures | N49: Non-resident entrepreneurs invoicing international clients | O49: E-commerce and IT services businesses | P49: Flow-through investment holding for non-residents | Q49: Agency and trading structures with G7 credibility | R49: Fiscally transparent — profits taxed at partner level only | S49: No Canadian corporate tax if no Canadian business and non-resident partners | T49: Prestigious G7 jurisdiction with strong banking access | U49: General partner may be a corporate entity | V49: Limited Partnership | W49: Common Law | X49: Limited partners liable only up to contribution | Y49: Ontario Ministry of Public and Business Service Delivery Limited Partnerships Act (Ontario), R.S.O. 1990 | Z49: Yes (limited details) | AA49: 1 GP + 1 LP | AB49: Non-resident international trading or services business seeking a reputable flow-through vehicle | AC49: GP bears unlimited liability; Canadian-source income triggers filing; bank account opening requires substance | AD49: 9540 | AE49: M | AG49: N/A | AI49: N/A | AK49: N/A | AM49: N/A | AO49: N/A | AQ49: N/A | AS49: N/A | AU49: N/A | AV49: 1980 | AW49: M | AY49: N/A | BA49: N/A | BC49: N/A | BD49: 1000 | BE49: O | BG49: N/A | BI49: N/A | BK49: N/A | BM49: N/A | BO49: N/A | BQ49: N/A | BS49: N/A | BU49: N/A | BW49: N/A | BY49: N/A | CA49: N/A | CC49: N/A | CE49: N/A | CG49: N/A | CK49: N/A | CM49: N/A | CO49: N/A | CQ49: N/A | CS49: N/A | CU49: N/A | CW49: N/A | CY49: N/A | DA49: N/A | DC49: N/A | DD49: =ROUND(0.075*SUM(AD49,AF49,AH49,AJ49,AL49,AN49,AP49,AR49,AT49,AV49,AX49,AZ49,BB49,BR49,BT49,BV49,BX49,BZ49,CB49,CD49,CF49,CJ49,CL49,CN49,CP49,CR49,CT49,CV49,CX49,CZ49),0) -> 864 | DE49: Canada#Partnership#Canada LP | DF49: =A49&"#"&C49&"#"&D49 -> Canada#Partnership#Canada LP | DG49: =DE49=DF49 -> TRUE
A50: CAYMAN ISLANDS | DE50: ## | DF50: =A47&"#"&C47&"#"&D47 -> Barbados#Company#Barbados External Company
A51: Cayman Islands | B51: Kimbert Solomon | C51: Company | D51: Cayman Islands EXEMPT | E51: USD | F51: Exempt Company with tax-exempt status, ideal for holding companies, joint ventures, and SPVs. | G51: The Cayman Islands EXEMPT is a entity structure regulated under local law and widely used by international clients of Amicorp. Exempt Company with tax-exempt status, ideal for holding companies, joint ventures, and SPVs. Our local team manages incorporation, ongoing administration, accounting, and compliance so you can focus on commercial objectives instead of paperwork. | H51: 3-7 business days | I51: Annual return, financial statements filing, and economic substance / UBO declarations | J51: Established Cayman Islands legal framework familiar to investors, banks, and counterparties | K51: End-to-end Amicorp service: incorporation, registered office, directors, accounting, and reporting | L51: Treaty network and regulatory standing supporting cross-border investment and capital flows | M51: Single point of contact across 30+ jurisdictions for multi-entity group structures | N51: Holding investments into and out of Cayman Islands | O51: Group holding companies and intermediate SPVs | P51: Joint ventures and shareholder agreements | Q51: Operating subsidiaries with local market access | R51: Limited liability for shareholders | S51: Separate legal entity | T51: Flexible management structure | U51: Tax efficient | V51: Exempt Company | W51: Common Law | X51: Full | Y51: Cayman Islands Registrar of Companies Companies Act (2023 Revision) | Z51: No | AA51: 1 | AB51: Offshore holding company, SPV for structured finance, or fund GP vehicle | AC51: Economic substance rules; FATF monitoring; annual government fee | AD51: 2170 | AE51: M | AG51: O | AI51: N/A | AJ51: 150 | AK51: O | AL51: 0 | AM51: M | AN51: 1500 | AO51: O | AP51: 2230 | AQ51: M | AS51: N/A | AT51: — | AU51: O | AV51: 1910 | AW51: O | AX51: 1600 | AY51: O | AZ51: 1189.93 | BA51: M | BB51: 182.93 | BC51: M | BD51: — | BE51: M | BF51: — | BG51: M | BI51: N/A | BK51: N/A | BM51: N/A | BN51: 165 | BO51: O | BP51: 150 | BQ51: O | BS51: N/A | BU51: N/A | BW51: N/A | BY51: N/A | CA51: N/A | CC51: N/A | CE51: N/A | CG51: N/A | CK51: N/A | CM51: N/A | CO51: N/A | CP51: 400 | CQ51: M | CR51: 300 | CS51: M | CU51: N/A | CV51: 165 | CW51: M | CY51: N/A | DA51: N/A | DB51: USD 100–750/hr (confirm with local office) | DC51: O | DD51: =ROUND(0.075*SUM(AD51,AF51,AH51,AJ51,AL51,AN51,AP51,AR51,AT51,AV51,AX51,AZ51,BB51,BR51,BT51,BV51,BX51,BZ51,CB51,CD51,CF51,CJ51,CL51,CN51,CP51,CR51,CT51,CV51,CX51,CZ51),0) -> 885 | DE51: Cayman Islands#Company#Cayman Islands EXEMPT | DF51: =A51&"#"&C51&"#"&D51 -> Cayman Islands#Company#Cayman Islands EXEMPT | DG51: =DE51=DF51 -> TRUE
A52: Cayman Islands | B52: Kimbert Solomon | C52: Company | D52: Cayman Islands EXEMPT LP | E52: USD | F52: Exempted Limited Partnership combining tax exemption with limited liability partnership structure. | G52: The Cayman Islands EXEMPT LP is a entity structure regulated under local law and widely used by international clients of Amicorp. Exempted Limited Partnership combining tax exemption with limited liability partnership structure. Our local team manages incorporation, ongoing administration, accounting, and compliance so you can focus on commercial objectives instead of paperwork. | H52: 3-7 business days | I52: Annual return, financial statements filing, and economic substance / UBO declarations | J52: Established Cayman Islands legal framework familiar to investors, banks, and counterparties | K52: End-to-end Amicorp service: incorporation, registered office, directors, accounting, and reporting | L52: Treaty network and regulatory standing supporting cross-border investment and capital flows | M52: Single point of contact across 30+ jurisdictions for multi-entity group structures | N52: Holding investments into and out of Cayman Islands | O52: Group holding companies and intermediate SPVs | P52: Joint ventures and shareholder agreements | Q52: Operating subsidiaries with local market access | R52: Limited liability for shareholders | S52: Separate legal entity | T52: Flexible management structure | U52: Tax efficient | V52: Limited Partnership | W52: Common Law | X52: Full for LPs; unlimited for GP | Y52: Cayman Islands Registrar of Companies Exempted Limited Partnership Act (2021 Revision) | Z52: No | AA52: 1 GP + 1 LP | AB52: Preferred vehicle for Cayman-domiciled PE, VC, and hedge funds | AC52: GP unlimited liability; CIMA registration for investment funds | AD52: 5500 | AE52: M | AG52: O | AI52: N/A | AJ52: 380 | AK52: O | AL52: 0 | AM52: M | AN52: 1500 | AO52: O | AP52: 4200 | AQ52: M | AS52: N/A | AT52: — | AU52: O | AV52: 1910 | AW52: O | AX52: 1600 | AY52: O | AZ52: 1189.93 | BA52: M | BB52: 182.93 | BC52: M | BD52: — | BE52: M | BF52: — | BG52: M | BI52: N/A | BK52: N/A | BM52: N/A | BN52: 165 | BO52: O | BP52: 150 | BQ52: O | BS52: N/A | BU52: N/A | BW52: N/A | BY52: N/A | CA52: N/A | CC52: N/A | CE52: N/A | CG52: N/A | CK52: N/A | CM52: N/A | CO52: N/A | CP52: 400 | CQ52: M | CR52: 300 | CS52: M | CU52: N/A | CV52: 165 | CW52: M | CY52: N/A | DA52: N/A | DB52: USD 100–750/hr (confirm with local office) | DC52: O | DD52: =ROUND(0.075*SUM(AD52,AF52,AH52,AJ52,AL52,AN52,AP52,AR52,AT52,AV52,AX52,AZ52,BB52,BR52,BT52,BV52,BX52,BZ52,CB52,CD52,CF52,CJ52,CL52,CN52,CP52,CR52,CT52,CV52,CX52,CZ52),0) -> 1300 | DE52: Cayman Islands#Company#Cayman Islands EXEMPT LP | DF52: =A52&"#"&C52&"#"&D52 -> Cayman Islands#Company#Cayman Islands EXEMPT LP | DG52: =DE52=DF52 -> TRUE
A53: Cayman Islands | B53: Kimbert Solomon | C53: Company | D53: Cayman Islands Ordinary Non-Resident | E53: USD | F53: Ordinary non-resident company for specific offshore structuring needs. | G53: The Cayman Islands Ordinary Non-Resident is a entity structure regulated under local law and widely used by international clients of Amicorp. Ordinary non-resident company for specific offshore structuring needs. Our local team manages incorporation, ongoing administration, accounting, and compliance so you can focus on commercial objectives instead of paperwork. | H53: 3-7 business days | I53: Annual return, financial statements filing, and economic substance / UBO declarations | J53: Established Cayman Islands legal framework familiar to investors, banks, and counterparties | K53: End-to-end Amicorp service: incorporation, registered office, directors, accounting, and reporting | L53: Treaty network and regulatory standing supporting cross-border investment and capital flows | M53: Single point of contact across 30+ jurisdictions for multi-entity group structures | N53: Holding investments into and out of Cayman Islands | O53: Group holding companies and intermediate SPVs | P53: Joint ventures and shareholder agreements | Q53: Operating subsidiaries with local market access | R53: Limited liability for shareholders | S53: Separate legal entity | T53: Flexible management structure | U53: Tax efficient | V53: Limited Company | W53: Common Law | X53: Full | Y53: Cayman Islands Registrar of Companies Companies Act (2023 Revision) | Z53: No | AA53: 1 | AB53: Non-resident company for specific offshore purposes where exempt status not required | AC53: Cannot conduct business in Cayman; less common than Exempt Company | AD53: 5500 | AE53: M | AG53: O | AI53: N/A | AJ53: 380 | AK53: O | AL53: 0 | AM53: M | AN53: 1500 | AO53: O | AP53: 4200 | AQ53: M | AS53: N/A | AT53: — | AU53: O | AV53: 1910 | AW53: O | AX53: 1600 | AY53: O | AZ53: 1189.93 | BA53: M | BB53: 182.93 | BC53: M | BD53: — | BE53: M | BF53: — | BG53: M | BI53: N/A | BK53: N/A | BM53: N/A | BN53: 165 | BO53: O | BP53: 150 | BQ53: O | BS53: N/A | BU53: N/A | BW53: N/A | BY53: N/A | CA53: N/A | CC53: N/A | CE53: N/A | CG53: N/A | CK53: N/A | CM53: N/A | CO53: N/A | CP53: 400 | CQ53: M | CR53: 300 | CS53: M | CU53: N/A | CV53: 165 | CW53: M | CY53: N/A | DA53: N/A | DB53: USD 100–750/hr (confirm with local office) | DC53: O | DD53: =ROUND(0.075*SUM(AD53,AF53,AH53,AJ53,AL53,AN53,AP53,AR53,AT53,AV53,AX53,AZ53,BB53,BR53,BT53,BV53,BX53,BZ53,CB53,CD53,CF53,CJ53,CL53,CN53,CP53,CR53,CT53,CV53,CX53,CZ53),0) -> 1300 | DE53: Cayman Islands#Company#Cayman Islands Ordinary Non-Resident | DF53: =A53&"#"&C53&"#"&D53 -> Cayman Islands#Company#Cayman Islands Ordinary Non-Resident | DG53: =DE53=DF53 -> TRUE
A54: Cayman Islands | B54: Kimbert Solomon | C54: Company | D54: Cayman Islands SPC | E54: USD | F54: Segregated Portfolio Company allowing creation of ring-fenced portfolios within a single legal entity. | G54: The Cayman Islands SPC is a entity structure regulated under local law and widely used by international clients of Amicorp. Segregated Portfolio Company allowing creation of ring-fenced portfolios within a single legal entity. Our local team manages incorporation, ongoing administration, accounting, and compliance so you can focus on commercial objectives instead of paperwork. | H54: 3-7 business days | I54: Annual return, financial statements filing, and economic substance / UBO declarations | J54: Established Cayman Islands legal framework familiar to investors, banks, and counterparties | K54: End-to-end Amicorp service: incorporation, registered office, directors, accounting, and reporting | L54: Treaty network and regulatory standing supporting cross-border investment and capital flows | M54: Single point of contact across 30+ jurisdictions for multi-entity group structures | N54: Holding investments into and out of Cayman Islands | O54: Group holding companies and intermediate SPVs | P54: Joint ventures and shareholder agreements | Q54: Operating subsidiaries with local market access | R54: Limited liability for shareholders | S54: Separate legal entity | T54: Flexible management structure | U54: Tax efficient | V54: Segregated Portfolio Company | W54: Common Law | X54: Full (statutory cell segregation) | Y54: Cayman Islands Monetary Authority (CIMA) Companies Act (2023 Revision) Part XIV | Z54: No | AA54: 1 | AB54: Multi-class hedge fund or insurance captive with ring-fenced portfolios | AC54: CIMA licensing required; cross-border cell recognition not universal | AD54: 2170 | AE54: M | AG54: O | AI54: N/A | AJ54: 175 | AK54: O | AL54: 0 | AM54: M | AN54: 2000 | AO54: O | AP54: 2230 | AQ54: M | AS54: N/A | AT54: — | AU54: O | AV54: 1910 | AW54: O | AX54: 1600 | AY54: O | AZ54: 3446 | BA54: M | BB54: 182.93 | BC54: M | BD54: — | BE54: M | BF54: — | BG54: M | BI54: N/A | BK54: N/A | BM54: N/A | BN54: 165 | BO54: O | BP54: 440 | BQ54: O | BS54: N/A | BU54: N/A | BW54: N/A | BY54: N/A | CA54: N/A | CC54: N/A | CE54: N/A | CG54: N/A | CK54: N/A | CM54: N/A | CO54: N/A | CP54: 400 | CQ54: M | CR54: 300 | CS54: M | CU54: N/A | CV54: 165 | CW54: M | CY54: N/A | DA54: N/A | DB54: USD 100–750/hr (confirm with local office) | DC54: O | DD54: =ROUND(0.075*SUM(AD54,AF54,AH54,AJ54,AL54,AN54,AP54,AR54,AT54,AV54,AX54,AZ54,BB54,BR54,BT54,BV54,BX54,BZ54,CB54,CD54,CF54,CJ54,CL54,CN54,CP54,CR54,CT54,CV54,CX54,CZ54),0) -> 1093 | DE54: Cayman Islands#Company#Cayman Islands SPC | DF54: =A54&"#"&C54&"#"&D54 -> Cayman Islands#Company#Cayman Islands SPC | DG54: =DE54=DF54 -> TRUE
A55: Cayman Islands | B55: Kimbert Solomon | C55: Company | D55: Cayman Islands LLC | E55: USD | F55: Limited Liability Company combining partnership flexibility with corporate liability protection. | G55: The Cayman Islands LLC is a entity structure regulated under local law and widely used by international clients of Amicorp. Limited Liability Company combining partnership flexibility with corporate liability protection. Our local team manages incorporation, ongoing administration, accounting, and compliance so you can focus on commercial objectives instead of paperwork. | H55: 3-7 business days | I55: Annual return, financial statements filing, and economic substance / UBO declarations | J55: Established Cayman Islands legal framework familiar to investors, banks, and counterparties | K55: End-to-end Amicorp service: incorporation, registered office, directors, accounting, and reporting | L55: Treaty network and regulatory standing supporting cross-border investment and capital flows | M55: Single point of contact across 30+ jurisdictions for multi-entity group structures | N55: Holding investments into and out of Cayman Islands | O55: Group holding companies and intermediate SPVs | P55: Joint ventures and shareholder agreements | Q55: Operating subsidiaries with local market access | R55: Limited liability for members | S55: Pass-through or elective tax treatment | T55: Flexible management structure | U55: Lower administrative burden than corporations | V55: LLC | W55: Common Law | X55: Full | Y55: Cayman Islands Registrar of Companies Limited Liability Companies Act (2021 Revision) | Z55: No | AA55: 1 | AB55: Alternative to LP for PE/VC; US-style LLC for Delaware-equivalent offshore structures | AC55: Relatively new vehicle (2016); less tested than Exempt Company/ELP | AD55: 5500 | AE55: M | AG55: O | AI55: N/A | AJ55: 380 | AK55: O | AL55: 0 | AM55: M | AN55: 1500 | AO55: O | AP55: 4200 | AQ55: M | AS55: N/A | AT55: — | AU55: O | AV55: 1910 | AW55: M | AX55: 1600 | AY55: M | AZ55: 1189.93 | BA55: M | BB55: 182.93 | BC55: M | BD55: — | BE55: M | BF55: — | BG55: M | BI55: N/A | BK55: N/A | BM55: N/A | BN55: 165 | BO55: O | BP55: 150 | BQ55: O | BS55: N/A | BU55: N/A | BW55: N/A | BY55: N/A | CA55: N/A | CC55: N/A | CE55: N/A | CG55: N/A | CK55: N/A | CM55: N/A | CO55: N/A | CP55: 400 | CQ55: M | CR55: 300 | CS55: M | CU55: N/A | CV55: 165 | CW55: M | CY55: N/A | DA55: N/A | DB55: USD 100–750/hr (confirm with local office) | DC55: O | DD55: =ROUND(0.075*SUM(AD55,AF55,AH55,AJ55,AL55,AN55,AP55,AR55,AT55,AV55,AX55,AZ55,BB55,BR55,BT55,BV55,BX55,BZ55,CB55,CD55,CF55,CJ55,CL55,CN55,CP55,CR55,CT55,CV55,CX55,CZ55),0) -> 1300 | DE55: Cayman Islands#Company#Cayman Islands LLC | DF55: =A55&"#"&C55&"#"&D55 -> Cayman Islands#Company#Cayman Islands LLC | DG55: =DE55=DF55 -> TRUE
A56: Cayman Islands | B56: Kimbert Solomon | C56: Trust | D56: Cayman Islands Trust | E56: USD | F56: Discretionary or fixed trust structure for asset protection and succession planning. | G56: The Cayman Islands Trust is a trust structure regulated under local law and widely used by international clients of Amicorp. Discretionary or fixed trust structure for asset protection and succession planning. Our local team manages incorporation, ongoing administration, accounting, and compliance so you can focus on commercial objectives instead of paperwork. | H56: 5-10 business days | I56: Annual trustee review, beneficiary statements, FATCA/CRS reporting where applicable | J56: Established Cayman Islands legal framework familiar to investors, banks, and counterparties | K56: End-to-end Amicorp service: incorporation, registered office, directors, accounting, and reporting | L56: Treaty network and regulatory standing supporting cross-border investment and capital flows | M56: Single point of contact across 30+ jurisdictions for multi-entity group structures | N56: High-net-worth families consolidating assets across jurisdictions | O56: Succession and inheritance planning for global families | P56: Asset protection from political, creditor, or matrimonial risks | Q56: Holding shares of a private trust company or family business | R56: Asset protection from third-party claims | S56: Multi-generational succession planning | T56: Confidentiality and privacy of beneficial ownership | U56: Flexible distribution control by trustee | V56: Trust | W56: Common Law | X56: Full | Y56: Cayman Islands Monetary Authority (CIMA) Trusts Act (2021 Revision) | Z56: No | AB56: International discretionary trust for HNW families with global assets | AC56: CRS reporting; trustee must hold CIMA licence | AD56: 6940 | AE56: M | AG56: O | AI56: N/A | AK56: N/A | AL56: 0 | AM56: M | AN56: 1500 | AO56: O | AQ56: N/A | AR56: 6940 | AS56: M | AT56: — | AU56: O | AV56: — | AW56: M | AX56: — | AY56: M | AZ56: — | BA56: M | BC56: M | BD56: 1000 | BE56: M | BF56: — | BG56: M | BI56: N/A | BK56: N/A | BM56: N/A | BN56: 165 | BO56: O | BQ56: N/A | BS56: N/A | BU56: N/A | BW56: N/A | BY56: N/A | CA56: N/A | CC56: N/A | CE56: N/A | CG56: N/A | CK56: N/A | CM56: N/A | CO56: N/A | CP56: 400 | CQ56: M | CR56: 300 | CS56: M | CU56: N/A | CV56: 165 | CW56: M | CY56: N/A | DA56: N/A | DB56: Other legal services: USD 150-250/hr | DC56: O | DD56: =ROUND(0.075*SUM(AD56,AF56,AH56,AJ56,AL56,AN56,AP56,AR56,AT56,AV56,AX56,AZ56,BB56,BR56,BT56,BV56,BX56,BZ56,CB56,CD56,CF56,CJ56,CL56,CN56,CP56,CR56,CT56,CV56,CX56,CZ56),0) -> 1218 | DE56: Cayman Islands#Trust#Cayman Islands Trust | DF56: =A56&"#"&C56&"#"&D56 -> Cayman Islands#Trust#Cayman Islands Trust | DG56: =DE56=DF56 -> TRUE
A57: Cayman Islands | B57: Kimbert Solomon | C57: Trust | D57: Cayman Islands Star Trust | E57: USD | F57: Cayman STAR Trust — Special Trusts (Alternative Regime) for purpose trusts. | G57: The Cayman Islands Star Trust is a trust structure regulated under local law and widely used by international clients of Amicorp. Cayman STAR Trust — Special Trusts (Alternative Regime) for purpose trusts. Our local team manages incorporation, ongoing administration, accounting, and compliance so you can focus on commercial objectives instead of paperwork. | H57: 5-10 business days | I57: Annual trustee review, beneficiary statements, FATCA/CRS reporting where applicable | J57: Established Cayman Islands legal framework familiar to investors, banks, and counterparties | K57: End-to-end Amicorp service: incorporation, registered office, directors, accounting, and reporting | L57: Treaty network and regulatory standing supporting cross-border investment and capital flows | M57: Single point of contact across 30+ jurisdictions for multi-entity group structures | N57: High-net-worth families consolidating assets across jurisdictions | O57: Succession and inheritance planning for global families | P57: Asset protection from political, creditor, or matrimonial risks | Q57: Holding shares of a private trust company or family business | R57: Asset protection from third-party claims | S57: Multi-generational succession planning | T57: Confidentiality and privacy of beneficial ownership | U57: Flexible distribution control by trustee | V57: Trust (Purpose Trust) | W57: Common Law | X57: Full | Y57: Cayman Islands Monetary Authority (CIMA) Special Trusts (Alternative Regime) Law 1997 (STAR) | Z57: No | AB57: Orphan structure for securitisation SPVs or charitable/non-charitable purpose trusts | AC57: Enforcer required; limited to specific purposes; complex drafting required | AD57: 6940 | AE57: M | AG57: O | AI57: N/A | AK57: N/A | AL57: 0 | AM57: M | AN57: 1500 | AO57: O | AQ57: N/A | AR57: 6940 | AS57: M | AT57: — | AU57: O | AV57: — | AW57: M | AX57: — | AY57: M | AZ57: — | BA57: M | BC57: M | BD57: 1000 | BE57: M | BF57: — | BG57: M | BI57: N/A | BK57: N/A | BM57: N/A | BN57: 165 | BO57: O | BQ57: N/A | BS57: N/A | BU57: N/A | BW57: N/A | BY57: N/A | CA57: N/A | CC57: N/A | CE57: N/A | CG57: N/A | CK57: N/A | CM57: N/A | CO57: N/A | CP57: 400 | CQ57: M | CR57: 300 | CS57: M | CU57: N/A | CV57: 165 | CW57: M | CY57: N/A | DA57: N/A | DB57: USD 350-650/hr USD 250-350/hr | DC57: O | DD57: =ROUND(0.075*SUM(AD57,AF57,AH57,AJ57,AL57,AN57,AP57,AR57,AT57,AV57,AX57,AZ57,BB57,BR57,BT57,BV57,BX57,BZ57,CB57,CD57,CF57,CJ57,CL57,CN57,CP57,CR57,CT57,CV57,CX57,CZ57),0) -> 1218 | DE57: Cayman Islands#Trust#Cayman Islands Star Trust | DF57: =A57&"#"&C57&"#"&D57 -> Cayman Islands#Trust#Cayman Islands Star Trust | DG57: =DE57=DF57 -> TRUE
A58: Cayman Islands | B58: Craig Lyall | C58: Fund - compartment | D58: Cayman Islands Investment Fund Compartment | E58: USD | F58: New share class / compartment within existing Cayman Islands Investment Fund Compartment, enabling rapid market entry via a CIMA-regulated platform with full administrative support. | G58: Cayman Islands Investment Fund Compartment — New Share Class / Compartment. Rather than establishing a standalone fund from scratch, investors and managers subscribe to a new share class within this existing, fully operational fund structure. All regulatory approvals, administrative infrastructure, compliance frameworks, AML/KYC processes, auditing relationships, and legal documentation are already in place. This dramatically reduces both time-to-market and costs, allowing managers to focus on investment strategy rather than operational build-out. A single annual fee of 0.45% AUA covers all services including administration, NAV calculation, regulatory filings, transfer agent, MLRO, audit coordination, and compliance. | H58: 2-4 weeks | I58: Annual fee of 0.45% AUA covers all services: administration, NAV, regulatory filings, audit coordination, compliance, MLRO, and reporting | J58: Rapid time-to-market: launch within weeks by leveraging an existing, fully licensed fund structure | K58: Zero infrastructure build-out: fund administration, compliance, AML/KYC, and audit already in place | L58: Cost-effective entry: share class setup at USD 15,000 versus USD 50,000–100,000+ for a standalone fund | M58: Ongoing all-inclusive fee of 0.45% AUA covers all administration, regulatory filings, and reporting | N58: Investment managers seeking fast, low-cost market entry on a proven, regulated platform | O58: Boutique asset managers and emerging market specialists without existing fund infrastructure | P58: Family offices and institutional investors requiring a regulated vehicle with minimal setup time | Q58: Managers launching niche or thematic strategies within an existing umbrella fund | R58: Plug-and-play fund infrastructure: regulation, administration, and compliance already operational | S58: Single all-inclusive annual fee of 0.45% AUA — no hidden costs across any service line | T58: Statutory separation of assets where applicable (SPC) or clearly defined share class economics | U58: Access to established fund directors, legal counsel, auditors, and prime broker relationships | V58: Investment Fund (Regulated) | W58: Common Law | X58: Full | Y58: Cayman Islands Monetary Authority (CIMA) Mutual Funds Act (2021 Revision) | Z58: No | AA58: 1 | AB58: Investment manager or fund promoter seeking rapid, cost-efficient launch of a new strategy or share class within a regulated, fully operational fund platform | AC58: CIMA annual reporting; AML/KYC obligations; annual audit required; existing fund compliance obligations apply | AE58: O | AG58: O | AI58: N/A | AK58: N/A | AM58: N/A | AO58: N/A | AQ58: N/A | AS58: N/A | AU58: O | AW58: O | AY58: O | BA58: O | BC58: O | BE58: O | BG58: O | BI58: N/A | BK58: N/A | BM58: N/A | BO58: N/A | BQ58: N/A | BS58: N/A | BT58: 15000 | BU58: O | BW58: N/A | BY58: N/A | CA58: N/A | CB58: 0.45 | CC58: O | CE58: N/A | CG58: N/A | CH58: 2500 | CJ58: 2500 | CK58: O | CL58: Included | CM58: O | CN58: Included | CO58: O | CP58: 400 | CQ58: M | CR58: 300 | CS58: M | CU58: N/A | CV58: 165 | CW58: M | CX58: Included | CY58: O | CZ58: Included | DA58: O | DB58: USD 100–750/hr (confirm with local office) | DC58: O | DD58: =ROUND(0.075*SUM(AD58,AF58,AH58,AJ58,AL58,AN58,AP58,AR58,AT58,AV58,AX58,AZ58,BB58,BR58,BT58,BV58,BX58,BZ58,CB58,CD58,CF58,CJ58,CL58,CN58,CP58,CR58,CT58,CV58,CX58,CZ58),0) -> 1377 | DE58: Cayman Islands#Fund#Cayman Islands Investment Fund Compartment | DF58: =A58&"#"&C58&"#"&D58 -> Cayman Islands#Fund - compartment#Cayman Islands Investment Fund Compartment | DG58: =DE58=DF58 -> FALSE
A59: Cayman Islands | B59: Kimbert Solomon | C59: Fund | D59: Cayman Islands Exempt Company | E59: USD | F59: Cayman exempt company structured as a regulated investment fund. | G59: The Cayman Islands Exempt Company is a fund structure regulated under local law and widely used by international clients of Amicorp. Cayman exempt company structured as a regulated investment fund. Our local team manages incorporation, ongoing administration, accounting, and compliance so you can focus on commercial objectives instead of paperwork. | H59: 4-6 weeks | I59: Annual audited financials, regulator filings, AML/KYC monitoring, and investor reporting | J59: Established Cayman Islands legal framework familiar to investors, banks, and counterparties | K59: End-to-end Amicorp service: incorporation, registered office, directors, accounting, and reporting | L59: Treaty network and regulatory standing supporting cross-border investment and capital flows | M59: Single point of contact across 30+ jurisdictions for multi-entity group structures | N59: Asset managers launching regulated or private funds | O59: PE/VC sponsors raising committed capital from institutional LPs | P59: Family offices pooling investments across asset classes | Q59: Structured products and securitisation arrangers | R59: Pooled capital with professional management | S59: Investor-friendly structure with familiar legal precedent | T59: Tax-efficient flow-through or treaty-eligible vehicle | U59: Scalable for additional sub-funds or share classes | V59: Investment Fund (Regulated) | W59: Common Law | X59: Full | Y59: Cayman Islands Monetary Authority (CIMA) Mutual Funds Act (2021 Revision) | Z59: No | AA59: 1 | AB59: Open-ended hedge fund for institutional investors in a Cayman company wrapper | AC59: CIMA annual reporting; AML/KYC obligations; annual audit required | AE59: M | AG59: O | AI59: N/A | AK59: N/A | AL59: 0 | AM59: M | AO59: N/A | AQ59: M | AS59: N/A | AT59: — | AU59: O | AW59: O | AY59: M | AZ59: 1189.93 | BA59: M | BB59: 182.93 | BC59: M | BD59: — | BE59: M | BF59: — | BG59: M | BI59: N/A | BK59: N/A | BM59: N/A | BO59: N/A | BQ59: N/A | BR59: 15000 | BS59: M | BU59: N/A | BW59: N/A | BY59: N/A | CA59: N/A | CB59: 2-8 Basispoints (min 2,000 USD per month) | CC59: O | CE59: N/A | CG59: N/A | CH59: 5000 | CI59: O | CJ59: 2500 | CK59: O | CL59: 1500 | CM59: O | CN59: 1500 | CO59: O | CP59: 400 | CQ59: M | CR59: 300 | CS59: M | CU59: N/A | CV59: 165 | CW59: M | CY59: N/A | DA59: N/A | DB59: USD 100–750/hr (confirm with local office) | DC59: O | DD59: =ROUND(0.075*SUM(AD59,AF59,AH59,AJ59,AL59,AN59,AP59,AR59,AT59,AV59,AX59,AZ59,BB59,BR59,BT59,BV59,BX59,BZ59,CB59,CD59,CF59,CJ59,CL59,CN59,CP59,CR59,CT59,CV59,CX59,CZ59),0) -> 1705 | DE59: Cayman Islands#Fund#Cayman Islands Exempt Company | DF59: =A59&"#"&C59&"#"&D59 -> Cayman Islands#Fund#Cayman Islands Exempt Company | DG59: =DE59=DF59 -> TRUE
A60: Cayman Islands | B60: Kimbert Solomon | C60: Fund | D60: Cayman Islands Exempt LP | E60: USD | F60: Exempted Limited Partnership, the most popular vehicle for PE/VC/RE funds. | G60: The Cayman Islands Exempt LP is a fund structure regulated under local law and widely used by international clients of Amicorp. Exempted Limited Partnership, the most popular vehicle for PE/VC/RE funds. Our local team manages incorporation, ongoing administration, accounting, and compliance so you can focus on commercial objectives instead of paperwork. | H60: 4-6 weeks | I60: Annual audited financials, regulator filings, AML/KYC monitoring, and investor reporting | J60: Established Cayman Islands legal framework familiar to investors, banks, and counterparties | K60: End-to-end Amicorp service: incorporation, registered office, directors, accounting, and reporting | L60: Treaty network and regulatory standing supporting cross-border investment and capital flows | M60: Single point of contact across 30+ jurisdictions for multi-entity group structures | N60: Asset managers launching regulated or private funds | O60: PE/VC sponsors raising committed capital from institutional LPs | P60: Family offices pooling investments across asset classes | Q60: Structured products and securitisation arrangers | R60: Pooled capital with professional management | S60: Investor-friendly structure with familiar legal precedent | T60: Tax-efficient flow-through or treaty-eligible vehicle | U60: Scalable for additional sub-funds or share classes | V60: Investment Fund (AIF) | W60: Common Law | X60: Full for LPs | Y60: Cayman Islands Monetary Authority (CIMA) Exempted Limited Partnership Act; Mutual Funds Act | Z60: No | AA60: 1 GP + 1 LP | AB60: Global PE/VC fund structure; preferred by US and European institutional investors | AC60: GP unlimited liability; CIMA registration; annual audit | AE60: M | AG60: O | AI60: N/A | AK60: N/A | AL60: 0 | AM60: M | AO60: N/A | AP60: — | AQ60: M | AS60: N/A | AT60: — | AU60: O | AY60: M | AZ60: 1189.93 | BA60: M | BB60: 182.93 | BC60: M | BD60: — | BE60: M | BF60: — | BG60: M | BI60: N/A | BK60: N/A | BM60: N/A | BO60: N/A | BQ60: N/A | BR60: 15000 | BS60: M | BU60: N/A | BW60: N/A | BY60: N/A | CA60: N/A | CB60: 2-8 Basispoints (min 2,000 USD per month) | CC60: O | CE60: N/A | CG60: N/A | CH60: 5000 | CI60: O | CJ60: 2500 | CK60: O | CL60: 1500 | CM60: O | CN60: 1500 | CO60: O | CP60: 400 | CQ60: M | CR60: 300 | CS60: M | CU60: N/A | CV60: 165 | CW60: M | CY60: N/A | DA60: N/A | DB60: USD 100–750/hr (confirm with local office) | DC60: O | DD60: =ROUND(0.075*SUM(AD60,AF60,AH60,AJ60,AL60,AN60,AP60,AR60,AT60,AV60,AX60,AZ60,BB60,BR60,BT60,BV60,BX60,BZ60,CB60,CD60,CF60,CJ60,CL60,CN60,CP60,CR60,CT60,CV60,CX60,CZ60),0) -> 1705 | DE60: Cayman Islands#Fund#Cayman Islands Exempt LP | DF60: =A60&"#"&C60&"#"&D60 -> Cayman Islands#Fund#Cayman Islands Exempt LP | DG60: =DE60=DF60 -> TRUE
A61: Cayman Islands | B61: Kimbert Solomon | C61: Fund | D61: Cayman Islands LLC | E61: USD | F61: Limited Liability Company combining partnership flexibility with corporate liability protection. | G61: The Cayman Islands LLC is a fund structure regulated under local law and widely used by international clients of Amicorp. Limited Liability Company combining partnership flexibility with corporate liability protection. Our local team manages incorporation, ongoing administration, accounting, and compliance so you can focus on commercial objectives instead of paperwork. | H61: 4-6 weeks | I61: Annual audited financials, regulator filings, AML/KYC monitoring, and investor reporting | J61: Established Cayman Islands legal framework familiar to investors, banks, and counterparties | K61: End-to-end Amicorp service: incorporation, registered office, directors, accounting, and reporting | L61: Treaty network and regulatory standing supporting cross-border investment and capital flows | M61: Single point of contact across 30+ jurisdictions for multi-entity group structures | N61: Asset managers launching regulated or private funds | O61: PE/VC sponsors raising committed capital from institutional LPs | P61: Family offices pooling investments across asset classes | Q61: Structured products and securitisation arrangers | R61: Pooled capital with professional management | S61: Investor-friendly structure with familiar legal precedent | T61: Tax-efficient flow-through or treaty-eligible vehicle | U61: Scalable for additional sub-funds or share classes | V61: Investment Fund (AIF) | W61: Common Law | X61: Full | Y61: Cayman Islands Monetary Authority (CIMA) Limited Liability Companies Act; Mutual Funds Act | Z61: No | AA61: 1 | AB61: Alternative to ELP for fund structures; US family office or co-investment vehicles | AC61: Newer structure; less precedent than ELP; CIMA registration | AE61: M | AG61: O | AI61: N/A | AK61: N/A | AL61: 0 | AM61: M | AO61: N/A | AP61: — | AQ61: M | AS61: N/A | AT61: — | AU61: O | AW61: M | AY61: M | AZ61: 1189.93 | BA61: M | BB61: 182.93 | BC61: M | BD61: — | BE61: M | BF61: — | BG61: M | BI61: N/A | BK61: N/A | BM61: N/A | BO61: N/A | BQ61: N/A | BR61: 15000 | BS61: M | BU61: N/A | BW61: N/A | BY61: N/A | CA61: N/A | CB61: 2-8 Basispoints (min 2,000 USD per month) | CC61: O | CE61: N/A | CG61: N/A | CH61: 10000 | CI61: O | CJ61: 2500 | CK61: O | CL61: 1500 | CM61: O | CN61: 1500 | CO61: O | CP61: 400 | CQ61: M | CR61: 300 | CS61: M | CU61: N/A | CV61: 165 | CW61: M | CY61: N/A | DA61: N/A | DB61: USD 100–750/hr (confirm with local office) | DC61: O | DD61: =ROUND(0.075*SUM(AD61,AF61,AH61,AJ61,AL61,AN61,AP61,AR61,AT61,AV61,AX61,AZ61,BB61,BR61,BT61,BV61,BX61,BZ61,CB61,CD61,CF61,CJ61,CL61,CN61,CP61,CR61,CT61,CV61,CX61,CZ61),0) -> 1705 | DE61: Cayman Islands#Fund#Cayman Islands LLC | DF61: =A61&"#"&C61&"#"&D61 -> Cayman Islands#Fund#Cayman Islands LLC | DG61: =DE61=DF61 -> TRUE
A62: Cayman Islands | B62: Kimbert Solomon | C62: Fund | D62: Cayman Islands SPC | E62: USD | F62: Segregated Portfolio Company allowing creation of ring-fenced portfolios within a single legal entity. | G62: The Cayman Islands SPC is a fund structure regulated under local law and widely used by international clients of Amicorp. Segregated Portfolio Company allowing creation of ring-fenced portfolios within a single legal entity. Our local team manages incorporation, ongoing administration, accounting, and compliance so you can focus on commercial objectives instead of paperwork. | H62: 4-6 weeks | I62: Annual audited financials, regulator filings, AML/KYC monitoring, and investor reporting | J62: Established Cayman Islands legal framework familiar to investors, banks, and counterparties | K62: End-to-end Amicorp service: incorporation, registered office, directors, accounting, and reporting | L62: Treaty network and regulatory standing supporting cross-border investment and capital flows | M62: Single point of contact across 30+ jurisdictions for multi-entity group structures | N62: Asset managers launching regulated or private funds | O62: PE/VC sponsors raising committed capital from institutional LPs | P62: Family offices pooling investments across asset classes | Q62: Structured products and securitisation arrangers | R62: Pooled capital with professional management | S62: Investor-friendly structure with familiar legal precedent | T62: Tax-efficient flow-through or treaty-eligible vehicle | U62: Scalable for additional sub-funds or share classes | V62: Segregated Portfolio Company | W62: Common Law | X62: Full (statutory cell segregation) | Y62: Cayman Islands Monetary Authority (CIMA) Companies Act (2023 Revision) Part XIV; Mutual Funds Act | Z62: No | AA62: 1 | AB62: Multi-strategy fund with legally segregated portfolios; insurance-linked securities | AC62: CIMA licensing; directors must understand cross-portfolio contamination risks | AE62: M | AG62: O | AI62: N/A | AK62: N/A | AL62: 0 | AM62: M | AO62: N/A | AQ62: M | AS62: N/A | AT62: — | AU62: O | AW62: M | AY62: M | AZ62: 3446 | BA62: M | BB62: 182.93 | BC62: M | BD62: — | BE62: M | BF62: — | BG62: M | BI62: N/A | BK62: N/A | BM62: N/A | BO62: N/A | BQ62: N/A | BR62: 15000 | BS62: M | BU62: N/A | BW62: N/A | BY62: N/A | CA62: N/A | CB62: 2-8 Basispoints (min 2,000 USD per month) | CC62: O | CE62: N/A | CG62: N/A | CH62: 10000 | CI62: O | CJ62: 2500 | CK62: O | CL62: 1500 | CM62: O | CN62: 1500 | CO62: O | CP62: 400 | CQ62: M | CR62: 300 | CS62: M | CU62: N/A | CV62: 165 | CW62: M | CY62: N/A | DA62: N/A | DB62: USD 100–750/hr (confirm with local office) | DC62: O | DD62: =ROUND(0.075*SUM(AD62,AF62,AH62,AJ62,AL62,AN62,AP62,AR62,AT62,AV62,AX62,AZ62,BB62,BR62,BT62,BV62,BX62,BZ62,CB62,CD62,CF62,CJ62,CL62,CN62,CP62,CR62,CT62,CV62,CX62,CZ62),0) -> 1875 | DE62: Cayman Islands#Fund#Cayman Islands SPC | DF62: =A62&"#"&C62&"#"&D62 -> Cayman Islands#Fund#Cayman Islands SPC | DG62: =DE62=DF62 -> TRUE
A63: Cayman Islands | B63: Kimbert Solomon | C63: Fund | D63: Cayman Islands Unit Trust | E63: USD | F63: Pooled investment vehicle where investors hold units representing beneficial interest. | G63: The Cayman Islands Unit Trust is a fund structure regulated under local law and widely used by international clients of Amicorp. Pooled investment vehicle where investors hold units representing beneficial interest. Our local team manages incorporation, ongoing administration, accounting, and compliance so you can focus on commercial objectives instead of paperwork. | H63: 4-6 weeks | I63: Annual audited financials, regulator filings, AML/KYC monitoring, and investor reporting | J63: Established Cayman Islands legal framework familiar to investors, banks, and counterparties | K63: End-to-end Amicorp service: incorporation, registered office, directors, accounting, and reporting | L63: Treaty network and regulatory standing supporting cross-border investment and capital flows | M63: Single point of contact across 30+ jurisdictions for multi-entity group structures | N63: Asset managers launching regulated or private funds | O63: PE/VC sponsors raising committed capital from institutional LPs | P63: Family offices pooling investments across asset classes | Q63: Structured products and securitisation arrangers | R63: Pooled capital with professional management | S63: Investor-friendly structure with familiar legal precedent | T63: Tax-efficient flow-through or treaty-eligible vehicle | U63: Scalable for additional sub-funds or share classes | V63: Investment Fund (Regulated) | W63: Common Law | X63: Full | Y63: Cayman Islands Monetary Authority (CIMA) Mutual Funds Act (2021 Revision) | Z63: No | AA63: 1 trustee + 1 unitholder | AB63: Open-ended unit trust for Middle Eastern and Asian sovereign wealth fund investors | AC63: CIMA registration; licensed trustee required; annual audit | AE63: M | AG63: O | AI63: N/A | AK63: N/A | AL63: 0 | AM63: M | AO63: N/A | AP63: — | AQ63: M | AS63: N/A | AT63: — | AU63: O | AW63: M | AY63: M | AZ63: 1189.93 | BA63: M | BB63: 182.93 | BC63: M | BD63: — | BE63: M | BF63: — | BG63: M | BI63: N/A | BK63: N/A | BM63: N/A | BO63: N/A | BQ63: N/A | BR63: 15000 | BS63: M | BU63: N/A | BW63: N/A | BY63: N/A | CA63: N/A | CB63: 2-8 Basispoints (2,000 USD per month minimum fee) | CC63: O | CE63: N/A | CG63: N/A | CH63: 10000 | CI63: O | CJ63: 2500 | CK63: O | CL63: 1500 | CM63: O | CN63: 1500 | CO63: O | CP63: 400 | CQ63: M | CR63: 300 | CS63: M | CU63: N/A | CV63: 165 | CW63: M | CY63: N/A | DA63: N/A | DB63: USD 100–750/hr (confirm with local office) | DC63: O | DD63: =ROUND(0.075*SUM(AD63,AF63,AH63,AJ63,AL63,AN63,AP63,AR63,AT63,AV63,AX63,AZ63,BB63,BR63,BT63,BV63,BX63,BZ63,CB63,CD63,CF63,CJ63,CL63,CN63,CP63,CR63,CT63,CV63,CX63,CZ63),0) -> 1705 | DE63: Cayman Islands#Fund#Cayman Islands Unit Trust | DF63: =A63&"#"&C63&"#"&D63 -> Cayman Islands#Fund#Cayman Islands Unit Trust | DG63: =DE63=DF63 -> TRUE
A64: CHILE | DE64: ## | DF64: =A61&"#"&C61&"#"&D61 -> Cayman Islands#Fund#Cayman Islands LLC
A65: Chile | B65: Paula Parra Hein | C65: Company | D65: Chile SA | E65: USD | F65: Sociedad Anónima — a public limited company structure common in Latin American and European jurisdictions. | G65: The Chile SA is a entity structure regulated under local law and widely used by international clients of Amicorp. Sociedad Anónima — a public limited company structure common in Latin American and European jurisdictions. Our local team manages incorporation, ongoing administration, accounting, and compliance so you can focus on commercial objectives instead of paperwork. | H65: 3-7 business days | I65: Annual return, financial statements filing, and economic substance / UBO declarations | J65: Established Chile legal framework familiar to investors, banks, and counterparties | K65: End-to-end Amicorp service: incorporation, registered office, directors, accounting, and reporting | L65: Treaty network and regulatory standing supporting cross-border investment and capital flows | M65: Single point of contact across 30+ jurisdictions for multi-entity group structures | N65: Holding investments into and out of Chile | O65: Group holding companies and intermediate SPVs | P65: Joint ventures and shareholder agreements | Q65: Operating subsidiaries with local market access | R65: Limited liability for shareholders | S65: Separate legal entity | T65: Flexible management structure | U65: Tax efficient | V65: Limited Company | W65: Civil Law | X65: Full | Y65: SII / Conservador de Bienes Raíces / CBR Law 18,046 on Corporations | Z65: Yes | AA65: 2 | AB65: Chile operating company or holding vehicle for South American investments | AC65: 27% FCT; dividend withholding; pension reform risk; labour law complexity | AD65: 3930 | AE65: M | AG65: O | AH65: 1000 | AI65: O | AK65: N/A | AL65: 0 | AM65: M | AN65: 1500 | AO65: O | AP65: 6180 | AQ65: M | AS65: N/A | AT65: — | AU65: O | AV65: 2470 | AW65: M | AX65: — | AY65: M | AZ65: 1000 | BA65: M | BC65: M | BD65: 1500 | BE65: M | BF65: 1500 | BG65: M | BI65: N/A | BK65: N/A | BM65: N/A | BO65: N/A | BQ65: N/A | BS65: N/A | BU65: N/A | BW65: N/A | BY65: N/A | CA65: N/A | CC65: N/A | CE65: N/A | CG65: N/A | CK65: N/A | CM65: N/A | CO65: N/A | CP65: 400 | CQ65: M | CS65: N/A | CU65: N/A | CW65: N/A | CY65: N/A | DA65: N/A | DB65: USD 100–750/hr (confirm with local office) | DC65: O | DD65: =ROUND(0.075*SUM(AD65,AF65,AH65,AJ65,AL65,AN65,AP65,AR65,AT65,AV65,AX65,AZ65,BB65,BR65,BT65,BV65,BX65,BZ65,CB65,CD65,CF65,CJ65,CL65,CN65,CP65,CR65,CT65,CV65,CX65,CZ65),0) -> 1236 | DE65: Chile#Company#Chile SA | DF65: =A65&"#"&C65&"#"&D65 -> Chile#Company#Chile SA | DG65: =DE65=DF65 -> TRUE
A66: Chile | B66: Paula Parra Hein | C66: Company | D66: Chile SPA | E66: USD | F66: Sociedad por Acciones — simplified stock corporation with flexible governance. | G66: The Chile SPA is a entity structure regulated under local law and widely used by international clients of Amicorp. Sociedad por Acciones — simplified stock corporation with flexible governance. Our local team manages incorporation, ongoing administration, accounting, and compliance so you can focus on commercial objectives instead of paperwork. | H66: 3-7 business days | I66: Annual return, financial statements filing, and economic substance / UBO declarations | J66: Established Chile legal framework familiar to investors, banks, and counterparties | K66: End-to-end Amicorp service: incorporation, registered office, directors, accounting, and reporting | L66: Treaty network and regulatory standing supporting cross-border investment and capital flows | M66: Single point of contact across 30+ jurisdictions for multi-entity group structures | N66: Holding investments into and out of Chile | O66: Group holding companies and intermediate SPVs | P66: Joint ventures and shareholder agreements | Q66: Operating subsidiaries with local market access | R66: Limited liability for shareholders | S66: Separate legal entity | T66: Flexible management structure | U66: Tax efficient | V66: Limited Company | W66: Civil Law | X66: Full | Y66: SII / CBR Law 20,190 on SpA | Z66: Yes | AA66: 1 | AB66: Flexible single-person corporation for startups and SMEs in Chile | AC66: 27% CIT; complex BEPS/transfer pricing for related party transactions | AD66: 3930 | AE66: M | AG66: O | AH66: 1000 | AI66: O | AK66: N/A | AL66: 0 | AM66: M | AN66: 1500 | AO66: O | AP66: 6180 | AQ66: M | AS66: N/A | AT66: — | AU66: O | AV66: 2470 | AW66: M | AX66: — | AY66: M | AZ66: 1000 | BA66: M | BC66: M | BD66: 1500 | BE66: M | BF66: 1500 | BG66: M | BI66: N/A | BK66: N/A | BM66: N/A | BO66: N/A | BQ66: N/A | BS66: N/A | BU66: N/A | BW66: N/A | BY66: N/A | CA66: N/A | CC66: N/A | CE66: N/A | CG66: N/A | CK66: N/A | CM66: N/A | CO66: N/A | CP66: 400 | CQ66: M | CS66: N/A | CU66: N/A | CW66: N/A | CY66: N/A | DA66: N/A | DB66: USD 100–750/hr (confirm with local office) | DC66: O | DD66: =ROUND(0.075*SUM(AD66,AF66,AH66,AJ66,AL66,AN66,AP66,AR66,AT66,AV66,AX66,AZ66,BB66,BR66,BT66,BV66,BX66,BZ66,CB66,CD66,CF66,CJ66,CL66,CN66,CP66,CR66,CT66,CV66,CX66,CZ66),0) -> 1236 | DE66: Chile#Company#Chile SPA | DF66: =A66&"#"&C66&"#"&D66 -> Chile#Company#Chile SPA | DG66: =DE66=DF66 -> TRUE
A67: Chile | B67: Paula Parra Hein | C67: Company | D67: Chile SRL | E67: USD | F67: Sociedad de Responsabilidad Limitada — a private limited liability company under civil law. | G67: The Chile SRL is a entity structure regulated under local law and widely used by international clients of Amicorp. Sociedad de Responsabilidad Limitada — a private limited liability company under civil law. Our local team manages incorporation, ongoing administration, accounting, and compliance so you can focus on commercial objectives instead of paperwork. | H67: 3-7 business days | I67: Annual return, financial statements filing, and economic substance / UBO declarations | J67: Established Chile legal framework familiar to investors, banks, and counterparties | K67: End-to-end Amicorp service: incorporation, registered office, directors, accounting, and reporting | L67: Treaty network and regulatory standing supporting cross-border investment and capital flows | M67: Single point of contact across 30+ jurisdictions for multi-entity group structures | N67: Holding investments into and out of Chile | O67: Group holding companies and intermediate SPVs | P67: Joint ventures and shareholder agreements | Q67: Operating subsidiaries with local market access | R67: Limited liability for shareholders | S67: Separate legal entity | T67: Flexible management structure | U67: Tax efficient | V67: Limited Company | W67: Civil Law | X67: Full | Y67: SII Commercial Code (Código de Comercio) | Z67: Yes | AA67: 2 | AB67: Chile limited liability company for SMEs and JV structures | AC67: Transfer of quotas restricted; 27% CIT; mandatory audit for large companies | AD67: 4000 | AE67: M | AG67: O | AI67: N/A | AK67: N/A | AL67: 0 | AM67: M | AO67: N/A | AP67: 3200 | AQ67: M | AS67: N/A | AT67: — | AU67: O | AV67: 2470 | AW67: M | AX67: — | AY67: M | AZ67: 1000 | BA67: M | BC67: M | BD67: — | BE67: M | BF67: — | BG67: M | BI67: N/A | BK67: N/A | BM67: N/A | BO67: N/A | BQ67: N/A | BS67: N/A | BU67: N/A | BW67: N/A | BY67: N/A | CA67: N/A | CC67: N/A | CE67: N/A | CG67: N/A | CK67: N/A | CM67: N/A | CO67: N/A | CP67: 400 | CQ67: M | CS67: N/A | CU67: N/A | CW67: N/A | CY67: N/A | DA67: N/A | DB67: USD 100–750/hr (confirm with local office) | DC67: O | DD67: =ROUND(0.075*SUM(AD67,AF67,AH67,AJ67,AL67,AN67,AP67,AR67,AT67,AV67,AX67,AZ67,BB67,BR67,BT67,BV67,BX67,BZ67,CB67,CD67,CF67,CJ67,CL67,CN67,CP67,CR67,CT67,CV67,CX67,CZ67),0) -> 830 | DE67: Chile#Company#Chile SRL | DF67: =A67&"#"&C67&"#"&D67 -> Chile#Company#Chile SRL | DG67: =DE67=DF67 -> TRUE
A68: Chile | B68: Paula Parra Hein | C68: Trust | D68: Chile Trust | E68: USD | F68: Discretionary or fixed trust structure for asset protection and succession planning. | G68: The Chile Trust is a trust structure regulated under local law and widely used by international clients of Amicorp. Discretionary or fixed trust structure for asset protection and succession planning. Our local team manages incorporation, ongoing administration, accounting, and compliance so you can focus on commercial objectives instead of paperwork. | H68: 5-10 business days | I68: Annual trustee review, beneficiary statements, FATCA/CRS reporting where applicable | J68: Established Chile legal framework familiar to investors, banks, and counterparties | K68: End-to-end Amicorp service: incorporation, registered office, directors, accounting, and reporting | L68: Treaty network and regulatory standing supporting cross-border investment and capital flows | M68: Single point of contact across 30+ jurisdictions for multi-entity group structures | N68: High-net-worth families consolidating assets across jurisdictions | O68: Succession and inheritance planning for global families | P68: Asset protection from political, creditor, or matrimonial risks | Q68: Holding shares of a private trust company or family business | R68: Asset protection from third-party claims | S68: Multi-generational succession planning | T68: Confidentiality and privacy of beneficial ownership | U68: Flexible distribution control by trustee | V68: Trust | W68: Civil Law | X68: Assets segregated | Y68: SVS / CMF Chilean Civil Code; Securitization Law | Z68: No | AB68: Chilean fideicomiso for real estate or structured finance | AC68: No general trust law; used mainly for securitisation; limited HNW wealth planning use | AD68: 4500 | AE68: M | AG68: O | AI68: N/A | AK68: N/A | AL68: 0 | AM68: M | AO68: N/A | AQ68: N/A | AR68: 3500 | AS68: M | AT68: — | AU68: O | AV68: — | AW68: M | AX68: — | AY68: M | AZ68: — | BA68: M | BC68: M | BD68: — | BE68: M | BF68: — | BG68: M | BI68: N/A | BK68: N/A | BM68: N/A | BO68: N/A | BQ68: N/A | BS68: N/A | BU68: N/A | BW68: N/A | BY68: N/A | CA68: N/A | CC68: N/A | CE68: N/A | CG68: N/A | CK68: N/A | CM68: N/A | CO68: N/A | CP68: 400 | CQ68: M | CS68: N/A | CU68: N/A | CW68: N/A | CY68: N/A | DA68: N/A | DB68: USD 100–750/hr (confirm with local office) | DC68: O | DD68: =ROUND(0.075*SUM(AD68,AF68,AH68,AJ68,AL68,AN68,AP68,AR68,AT68,AV68,AX68,AZ68,BB68,BR68,BT68,BV68,BX68,BZ68,CB68,CD68,CF68,CJ68,CL68,CN68,CP68,CR68,CT68,CV68,CX68,CZ68),0) -> 630 | DE68: Chile#Trust#Chile Trust | DF68: =A68&"#"&C68&"#"&D68 -> Chile#Trust#Chile Trust | DG68: =DE68=DF68 -> TRUE
A69: Chile | B69: Juan Cristobal Recart Salas | C69: Fund | D69: Chile Fondo de Inversion Publico | E69: USD | F69: Chilean public investment fund regulated by the CMF. | G69: The Chile Fondo de Inversion Publico is a fund structure regulated under local law and widely used by international clients of Amicorp. Chilean public investment fund regulated by the CMF. Our local team manages incorporation, ongoing administration, accounting, and compliance so you can focus on commercial objectives instead of paperwork. | H69: 4-6 weeks | I69: Annual audited financials, regulator filings, AML/KYC monitoring, and investor reporting | J69: Established Chile legal framework familiar to investors, banks, and counterparties | K69: End-to-end Amicorp service: incorporation, registered office, directors, accounting, and reporting | L69: Treaty network and regulatory standing supporting cross-border investment and capital flows | M69: Single point of contact across 30+ jurisdictions for multi-entity group structures | N69: Asset managers launching regulated or private funds | O69: PE/VC sponsors raising committed capital from institutional LPs | P69: Family offices pooling investments across asset classes | Q69: Structured products and securitisation arrangers | R69: Pooled capital with professional management | S69: Investor-friendly structure with familiar legal precedent | T69: Tax-efficient flow-through or treaty-eligible vehicle | U69: Scalable for additional sub-funds or share classes | V69: Investment Fund (Regulated) | W69: Civil Law | X69: Full | Y69: CMF (Comisión para el Mercado Financiero) Law 20,712 on Fund Administration | Z69: Yes | AA69: Management company + investors | AB69: Public Chilean investment fund for retail and institutional investors | AC69: CMF authorisation; mandatory audit; distribution requirements | AE69: M | AG69: O | AI69: N/A | AK69: N/A | AL69: 0 | AM69: M | AO69: N/A | AP69: — | AQ69: M | AS69: N/A | AT69: — | AU69: O | AV69: — | AW69: M | AX69: — | AY69: M | AZ69: — | BA69: M | BC69: M | BD69: — | BE69: M | BF69: — | BG69: M | BI69: N/A | BK69: N/A | BM69: N/A | BO69: N/A | BQ69: N/A | BR69: 12000 | BS69: M | BU69: N/A | BW69: N/A | BY69: N/A | CA69: N/A | CB69: 2-8 Basispoints (2,000 USD per month minimum fee) | CC69: O | CE69: N/A | CG69: N/A | CI69: O | CJ69: 2500 | CK69: O | CL69: 1500 | CM69: O | CN69: 1500 | CO69: O | CP69: 400 | CQ69: M | CS69: N/A | CU69: N/A | CW69: N/A | CY69: N/A | DA69: N/A | DB69: USD 100–750/hr (confirm with local office) | DC69: O | DD69: =ROUND(0.075*SUM(AD69,AF69,AH69,AJ69,AL69,AN69,AP69,AR69,AT69,AV69,AX69,AZ69,BB69,BR69,BT69,BV69,BX69,BZ69,CB69,CD69,CF69,CJ69,CL69,CN69,CP69,CR69,CT69,CV69,CX69,CZ69),0) -> 1343 | DE69: Chile#Fund#Chile Fondo de Inversion Publico | DF69: =A69&"#"&C69&"#"&D69 -> Chile#Fund#Chile Fondo de Inversion Publico | DG69: =DE69=DF69 -> TRUE
A70: Chile | B70: Juan Cristobal Recart Salas | C70: Fund | D70: Chile Fondo de Inversion Privado | E70: USD | F70: Chilean private investment fund with fewer regulatory requirements. | G70: The Chile Fondo de Inversion Privado is a fund structure regulated under local law and widely used by international clients of Amicorp. Chilean private investment fund with fewer regulatory requirements. Our local team manages incorporation, ongoing administration, accounting, and compliance so you can focus on commercial objectives instead of paperwork. | H70: 4-6 weeks | I70: Annual audited financials, regulator filings, AML/KYC monitoring, and investor reporting | J70: Established Chile legal framework familiar to investors, banks, and counterparties | K70: End-to-end Amicorp service: incorporation, registered office, directors, accounting, and reporting | L70: Treaty network and regulatory standing supporting cross-border investment and capital flows | M70: Single point of contact across 30+ jurisdictions for multi-entity group structures | N70: Asset managers launching regulated or private funds | O70: PE/VC sponsors raising committed capital from institutional LPs | P70: Family offices pooling investments across asset classes | Q70: Structured products and securitisation arrangers | R70: Pooled capital with professional management | S70: Investor-friendly structure with familiar legal precedent | T70: Tax-efficient flow-through or treaty-eligible vehicle | U70: Scalable for additional sub-funds or share classes | V70: Investment Fund (AIF) | W70: Civil Law | X70: Full | Y70: CMF (limited oversight) Law 20,712 | Z70: No | AA70: 1 administrator + investors | AB70: Private PE/VC or real estate fund for accredited Chilean investors | AC70: Limited to accredited investors; annual audit; CMF notification | AE70: M | AG70: O | AI70: N/A | AK70: N/A | AL70: 0 | AM70: M | AO70: N/A | AP70: — | AQ70: M | AS70: N/A | AT70: — | AU70: O | AV70: — | AW70: M | AX70: — | AY70: M | AZ70: — | BA70: M | BC70: M | BD70: — | BE70: M | BF70: — | BG70: M | BI70: N/A | BK70: N/A | BM70: N/A | BO70: N/A | BQ70: N/A | BR70: 12000 | BS70: M | BU70: N/A | BW70: N/A | BY70: N/A | CA70: N/A | CB70: 2-8 Basispoints (2,000 USD per month minimum fee) | CC70: O | CE70: N/A | CG70: N/A | CI70: O | CJ70: 2500 | CK70: O | CL70: 1500 | CM70: O | CN70: 1500 | CO70: O | CP70: 400 | CQ70: M | CS70: N/A | CU70: N/A | CW70: N/A | CY70: N/A | DA70: N/A | DB70: USD 100–750/hr (confirm with local office) | DC70: O | DD70: =ROUND(0.075*SUM(AD70,AF70,AH70,AJ70,AL70,AN70,AP70,AR70,AT70,AV70,AX70,AZ70,BB70,BR70,BT70,BV70,BX70,BZ70,CB70,CD70,CF70,CJ70,CL70,CN70,CP70,CR70,CT70,CV70,CX70,CZ70),0) -> 1343 | DE70: Chile#Fund#Chile Fondo de Inversion Privado | DF70: =A70&"#"&C70&"#"&D70 -> Chile#Fund#Chile Fondo de Inversion Privado | DG70: =DE70=DF70 -> TRUE
A71: Chile | B71: Juan Cristobal Recart Salas | C71: Fund | D71: Chile Fondo de Inversion Inmobiliario | E71: USD | F71: Chilean real estate investment fund for property portfolios. | G71: The Chile Fondo de Inversion Inmobiliario is a fund structure regulated under local law and widely used by international clients of Amicorp. Chilean real estate investment fund for property portfolios. Our local team manages incorporation, ongoing administration, accounting, and compliance so you can focus on commercial objectives instead of paperwork. | H71: 4-6 weeks | I71: Annual audited financials, regulator filings, AML/KYC monitoring, and investor reporting | J71: Established Chile legal framework familiar to investors, banks, and counterparties | K71: End-to-end Amicorp service: incorporation, registered office, directors, accounting, and reporting | L71: Treaty network and regulatory standing supporting cross-border investment and capital flows | M71: Single point of contact across 30+ jurisdictions for multi-entity group structures | N71: Asset managers launching regulated or private funds | O71: PE/VC sponsors raising committed capital from institutional LPs | P71: Family offices pooling investments across asset classes | Q71: Structured products and securitisation arrangers | R71: Pooled capital with professional management | S71: Investor-friendly structure with familiar legal precedent | T71: Tax-efficient flow-through or treaty-eligible vehicle | U71: Scalable for additional sub-funds or share classes | V71: REIT/Business Trust | W71: Civil Law | X71: Full | Y71: CMF Law 20,712; Real Estate Fund Regulations | Z71: Yes | AA71: Management company + investors | AB71: Chilean real estate investment fund for residential, commercial, or industrial properties | AC71: CMF authorisation; mandatory property valuations; liquidity constraints | AE71: M | AG71: O | AI71: N/A | AK71: N/A | AL71: 0 | AM71: M | AO71: N/A | AP71: — | AQ71: M | AS71: N/A | AT71: — | AU71: O | AV71: — | AW71: M | AX71: — | AY71: M | AZ71: — | BA71: M | BC71: M | BD71: — | BE71: M | BF71: — | BG71: M | BI71: N/A | BK71: N/A | BM71: N/A | BO71: N/A | BQ71: N/A | BR71: 12000 | BS71: M | BU71: N/A | BW71: N/A | BY71: N/A | CA71: N/A | CB71: 2-8 Basispoints (2,000 USD per month minimum fee) | CC71: O | CE71: N/A | CG71: N/A | CI71: O | CJ71: 2500 | CK71: O | CL71: 1500 | CM71: O | CN71: 1500 | CO71: O | CP71: 400 | CQ71: M | CS71: N/A | CU71: N/A | CW71: N/A | CY71: N/A | DA71: N/A | DB71: USD 100–750/hr (confirm with local office) | DC71: O | DD71: =ROUND(0.075*SUM(AD71,AF71,AH71,AJ71,AL71,AN71,AP71,AR71,AT71,AV71,AX71,AZ71,BB71,BR71,BT71,BV71,BX71,BZ71,CB71,CD71,CF71,CJ71,CL71,CN71,CP71,CR71,CT71,CV71,CX71,CZ71),0) -> 1343 | DE71: Chile#Fund#Chile Fondo de Inversion Inmobiliario | DF71: =A71&"#"&C71&"#"&D71 -> Chile#Fund#Chile Fondo de Inversion Inmobiliario | DG71: =DE71=DF71 -> TRUE
A72: Chile | B72: Juan Cristobal Recart Salas | C72: Fund | D72: Chile Fondo Extranjero | E72: USD | F72: Chilean foreign fund vehicle for cross-border investment management. | G72: The Chile Fondo Extranjero is a fund structure regulated under local law and widely used by international clients of Amicorp. Chilean foreign fund vehicle for cross-border investment management. Our local team manages incorporation, ongoing administration, accounting, and compliance so you can focus on commercial objectives instead of paperwork. | H72: 4-6 weeks | I72: Annual audited financials, regulator filings, AML/KYC monitoring, and investor reporting | J72: Established Chile legal framework familiar to investors, banks, and counterparties | K72: End-to-end Amicorp service: incorporation, registered office, directors, accounting, and reporting | L72: Treaty network and regulatory standing supporting cross-border investment and capital flows | M72: Single point of contact across 30+ jurisdictions for multi-entity group structures | N72: Asset managers launching regulated or private funds | O72: PE/VC sponsors raising committed capital from institutional LPs | P72: Family offices pooling investments across asset classes | Q72: Structured products and securitisation arrangers | R72: Pooled capital with professional management | S72: Investor-friendly structure with familiar legal precedent | T72: Tax-efficient flow-through or treaty-eligible vehicle | U72: Scalable for additional sub-funds or share classes | V72: Investment Fund (Regulated) | W72: Civil Law | X72: Full | Y72: CMF Law 20,712 (Title III) | Z72: Yes | AA72: Management company + investors | AB72: Foreign fund vehicle registered in Chile for cross-border portfolio management | AC72: CMF registration; compliance with Chilean securities law; currency risk | AE72: M | AG72: O | AI72: N/A | AK72: N/A | AL72: 0 | AM72: M | AO72: N/A | AP72: — | AQ72: M | AS72: N/A | AT72: — | AU72: O | AV72: — | AW72: M | AX72: — | AY72: M | AZ72: — | BA72: M | BC72: M | BD72: — | BE72: M | BF72: — | BG72: M | BI72: N/A | BK72: N/A | BM72: N/A | BO72: N/A | BQ72: N/A | BR72: 12000 | BS72: M | BU72: N/A | BW72: N/A | BY72: N/A | CA72: N/A | CB72: 2-8 Basispoints (2,000 USD per month minimum fee) | CC72: O | CE72: N/A | CG72: N/A | CI72: O | CJ72: 2500 | CK72: O | CL72: 1500 | CM72: O | CN72: 1500 | CO72: O | CP72: 400 | CQ72: M | CS72: N/A | CU72: N/A | CW72: N/A | CY72: N/A | DA72: N/A | DB72: USD 100–750/hr (confirm with local office) | DC72: O | DD72: =ROUND(0.075*SUM(AD72,AF72,AH72,AJ72,AL72,AN72,AP72,AR72,AT72,AV72,AX72,AZ72,BB72,BR72,BT72,BV72,BX72,BZ72,CB72,CD72,CF72,CJ72,CL72,CN72,CP72,CR72,CT72,CV72,CX72,CZ72),0) -> 1343 | DE72: Chile#Fund#Chile Fondo Extranjero | DF72: =A72&"#"&C72&"#"&D72 -> Chile#Fund#Chile Fondo Extranjero | DG72: =DE72=DF72 -> TRUE
A73: Chile | B73: Juan Cristobal Recart Salas | C73: Fund | D73: Chile Fondo Mutuo | E73: USD | F73: Mutual fund vehicle for retail investors with daily liquidity. | G73: The Chile Fondo Mutuo is a fund structure regulated under local law and widely used by international clients of Amicorp. Mutual fund vehicle for retail investors with daily liquidity. Our local team manages incorporation, ongoing administration, accounting, and compliance so you can focus on commercial objectives instead of paperwork. | H73: 4-6 weeks | I73: Annual audited financials, regulator filings, AML/KYC monitoring, and investor reporting | J73: Established Chile legal framework familiar to investors, banks, and counterparties | K73: End-to-end Amicorp service: incorporation, registered office, directors, accounting, and reporting | L73: Treaty network and regulatory standing supporting cross-border investment and capital flows | M73: Single point of contact across 30+ jurisdictions for multi-entity group structures | N73: Asset managers launching regulated or private funds | O73: PE/VC sponsors raising committed capital from institutional LPs | P73: Family offices pooling investments across asset classes | Q73: Structured products and securitisation arrangers | R73: Pooled capital with professional management | S73: Investor-friendly structure with familiar legal precedent | T73: Tax-efficient flow-through or treaty-eligible vehicle | U73: Scalable for additional sub-funds or share classes | V73: Investment Fund (UCITS-like) | W73: Civil Law | X73: Full | Y73: CMF Law 20,712 | Z73: Yes | AA73: Management company + investors | AB73: Open-ended Chilean mutual fund for retail savings and investment | AC73: CMF compliance; mandatory administrator; redemption rights; low barriers to competition | AE73: M | AG73: O | AI73: N/A | AK73: N/A | AL73: 0 | AM73: M | AO73: N/A | AP73: — | AQ73: M | AS73: N/A | AT73: — | AU73: O | AV73: — | AW73: M | AX73: — | AY73: M | AZ73: — | BA73: M | BC73: M | BD73: — | BE73: M | BF73: — | BG73: M | BI73: N/A | BK73: N/A | BM73: N/A | BO73: N/A | BQ73: N/A | BR73: 12000 | BS73: M | BU73: N/A | BW73: N/A | BY73: N/A | CA73: N/A | CB73: 2-8 Basispoints (2,000 USD per month minimum fee) | CC73: O | CE73: N/A | CG73: N/A | CI73: O | CJ73: 2500 | CK73: O | CL73: 1500 | CM73: O | CN73: 1500 | CO73: O | CP73: 400 | CQ73: M | CS73: N/A | CU73: N/A | CW73: N/A | CY73: N/A | DA73: N/A | DB73: USD 100–750/hr (confirm with local office) | DC73: O | DD73: =ROUND(0.075*SUM(AD73,AF73,AH73,AJ73,AL73,AN73,AP73,AR73,AT73,AV73,AX73,AZ73,BB73,BR73,BT73,BV73,BX73,BZ73,CB73,CD73,CF73,CJ73,CL73,CN73,CP73,CR73,CT73,CV73,CX73,CZ73),0) -> 1343 | DE73: Chile#Fund#Chile Fondo Mutuo | DF73: =A73&"#"&C73&"#"&D73 -> Chile#Fund#Chile Fondo Mutuo | DG73: =DE73=DF73 -> TRUE
A74: CHINA | DE74: ## | DF74: =A71&"#"&C71&"#"&D71 -> Chile#Fund#Chile Fondo de Inversion Inmobiliario
A75: China | B75: Hudson He | C75: Company | D75: China WFOE | E75: USD | F75: Wholly Foreign-Owned Enterprise — a limited liability company 100% owned by foreign investors for operating in China. | G75: The China WFOE (Wholly Foreign-Owned Enterprise) is a company structure regulated under local law and widely used by international clients of Amicorp. A WFOE is a limited liability company fully owned by foreign investors, enabling direct business operations, local hiring, and RMB invoicing in China without a Chinese partner. Our local team manages incorporation, ongoing administration, accounting, and compliance so you can focus on commercial objectives instead of paperwork. | H75: 4-8 weeks | I75: Annual CIT return, VAT filings, annual inspection, statistical reporting, and UBO declarations | J75: Established China legal framework familiar to investors, banks, and counterparties | K75: End-to-end Amicorp service: incorporation, registered office, directors, accounting, and reporting | L75: Treaty network and regulatory standing supporting cross-border investment and capital flows | M75: Single point of contact across 30+ jurisdictions for multi-entity group structures | N75: 100% foreign ownership — no local Chinese partner required | O75: RMB invoicing and ability to convert and repatriate profits | P75: Full operational control over employees, IP, and business activities | Q75: Access to Chinese domestic market and supply chains | R75: Limited liability for shareholders | S75: Separate legal entity | T75: Full operational control (unlike JV structures) | U75: Access to China domestic market | V75: LLC (WFOE) | W75: Civil Law | X75: Full | Y75: SAMR (State Administration for Market Regulation) Company Law 2023; Foreign Investment Law 2020 | Z75: Yes | AA75: 1 | AB75: Foreign-owned operating company in China for manufacturing, trading, services, or technology | AC75: CIT 25% (15% in high-tech zones); multi-agency registration; FX repatriation restrictions; sector restrictions under foreign investment negative list | AD75: 4500 | AE75: M | AG75: O | AI75: N/A | AK75: N/A | AL75: 0 | AM75: M | AO75: N/A | AP75: Confirm with local office | AQ75: M | AS75: N/A | AT75: — | AU75: O | AV75: — | AW75: M | AX75: — | AY75: M | AZ75: — | BA75: M | BC75: M | BD75: Confirm with local office | BE75: M | BF75: Confirm with local office | BG75: M | BI75: N/A | BK75: N/A | BM75: N/A | BO75: N/A | BQ75: N/A | BS75: N/A | BU75: N/A | BW75: N/A | BY75: N/A | CA75: N/A | CC75: N/A | CE75: N/A | CG75: N/A | CK75: N/A | CM75: N/A | CO75: N/A | CP75: 400 | CQ75: M | CS75: N/A | CU75: N/A | CW75: N/A | CY75: N/A | DA75: N/A | DB75: USD 100–750/hr (confirm with local office) | DC75: O | DD75: =ROUND(0.075*SUM(AD75,AF75,AH75,AJ75,AL75,AN75,AP75,AR75,AT75,AV75,AX75,AZ75,BB75,BR75,BT75,BV75,BX75,BZ75,CB75,CD75,CF75,CJ75,CL75,CN75,CP75,CR75,CT75,CV75,CX75,CZ75),0) -> 368 | DE75: China#Company#China WFOE | DF75: =A75&"#"&C75&"#"&D75 -> China#Company#China WFOE | DG75: =DE75=DF75 -> TRUE
A76: China | B76: Hudson He | C76: Company | D76: China Rep Office | E76: USD | F76: Representative Office — a non-revenue generating liaison and market research presence for foreign companies in China. | G76: The China Representative Office is a presence structure regulated under local law and widely used by international clients of Amicorp. A Rep Office allows foreign companies to establish a presence in China for liaison, market research, and promotional activities — it cannot directly generate revenue or sign contracts on behalf of the foreign parent. Our local team manages registration, ongoing administration, and compliance so you can focus on commercial objectives instead of paperwork. | H76: 4-8 weeks | I76: Annual registration renewal, tax filing on deemed profit basis, annual inspection, and statistical reporting | J76: Established China legal framework familiar to investors, banks, and counterparties | K76: End-to-end Amicorp service: registration, registered address, compliance, and reporting | L76: Treaty network and regulatory standing supporting cross-border investment and capital flows | M76: Single point of contact across 30+ jurisdictions for multi-entity group structures | N76: Low-cost China market entry without full company incorporation | O76: Market research, liaison, and promotional activities | P76: No minimum registered capital requirement | Q76: Suitable as a precursor to full WFOE establishment | R76: No separate legal personality (extension of parent) | S76: No registered capital requirement | T76: Simpler registration than WFOE | U76: Low-cost market entry vehicle | V76: Representative Office | W76: Civil Law | X76: None (parent company liable) | Y76: SAMR / Municipal Commerce Bureau Regulations on Administration of Foreign-Invested Enterprises 2019 | Z76: Yes (parent company) | AA76: Chief Representative (min. 1) | AB76: Foreign companies entering China for market research, liaison, and sourcing without generating local revenue | AC76: Cannot sign contracts or generate revenue; taxed on deemed profit basis; annual registration renewal; cannot hire Chinese employees directly (must use licensed HR agency) | AD76: 3500 | AE76: M | AG76: O | AI76: N/A | AK76: N/A | AL76: 0 | AM76: M | AO76: N/A | AP76: Confirm with local office | AQ76: M | AS76: N/A | AT76: — | AU76: O | AV76: — | AW76: M | AX76: — | AY76: M | AZ76: — | BA76: M | BC76: M | BD76: Confirm with local office | BE76: M | BF76: Confirm with local office | BG76: M | BI76: N/A | BK76: N/A | BM76: N/A | BO76: N/A | BQ76: N/A | BS76: N/A | BU76: N/A | BW76: N/A | BY76: N/A | CA76: N/A | CC76: N/A | CE76: N/A | CG76: N/A | CK76: N/A | CM76: N/A | CO76: N/A | CP76: 400 | CQ76: M | CS76: N/A | CU76: N/A | CW76: N/A | CY76: N/A | DA76: N/A | DB76: USD 100–750/hr (confirm with local office) | DC76: O | DD76: =ROUND(0.075*SUM(AD76,AF76,AH76,AJ76,AL76,AN76,AP76,AR76,AT76,AV76,AX76,AZ76,BB76,BR76,BT76,BV76,BX76,BZ76,CB76,CD76,CF76,CJ76,CL76,CN76,CP76,CR76,CT76,CV76,CX76,CZ76),0) -> 293 | DE76: China#Company#China Rep Office | DF76: =A76&"#"&C76&"#"&D76 -> China#Company#China Rep Office | DG76: =DE76=DF76 -> TRUE
A77: CURACAO | DE77: ## | DF77: =A74&"#"&C74&"#"&D74 -> CHINA##
A78: Curacao | B78: Anneliese Garcia-deJongh | C78: Company | D78: Curacao BV | E78: USD, USD/EUR/GBP | F78: Besloten Vennootschap — Dutch-style private limited company with minimal capital requirements. | G78: The Curacao BV is a entity structure regulated under local law and widely used by international clients of Amicorp. Besloten Vennootschap — Dutch-style private limited company with minimal capital requirements. Our local team manages incorporation, ongoing administration, accounting, and compliance so you can focus on commercial objectives instead of paperwork. | H78: 3-7 business days | I78: Annual return, financial statements filing, and economic substance / UBO declarations | J78: Established Curacao legal framework familiar to investors, banks, and counterparties | K78: End-to-end Amicorp service: incorporation, registered office, directors, accounting, and reporting | L78: Treaty network and regulatory standing supporting cross-border investment and capital flows | M78: Single point of contact across 30+ jurisdictions for multi-entity group structures | N78: Holding investments into and out of Curacao | O78: Group holding companies and intermediate SPVs | P78: Joint ventures and shareholder agreements | Q78: Operating subsidiaries with local market access | R78: Limited liability for shareholders | S78: Separate legal entity | T78: Flexible management structure | U78: Tax efficient | V78: Limited Company | W78: Civil Law (Dutch-based) | X78: Full | Y78: Curaçao Chamber of Commerce / CAft Civil Code of Curaçao Book 2 | Z78: Yes | AA78: 1 | AB78: Dutch Caribbean holding company for LatAm and Caribbean investments | AC78: FATF grey-list risk; limited treaty access post-kingdom restructuring; substance required | AD78: 3020 | AE78: M | AG78: O | AI78: N/A | AK78: N/A | AL78: 0 | AM78: M | AO78: N/A | AP78: 2650 | AQ78: M | AS78: N/A | AT78: — | AU78: O | AV78: 2230 | AW78: O | AX78: — | AY78: M | AZ78: 75 | BA78: M | BB78: 100 | BC78: M | BD78: — | BE78: M | BF78: 500 | BG78: M | BI78: N/A | BK78: N/A | BM78: N/A | BO78: N/A | BQ78: N/A | BS78: N/A | BU78: N/A | BW78: N/A | BY78: N/A | CA78: N/A | CC78: N/A | CE78: N/A | CG78: N/A | CK78: N/A | CM78: N/A | CO78: N/A | CP78: 400 | CQ78: M | CS78: N/A | CU78: N/A | CW78: N/A | CY78: N/A | DA78: N/A | DB78: USD 100–750/hr (confirm with local office) | DC78: O | DD78: =ROUND(0.075*SUM(AD78,AF78,AH78,AJ78,AL78,AN78,AP78,AR78,AT78,AV78,AX78,AZ78,BB78,BR78,BT78,BV78,BX78,BZ78,CB78,CD78,CF78,CJ78,CL78,CN78,CP78,CR78,CT78,CV78,CX78,CZ78),0) -> 636 | DE78: Curacao#Company#Curacao BV | DF78: =A78&"#"&C78&"#"&D78 -> Curacao#Company#Curacao BV | DG78: =DE78=DF78 -> TRUE
A79: Curacao | B79: Anneliese Garcia-deJongh | C79: Company | D79: Curacao NV | E79: USD | F79: Naamloze Vennootschap — public limited company suitable for larger enterprises and listings. | G79: The Curacao NV is a entity structure regulated under local law and widely used by international clients of Amicorp. Naamloze Vennootschap — public limited company suitable for larger enterprises and listings. Our local team manages incorporation, ongoing administration, accounting, and compliance so you can focus on commercial objectives instead of paperwork. | H79: 3-7 business days | I79: Annual return, financial statements filing, and economic substance / UBO declarations | J79: Established Curacao legal framework familiar to investors, banks, and counterparties | K79: End-to-end Amicorp service: incorporation, registered office, directors, accounting, and reporting | L79: Treaty network and regulatory standing supporting cross-border investment and capital flows | M79: Single point of contact across 30+ jurisdictions for multi-entity group structures | N79: Holding investments into and out of Curacao | O79: Group holding companies and intermediate SPVs | P79: Joint ventures and shareholder agreements | Q79: Operating subsidiaries with local market access | R79: Limited liability for shareholders | S79: Separate legal entity | T79: Flexible management structure | U79: Tax efficient | V79: Limited Company | W79: Civil Law (Dutch-based) | X79: Full | Y79: Curaçao Chamber of Commerce Civil Code of Curaçao Book 2 | Z79: Yes | AA79: 1 | AB79: Larger Curaçao company for public offerings or financial services licensing | AC79: FATF scrutiny; substance requirements; limited treaty network | AD79: 3020 | AE79: M | AG79: O | AI79: N/A | AK79: N/A | AL79: 0 | AM79: M | AO79: N/A | AP79: 2650 | AQ79: M | AS79: N/A | AT79: — | AU79: O | AV79: 2230 | AW79: O | AX79: — | AY79: M | AZ79: 75 | BA79: M | BB79: 100 | BC79: M | BD79: 1200 | BE79: M | BF79: 500 | BG79: M | BI79: N/A | BK79: N/A | BM79: N/A | BO79: N/A | BQ79: N/A | BS79: N/A | BU79: N/A | BW79: N/A | BY79: N/A | CA79: N/A | CC79: N/A | CE79: N/A | CG79: N/A | CK79: N/A | CM79: N/A | CO79: N/A | CP79: 400 | CQ79: M | CS79: N/A | CU79: N/A | CW79: N/A | CY79: N/A | DA79: N/A | DB79: USD 100–750/hr (confirm with local office) | DC79: O | DD79: =ROUND(0.075*SUM(AD79,AF79,AH79,AJ79,AL79,AN79,AP79,AR79,AT79,AV79,AX79,AZ79,BB79,BR79,BT79,BV79,BX79,BZ79,CB79,CD79,CF79,CJ79,CL79,CN79,CP79,CR79,CT79,CV79,CX79,CZ79),0) -> 636 | DE79: Curacao#Company#Curacao NV | DF79: =A79&"#"&C79&"#"&D79 -> Curacao#Company#Curacao NV | DG79: =DE79=DF79 -> TRUE
A80: Curacao | B80: Jan Frederik Stembord | C80: Fund | D80: Curacao NV | E80: USD | F80: Naamloze Vennootschap — public limited company suitable for larger enterprises and listings. | G80: The Curacao NV is a fund structure regulated under local law and widely used by international clients of Amicorp. Naamloze Vennootschap — public limited company suitable for larger enterprises and listings. Our local team manages incorporation, ongoing administration, accounting, and compliance so you can focus on commercial objectives instead of paperwork. | H80: 4-6 weeks | I80: Annual audited financials, regulator filings, AML/KYC monitoring, and investor reporting | J80: Established Curacao legal framework familiar to investors, banks, and counterparties | K80: End-to-end Amicorp service: incorporation, registered office, directors, accounting, and reporting | L80: Treaty network and regulatory standing supporting cross-border investment and capital flows | M80: Single point of contact across 30+ jurisdictions for multi-entity group structures | N80: Asset managers launching regulated or private funds | O80: PE/VC sponsors raising committed capital from institutional LPs | P80: Family offices pooling investments across asset classes | Q80: Structured products and securitisation arrangers | R80: Pooled capital with professional management | S80: Investor-friendly structure with familiar legal precedent | T80: Tax-efficient flow-through or treaty-eligible vehicle | U80: Scalable for additional sub-funds or share classes | V80: Investment Fund (Private) | W80: Civil Law | X80: Full | Y80: CBA (Central Bank of Curaçao and Sint Maarten) National Ordinance on Investment Institutions | Z80: Yes | AA80: 1 | AB80: Investment fund vehicle for Caribbean-based investment structures | AC80: CBA licensing; FATF risk; limited treaty access | AE80: M | AG80: O | AI80: N/A | AK80: N/A | AL80: 0 | AM80: M | AO80: N/A | AP80: 2650 | AQ80: M | AS80: N/A | AT80: — | AU80: O | AV80: 2230 | AW80: O | AX80: — | AY80: M | AZ80: 75 | BA80: M | BC80: M | BD80: 1200 | BE80: M | BF80: 500 | BG80: M | BI80: N/A | BK80: N/A | BM80: N/A | BO80: N/A | BQ80: N/A | BR80: 12000 | BS80: M | BU80: N/A | BW80: N/A | BY80: N/A | CA80: N/A | CB80: 2-8 Basispoints (2,000 USD per month minimum fee) | CC80: O | CE80: N/A | CG80: N/A | CH80: 5000 | CI80: O | CJ80: 2500 | CK80: O | CL80: 1500 | CM80: O | CN80: 1500 | CO80: O | CP80: 400 | CQ80: M | CS80: N/A | CU80: N/A | CW80: N/A | CY80: N/A | DA80: N/A | DB80: USD 100–750/hr (confirm with local office) | DC80: O | DD80: =ROUND(0.075*SUM(AD80,AF80,AH80,AJ80,AL80,AN80,AP80,AR80,AT80,AV80,AX80,AZ80,BB80,BR80,BT80,BV80,BX80,BZ80,CB80,CD80,CF80,CJ80,CL80,CN80,CP80,CR80,CT80,CV80,CX80,CZ80),0) -> 1714 | DE80: Curacao#Fund#Curacao NV | DF80: =A80&"#"&C80&"#"&D80 -> Curacao#Fund#Curacao NV | DG80: =DE80=DF80 -> TRUE
A81: Curacao | B81: Jan Frederik Stembord | C81: Fund | D81: Curacao BV | E81: USD, USD/EUR/GBP | F81: Besloten Vennootschap — Dutch-style private limited company with minimal capital requirements. | G81: The Curacao BV is a fund structure regulated under local law and widely used by international clients of Amicorp. Besloten Vennootschap — Dutch-style private limited company with minimal capital requirements. Our local team manages incorporation, ongoing administration, accounting, and compliance so you can focus on commercial objectives instead of paperwork. | H81: 4-6 weeks | I81: Annual audited financials, regulator filings, AML/KYC monitoring, and investor reporting | J81: Established Curacao legal framework familiar to investors, banks, and counterparties | K81: End-to-end Amicorp service: incorporation, registered office, directors, accounting, and reporting | L81: Treaty network and regulatory standing supporting cross-border investment and capital flows | M81: Single point of contact across 30+ jurisdictions for multi-entity group structures | N81: Asset managers launching regulated or private funds | O81: PE/VC sponsors raising committed capital from institutional LPs | P81: Family offices pooling investments across asset classes | Q81: Structured products and securitisation arrangers | R81: Pooled capital with professional management | S81: Investor-friendly structure with familiar legal precedent | T81: Tax-efficient flow-through or treaty-eligible vehicle | U81: Scalable for additional sub-funds or share classes | V81: Investment Fund (Private) | W81: Civil Law | X81: Full | Y81: CBA National Ordinance on Investment Institutions | Z81: Yes | AA81: 1 | AB81: BV fund vehicle for Caribbean or LatAm investment structures | AC81: CBA licensing required; FATF scrutiny; substance requirements | AE81: M | AG81: O | AI81: N/A | AK81: N/A | AL81: 0 | AM81: M | AO81: N/A | AQ81: M | AS81: N/A | AT81: — | AU81: O | AW81: M | AX81: — | AY81: M | BA81: M | BC81: M | BD81: — | BE81: M | BG81: M | BI81: N/A | BK81: N/A | BM81: N/A | BO81: N/A | BQ81: N/A | BR81: 12000 | BS81: M | BU81: N/A | BW81: N/A | BY81: N/A | CA81: N/A | CB81: 2-8 Basispoints (2,000 USD per month minimum fee) | CC81: O | CE81: N/A | CG81: N/A | CH81: 5000 | CI81: O | CJ81: 2500 | CK81: O | CL81: 1500 | CM81: O | CN81: 1500 | CO81: O | CP81: 400 | CQ81: M | CS81: N/A | CU81: N/A | CW81: N/A | CY81: N/A | DA81: N/A | DB81: USD 100–750/hr (confirm with local office) | DC81: O | DD81: =ROUND(0.075*SUM(AD81,AF81,AH81,AJ81,AL81,AN81,AP81,AR81,AT81,AV81,AX81,AZ81,BB81,BR81,BT81,BV81,BX81,BZ81,CB81,CD81,CF81,CJ81,CL81,CN81,CP81,CR81,CT81,CV81,CX81,CZ81),0) -> 1343 | DE81: Curacao#Fund#Curacao BV | DF81: =A81&"#"&C81&"#"&D81 -> Curacao#Fund#Curacao BV | DG81: =DE81=DF81 -> TRUE
A82: Curacao | B82: Jan Frederik Stembord | C82: Fund | D82: Curacao CV | E82: USD | F82: Commanditaire Vennootschap — limited partnership under Dutch/Curacao law. | G82: The Curacao CV is a fund structure regulated under local law and widely used by international clients of Amicorp. Commanditaire Vennootschap — limited partnership under Dutch/Curacao law. Our local team manages incorporation, ongoing administration, accounting, and compliance so you can focus on commercial objectives instead of paperwork. | H82: 4-6 weeks | I82: Annual audited financials, regulator filings, AML/KYC monitoring, and investor reporting | J82: Established Curacao legal framework familiar to investors, banks, and counterparties | K82: End-to-end Amicorp service: incorporation, registered office, directors, accounting, and reporting | L82: Treaty network and regulatory standing supporting cross-border investment and capital flows | M82: Single point of contact across 30+ jurisdictions for multi-entity group structures | N82: Asset managers launching regulated or private funds | O82: PE/VC sponsors raising committed capital from institutional LPs | P82: Family offices pooling investments across asset classes | Q82: Structured products and securitisation arrangers | R82: Pooled capital with professional management | S82: Investor-friendly structure with familiar legal precedent | T82: Tax-efficient flow-through or treaty-eligible vehicle | U82: Scalable for additional sub-funds or share classes | V82: Investment Fund (AIF) | W82: Civil Law (Dutch) | X82: Full for LPs; unlimited for GP | Y82: CBA / Chamber of Commerce Civil Code of Curaçao | Z82: Yes | AA82: 1 GP + 1 LP | AB82: Tax-transparent Caribbean limited partnership for PE or VC fund structures | AC82: GP unlimited liability; FATF; CBA registration | AE82: M | AG82: O | AI82: N/A | AK82: N/A | AL82: 0 | AM82: M | AO82: N/A | AP82: — | AQ82: M | AS82: N/A | AT82: — | AU82: O | AW82: M | AX82: — | AY82: M | BA82: M | BC82: M | BE82: M | BF82: — | BG82: M | BI82: N/A | BK82: N/A | BM82: N/A | BO82: N/A | BQ82: N/A | BR82: 12000 | BS82: M | BU82: N/A | BW82: N/A | BY82: N/A | CA82: N/A | CB82: 2-8 Basispoints (2,000 USD per month minimum fee) | CC82: O | CE82: N/A | CG82: N/A | CH82: 5000 | CI82: O | CJ82: 2500 | CK82: O | CL82: 1500 | CM82: O | CN82: 1500 | CO82: O | CP82: 400 | CQ82: M | CS82: N/A | CU82: N/A | CW82: N/A | CY82: N/A | DA82: N/A | DB82: USD 100–750/hr (confirm with local office) | DC82: O | DD82: =ROUND(0.075*SUM(AD82,AF82,AH82,AJ82,AL82,AN82,AP82,AR82,AT82,AV82,AX82,AZ82,BB82,BR82,BT82,BV82,BX82,BZ82,CB82,CD82,CF82,CJ82,CL82,CN82,CP82,CR82,CT82,CV82,CX82,CZ82),0) -> 1343 | DE82: Curacao#Fund#Curacao CV | DF82: =A82&"#"&C82&"#"&D82 -> Curacao#Fund#Curacao CV | DG82: =DE82=DF82 -> TRUE
A83: Curacao | B83: Jan Frederik Stembord | C83: Foundation | D83: Curacao SPF | E83: USD | F83: Stichting Particulier Fonds — Curacao private foundation for wealth management. | G83: The Curacao SPF is a fund structure regulated under local law and widely used by international clients of Amicorp. Stichting Particulier Fonds — Curacao private foundation for wealth management. Our local team manages incorporation, ongoing administration, accounting, and compliance so you can focus on commercial objectives instead of paperwork. | H83: 4-6 weeks | I83: Annual audited financials, regulator filings, AML/KYC monitoring, and investor reporting | J83: Established Curacao legal framework familiar to investors, banks, and counterparties | K83: End-to-end Amicorp service: incorporation, registered office, directors, accounting, and reporting | L83: Treaty network and regulatory standing supporting cross-border investment and capital flows | M83: Single point of contact across 30+ jurisdictions for multi-entity group structures | N83: Asset managers launching regulated or private funds | O83: PE/VC sponsors raising committed capital from institutional LPs | P83: Family offices pooling investments across asset classes | Q83: Structured products and securitisation arrangers | R83: Pooled capital with professional management | S83: Investor-friendly structure with familiar legal precedent | T83: Tax-efficient flow-through or treaty-eligible vehicle | U83: Scalable for additional sub-funds or share classes | V83: Foundation | W83: Civil Law (Dutch) | X83: Full (no members) | Y83: Chamber of Commerce Curaçao National Ordinance on Private Foundations (SPF) | Z83: Yes | AA83: N/A (foundation board) | AB83: Private family foundation for wealth preservation and succession planning in the Caribbean | AC83: FATF; substance; limited international recognition vs Liechtenstein/Panama foundation | AD83: 3020 | AE83: M | AG83: O | AI83: N/A | AK83: N/A | AL83: 0 | AM83: M | AO83: N/A | AP83: 2230 | AQ83: M | AS83: N/A | AT83: — | AU83: O | AV83: 2650 | AW83: O | AX83: — | AY83: M | AZ83: 75 | BA83: M | BB83: 100 | BC83: M | BD83: — | BE83: M | BF83: — | BG83: M | BI83: N/A | BK83: N/A | BM83: N/A | BO83: N/A | BQ83: N/A | BS83: N/A | BU83: N/A | BW83: N/A | BY83: N/A | CA83: N/A | CC83: N/A | CE83: N/A | CG83: N/A | CK83: N/A | CM83: N/A | CO83: N/A | CP83: 400 | CQ83: M | CS83: N/A | CU83: N/A | CW83: N/A | CY83: N/A | DA83: N/A | DB83: USD 100–750/hr (confirm with local office) | DC83: O | DD83: =ROUND(0.075*SUM(AD83,AF83,AH83,AJ83,AL83,AN83,AP83,AR83,AT83,AV83,AX83,AZ83,BB83,BR83,BT83,BV83,BX83,BZ83,CB83,CD83,CF83,CJ83,CL83,CN83,CP83,CR83,CT83,CV83,CX83,CZ83),0) -> 636 | DE83: Curacao#Foundation#Curacao SPF | DF83: =A83&"#"&C83&"#"&D83 -> Curacao#Foundation#Curacao SPF | DG83: =DE83=DF83 -> TRUE
